Workbook

Sheet Forecast Q3
B2: 45550 | D2: ="Days = "&(+B2-A24) -> Days = 77 | E2: ="Days = "&(+A25-B2) -> Days = 15 | G2: 0.7 | M2: Weekly Orders
B3: QUARTER ORDERS | C3: CANCELLATIONS | D3: ORDERS PER DAY | E3: FORECAST ORDERS | F3: CURRENT TOTAL | G3: FORECAST TOTAL | H3: B/FWD | I3: TOTAL | J3: TARGET | K3: C/FWD | M3: 45480 | N3: 45487 | O3: 45494 | P3: 45501 | Q3: 45508 | R3: 45515 | S3: 45522 | T3: 45529 | U3: 45536 | V3: 45543 | W3: 45550 | X3: 45557 | Y3: 45564 | AA3: FORECAST 9/9/24 | AB3: FORECAST 15/9/24
A6: Salford | B6: 158 | C6: 2 | D6: =(B6-C6)/($B$2-$A$24) -> 2.025974 | E6: =ROUNDDOWN(D6*($A$25-$B$2),0) -> 30 | F6: ='2024 - Q3'!Q6+'2024 - Q3'!R6 -> 173 | G6: =F6+ROUND(E6*$G$2,0) -> 194 | H6: ='2024 - Q3'!B6 -> 80 | I6: =G6+H6 -> 274 | J6: ='2024 - Q3'!T6 -> 183 | K6: =I6-J6 -> 91 | M6: 13 | N6: 27 | O6: 30 | P6: 40 | Q6: 57 | R6: 65 | S6: 80 | T6: 106 | U6: 118 | V6: 147 | W6: 156 | AA6: 204 | AB6: 183
A7: Bolton | B7: 73 | C7: 8 | D7: =(B7-C7)/($B$2-$A$24) -> 0.84415584 | E7: =ROUNDDOWN(D7*($A$25-$B$2),0) -> 12 | F7: ='2024 - Q3'!Q7+'2024 - Q3'!R7 -> 94 | G7: =F7+ROUND(E7*$G$2,0) -> 102 | H7: ='2024 - Q3'!B7 -> -20 | I7: =G7+H7 -> 82 | J7: ='2024 - Q3'!T7 -> 168 | K7: =I7-J7 -> -86 | M7: 2 | N7: 8 | O7: 14 | P7: 16 | Q7: 25 | R7: 27 | S7: 36 | T7: 47 | U7: 54 | V7: 60 | W7: 65 | AA7: 103 | AB7: 93
A8: Bury | B8: 75 | C8: 3 | D8: =(B8-C8)/($B$2-$A$24) -> 0.93506494 | E8: =ROUNDDOWN(D8*($A$25-$B$2),0) -> 14 | F8: ='2024 - Q3'!Q8+'2024 - Q3'!R8 -> 107 | G8: =F8+ROUND(E8*$G$2,0) -> 117 | H8: ='2024 - Q3'!B8 -> 17 | I8: =G8+H8 -> 134 | J8: ='2024 - Q3'!T8 -> 118 | K8: =I8-J8 -> 16 | M8: 5 | N8: 6 | O8: 9 | P8: 18 | Q8: 30 | R8: 48 | S8: 53 | T8: 57 | U8: 62 | V8: 65 | W8: 72 | AA8: 120 | AB8: 111
A9: Rochdale | B9: 116 | C9: 2 | D9: =(B9-C9)/($B$2-$A$24) -> 1.4805195 | E9: =ROUNDDOWN(D9*($A$25-$B$2),0) -> 22 | F9: ='2024 - Q3'!Q9+'2024 - Q3'!R9 -> 144 | G9: =F9+ROUND(E9*$G$2,0) -> 159 | H9: ='2024 - Q3'!B9 -> 25 | I9: =G9+H9 -> 184 | J9: ='2024 - Q3'!T9 -> 148 | K9: =I9-J9 -> 36 | M9: 6 | N9: 23 | O9: 32 | P9: 42 | Q9: 48 | R9: 54 | S9: 60 | T9: 67 | U9: 73 | V9: 83 | W9: 114 | AA9: 150 | AB9: 159
A10: NORTH CDA | B10: =SUM(B6:B9) -> 422 | C10: =SUM(C6:C9) -> 15 | D10: =SUM(D6:D9) -> 5.2857143 | E10: =SUM(E6:E9) -> 78 | F10: =SUM(F6:F9) -> 518 | G10: =SUM(G6:G9) -> 572 | H10: =SUM(H6:H9) -> 102 | I10: =SUM(I6:I9) -> 674 | ... K10: =SUM(K6:K9) -> 57
A11: Macclesfield | B11: 126 | C11: 9 | D11: =(B11-C11)/($B$2-$A$24) -> 1.5194805 | E11: =ROUNDDOWN(D11*($A$25-$B$2),0) -> 22 | F11: ='2024 - Q3'!Q11+'2024 - Q3'!R11 -> 124 | G11: =F11+ROUND(E11*$G$2,0) -> 139 | H11: ='2024 - Q3'!B11 -> 31 | I11: =G11+H11 -> 170 | J11: ='2024 - Q3'!T11 -> 139 | K11: =I11-J11 -> 31 | M11: 6 | N11: 13 | O11: 17 | P11: 23 | Q11: 29 | R11: 42 | S11: 66 | T11: 77 | U11: 88 | V11: 100 | W11: 117 | AA11: 148 | AB11: 134
A12: Denton | B12: 102 | C12: 8 | D12: =(B12-C12)/($B$2-$A$24) -> 1.2207792 | E12: =ROUNDDOWN(D12*($A$25-$B$2),0) -> 18 | F12: ='2024 - Q3'!Q12+'2024 - Q3'!R12 -> 111 | G12: =F12+ROUND(E12*$G$2,0) -> 124 | H12: ='2024 - Q3'!B12 -> 20 | I12: =G12+H12 -> 144 | J12: ='2024 - Q3'!T12 -> 127 | K12: =I12-J12 -> 17 | M12: 4 | N12: 15 | O12: 16 | P12: 19 | Q12: 28 | R12: 31 | S12: 38 | T12: 46 | U12: 66 | V12: 87 | W12: 94 | AA12: 130 | AB12: 119
A13: Altrincham | B13: 82 | C13: 4 | D13: =(B13-C13)/($B$2-$A$24) -> 1.012987 | E13: =ROUNDDOWN(D13*($A$25-$B$2),0) -> 15 | F13: ='2024 - Q3'!Q13+'2024 - Q3'!R13 -> 89 | G13: =F13+ROUND(E13*$G$2,0) -> 100 | H13: ='2024 - Q3'!B13 -> 47 | I13: =G13+H13 -> 147 | J13: ='2024 - Q3'!T13 -> 107 | K13: =I13-J13 -> 40 | M13: 2 | N13: 3 | O13: 9 | P13: 13 | Q13: 18 | R13: 29 | S13: 38 | T13: 46 | U13: 53 | V13: 65 | W13: 78 | AA13: 104 | AB13: 100
A14: Stockport | B14: 142 | C14: 4 | D14: =(B14-C14)/($B$2-$A$24) -> 1.7922078 | E14: =ROUNDDOWN(D14*($A$25-$B$2),0) -> 26 | F14: ='2024 - Q3'!Q14+'2024 - Q3'!R14 -> 178 | G14: =F14+ROUND(E14*$G$2,0) -> 196 | H14: ='2024 - Q3'!B14 -> 9 | I14: =G14+H14 -> 205 | J14: ='2024 - Q3'!T14 -> 186 | K14: =I14-J14 -> 19 | M14: 14 | N14: 18 | O14: 25 | P14: 35 | Q14: 40 | R14: 58 | S14: 70 | T14: 81 | U14: 91 | V14: 103 | W14: 138 | AA14: 175 | AB14: 183
A15: SOUTH CDA | B15: =SUM(B11:B14) -> 452 | C15: =SUM(C11:C14) -> 25 | D15: =SUM(D11:D14) -> 5.5454545 | E15: =SUM(E11:E14) -> 81 | F15: =SUM(F11:F14) -> 502 | G15: =SUM(G11:G14) -> 559 | H15: =SUM(H11:H14) -> 107 | I15: =SUM(I11:I14) -> 666 | ... K15: =SUM(K11:K14) -> 107
A16: Bradford | B16: 105 | C16: 1 | D16: =(B16-C16)/($B$2-$A$24) -> 1.3506494 | E16: =ROUNDDOWN(D16*($A$25-$B$2),0) -> 20 | F16: ='2024 - Q3'!Q16+'2024 - Q3'!R16 -> 118 | G16: =F16+ROUND(E16*$G$2,0) -> 132 | H16: ='2024 - Q3'!B16 -> 20 | I16: =G16+H16 -> 152 | J16: ='2024 - Q3'!T16 -> 126 | K16: =I16-J16 -> 26 | M16: 1 | N16: 6 | O16: 8 | P16: 20 | Q16: 30 | R16: 35 | S16: 44 | T16: 53 | U16: 67 | V16: 72 | W16: 104 | AA16: 112 | AB16: 126
A17: Huddersfield | B17: 104 | C17: 2 | D17: =(B17-C17)/($B$2-$A$24) -> 1.3246753 | E17: =ROUNDDOWN(D17*($A$25-$B$2),0) -> 19 | F17: ='2024 - Q3'!Q17+'2024 - Q3'!R17 -> 134 | G17: =F17+ROUND(E17*$G$2,0) -> 147 | H17: ='2024 - Q3'!B17 -> 0 | I17: =G17+H17 -> 147 | J17: ='2024 - Q3'!T17 -> 149 | K17: =I17-J17 -> -2 | M17: 5 | N17: 11 | O17: 18 | P17: 22 | Q17: 28 | R17: 42 | S17: 54 | T17: 59 | U17: 71 | V17: 79 | W17: 102 | AA17: 140 | AB17: 136
A18: Silsden | B18: 41 | C18: 2 | D18: =(B18-C18)/($B$2-$A$24) -> 0.50649351 | E18: =ROUNDDOWN(D18*($A$25-$B$2),0) -> 7 | F18: ='2024 - Q3'!Q18+'2024 - Q3'!R18 -> 45 | G18: =F18+ROUND(E18*$G$2,0) -> 50 | H18: ='2024 - Q3'!B18 -> 14 | I18: =G18+H18 -> 64 | J18: ='2024 - Q3'!T18 -> 55 | K18: =I18-J18 -> 9 | M18: 3 | N18: 4 | O18: 5 | P18: 8 | Q18: 14 | R18: 16 | S18: 17 | T18: 19 | U18: 26 | V18: 31 | W18: 39 | AA18: 51 | AB18: 52
A19: WY CDA | B19: =SUM(B16:B18) -> 250 | C19: =SUM(C16:C18) -> 5 | D19: =SUM(D16:D18) -> 3.1818182 | E19: =SUM(E16:E18) -> 46 | F19: =SUM(F16:F18) -> 297 | G19: =SUM(G16:G18) -> 329 | H19: =SUM(H16:H18) -> 34 | I19: =SUM(I16:I18) -> 363 | ... K19: =SUM(K16:K18) -> 33
A22: TOTAL | B22: =B19+B15+B10 -> 1124 | C22: =C19+C15+C10 -> 45 | D22: =D19+D15+D10 -> 14.012987 | E22: =E19+E15+E10 -> 205 | F22: =F19+F15+F10 -> 1317 | G22: =G19+G15+G10 -> 1460 | H22: =H19+H15+H10 -> 243 | I22: =I19+I15+I10 -> 1703 | ... K22: =K19+K15+K10 -> 197 | M22: =SUM(M6:M21) -> 61 | N22: =SUM(N6:N21) -> 134 | O22: =SUM(O6:O21) -> 183 | P22: =SUM(P6:P21) -> 256 | Q22: =SUM(Q6:Q21) -> 347 | R22: =SUM(R6:R21) -> 447 | S22: =SUM(S6:S21) -> 556 | T22: =SUM(T6:T21) -> 658 | ... Y22: =SUM(Y6:Y21) -> 0 | AA22: =SUM(AA6:AA21) -> 1437 | AB22: =SUM(AB6:AB21) -> 1396
A24: 45473 | C24: =B22-C22 -> 1079 | L24: Orders Per Week | M24: =M22 -> 61 | N24: =N22-M22 -> 73 | O24: =O22-N22 -> 49 | P24: =P22-O22 -> 73 | Q24: =Q22-P22 -> 91 | R24: =R22-Q22 -> 100 | S24: =S22-R22 -> 109 | T24: =T22-S22 -> 102 | U24: =U22-T22 -> 111 | ... Y24: =Y22-X22 -> 0
A25: 45565

Sheet 2026 - Q4
A1: REGISTRATIONS (COUNTING) | AC1: Updated | AD1: By
B2: OCT | H2: NOV | N2: DEC | T2: TOTAL
B3: Counting | C3: CLCP Regs | D3: Counting Fleet | E3: Total | F3: Target | H3: Counting | I3: CLCP Regs | J3: Counting Fleet | K3: Total | L3: Target | N3: Counting | O3: CLCP Regs | P3: Counting Fleet | Q3: Total | R3: Target | T3: Counting | U3: Counting Fleet | V3: Total | W3: Target | X3: TO GO | Y3: PER WEEK | Z3: QTR REGS | AA3: TARGET | AB3: REGS v TGT
A4: Bolton | B4: 29 | D4: 1 | E4: =SUM(B4:D4) -> 30 | F4: 27 | G4: =E4/F4 -> 1.1111111 | H4: 14 | K4: =SUM(H4:J4) -> 14 | L4: 33 | M4: =K4/L4 -> 0.42424242 | N4: 6 | Q4: =SUM(N4:P4) -> 6 | R4: 27 | S4: =Q4/R4 -> 0.22222222 | T4: =N4+H4+B4+O4+I4 -> 49 | U4: =P4+J4+D4 -> 1 | V4: =SUM(T4:U4) -> 50 | W4: =F4+L4+R4 -> 87 | X4: =W4-V4 -> 37 | Y4: =ROUND(X4/$Y$24*7,0) -> 3 | Z4: =V4 -> 50 | AA4: =W4 -> 87 | AB4: =Z4/AA4 -> 0.57471264 | AC4: 46306 | AD4: DH
A5: Bury | B5: 22 | D5: 2 | E5: =SUM(B5:D5) -> 24 | F5: 20 | G5: =E5/F5 -> 1.2 | H5: 9 | K5: =SUM(H5:J5) -> 9 | L5: 23 | M5: =K5/L5 -> 0.39130435 | N5: 3 | Q5: =SUM(N5:P5) -> 3 | R5: 19 | S5: =Q5/R5 -> 0.15789474 | T5: =N5+H5+B5+O5+I5 -> 34 | U5: =P5+J5+D5 -> 2 | V5: =SUM(T5:U5) -> 36 | W5: =F5+L5+R5 -> 62 | X5: =W5-V5 -> 26 | Y5: =ROUND(X5/$Y$24*7,0) -> 2 | Z5: =V5 -> 36 | AA5: =W5 -> 62 | AB5: =Z5/AA5 -> 0.58064516 | AC5: 46306 | AD5: TP
A6: Rochdale | B6: 14 | E6: =SUM(B6:D6) -> 14 | F6: 21 | G6: =E6/F6 -> 0.66666667 | H6: 12 | K6: =SUM(H6:J6) -> 12 | L6: 27 | M6: =K6/L6 -> 0.44444444 | N6: 5 | Q6: =SUM(N6:P6) -> 5 | R6: 24 | S6: =Q6/R6 -> 0.20833333 | T6: =N6+H6+B6+O6+I6 -> 31 | U6: =P6+J6+D6 -> 0 | V6: =SUM(T6:U6) -> 31 | W6: =F6+L6+R6 -> 72 | X6: =W6-V6 -> 41 | Y6: =ROUND(X6/$Y$24*7,0) -> 4 | Z6: =V6 -> 31 | AA6: =W6 -> 72 | AB6: =Z6/AA6 -> 0.43055556 | AC6: 46306 | AD6: PF
A7: SQ | B7: 25 | D7: 7 | E7: =SUM(B7:D7) -> 32 | F7: 38 | G7: =E7/F7 -> 0.84210526 | H7: 4 | K7: =SUM(H7:J7) -> 4 | L7: 44 | M7: =K7/L7 -> 0.090909091 | N7: 8 | Q7: =SUM(N7:P7) -> 8 | R7: 34 | S7: =Q7/R7 -> 0.23529412 | T7: =N7+H7+B7+O7+I7 -> 37 | U7: =P7+J7+D7 -> 7 | V7: =SUM(T7:U7) -> 44 | W7: =F7+L7+R7 -> 116 | X7: =W7-V7 -> 72 | Y7: =ROUND(X7/$Y$24*7,0) -> 6 | Z7: =V7 -> 44 | AA7: =W7 -> 116 | AB7: =Z7/AA7 -> 0.37931034 | AC7: 46306 | AD7: DP
A8: NORTH CDA | B8: =SUM(B4:B7) -> 90 | C8: =SUM(C4:C7) -> 0 | D8: =SUM(D4:D7) -> 10 | E8: =SUM(E4:E7) -> 100 | F8: =SUM(F4:F7) -> 106 | G8: =E8/F8 -> 0.94339623 | H8: =SUM(H3:H7) -> 39 | I8: =SUM(I4:I7) -> 0 | J8: =SUM(J4:J7) -> 0 | K8: =SUM(K4:K7) -> 39 | L8: =SUM(L4:L7) -> 127 | M8: =K8/L8 -> 0.30708661 | N8: =SUM(N4:N7) -> 22 | O8: =SUM(O4:O7) -> 0 | P8: =SUM(P4:P7) -> 0 | Q8: =SUM(Q4:Q7) -> 22 | R8: =SUM(R4:R7) -> 104 | S8: =Q8/R8 -> 0.21153846 | T8: =SUM(T4:T7) -> 151 | U8: =SUM(U4:U7) -> 10 | V8: =SUM(V4:V7) -> 161 | W8: =SUM(W4:W7) -> 337 | X8: =SUM(X4:X7) -> 176 | Y8: =ROUND(X8/Y24*7,0) -> 16 | Z8: =SUM(Z4:Z7) -> 161 | AA8: =SUM(AA4:AA7) -> 337 | AB8: =Z8/AA8 -> 0.47774481
A9: Altrincham | B9: 18 | E9: =SUM(B9:D9) -> 18 | F9: 22 | G9: =E9/F9 -> 0.81818182 | H9: 10 | K9: =SUM(H9:J9) -> 10 | L9: 25 | M9: =K9/L9 -> 0.4 | N9: 2 | Q9: =SUM(N9:P9) -> 2 | R9: 23 | S9: =Q9/R9 -> 0.086956522 | T9: =N9+H9+B9+O9+I9 -> 30 | U9: =P9+J9+D9 -> 0 | V9: =SUM(T9:U9) -> 30 | W9: =F9+L9+R9 -> 70 | X9: =W9-V9 -> 40 | Y9: =ROUND(X9/$Y$24*7,0) -> 4 | Z9: =V9 -> 30 | AA9: =W9 -> 70 | AB9: =Z9/AA9 -> 0.42857143 | AC9: 46306 | AD9: NF
A10: Denton | B10: 13 | D10: 6 | E10: =SUM(B10:D10) -> 19 | F10: 24 | G10: =E10/F10 -> 0.79166667 | H10: 11 | K10: =SUM(H10:J10) -> 11 | L10: 28 | M10: =K10/L10 -> 0.39285714 | N10: 5 | Q10: =SUM(N10:P10) -> 5 | R10: 25 | S10: =Q10/R10 -> 0.2 | T10: =N10+H10+B10+O10+I10 -> 29 | U10: =P10+J10+D10 -> 6 | V10: =SUM(T10:U10) -> 35 | W10: =F10+L10+R10 -> 77 | X10: =W10-V10 -> 42 | Y10: =ROUND(X10/$Y$24*7,0) -> 4 | Z10: =V10 -> 35 | AA10: =W10 -> 77 | AB10: =Z10/AA10 -> 0.45454545 | AC10: 46306 | AD10: NF
A11: Macclesfield | B11: 22 | E11: =SUM(B11:D11) -> 22 | F11: 24 | G11: =E11/F11 -> 0.91666667 | H11: 7 | K11: =SUM(H11:J11) -> 7 | L11: 27 | M11: =K11/L11 -> 0.25925926 | N11: 8 | Q11: =SUM(N11:P11) -> 8 | R11: 27 | S11: =Q11/R11 -> 0.2962963 | T11: =N11+H11+B11+O11+I11 -> 37 | U11: =P11+J11+D11 -> 0 | V11: =SUM(T11:U11) -> 37 | W11: =F11+L11+R11 -> 78 | X11: =W11-V11 -> 41 | Y11: =ROUND(X11/$Y$24*7,0) -> 4 | Z11: =V11 -> 37 | AA11: =W11 -> 78 | AB11: =Z11/AA11 -> 0.47435897 | AC11: 46306 | AD11: NF
A12: Stockport | B12: 32 | E12: =SUM(B12:D12) -> 32 | F12: 40 | G12: =E12/F12 -> 0.8 | H12: 11 | K12: =SUM(H12:J12) -> 11 | L12: 46 | M12: =K12/L12 -> 0.23913043 | N12: 3 | Q12: =SUM(N12:P12) -> 3 | R12: 40 | S12: =Q12/R12 -> 0.075 | T12: =N12+H12+B12+O12+I12 -> 46 | U12: =P12+J12+D12 -> 0 | V12: =SUM(T12:U12) -> 46 | W12: =F12+L12+R12 -> 126 | X12: =W12-V12 -> 80 | Y12: =ROUND(X12/$Y$24*7,0) -> 7 | Z12: =V12 -> 46 | AA12: =W12 -> 126 | AB12: =Z12/AA12 -> 0.36507937 | AC12: 46306 | AD12: NF
A13: SOUTH CDA | B13: =SUM(B9:B12) -> 85 | C13: =SUM(C9:C12) -> 0 | D13: =SUM(D9:D12) -> 6 | E13: =SUM(E9:E12) -> 91 | F13: =SUM(F9:F12) -> 110 | G13: =E13/F13 -> 0.82727273 | H13: =SUM(H9:H12) -> 39 | I13: =SUM(I9:I12) -> 0 | J13: =SUM(J9:J12) -> 0 | K13: =SUM(K9:K12) -> 39 | L13: =SUM(L9:L12) -> 126 | M13: =K13/L13 -> 0.30952381 | N13: =SUM(N9:N12) -> 18 | O13: =SUM(O9:O12) -> 0 | P13: =SUM(P9:P12) -> 0 | Q13: =SUM(Q9:Q12) -> 18 | R13: =SUM(R9:R12) -> 115 | S13: =Q13/R13 -> 0.15652174 | T13: =SUM(T9:T12) -> 142 | U13: =SUM(U9:U12) -> 6 | V13: =SUM(V9:V12) -> 148 | W13: =SUM(W9:W12) -> 351 | X13: =SUM(X9:X12) -> 203 | Y13: =ROUND(X13/Y24*7,0) -> 18 | Z13: =SUM(Z9:Z12) -> 148 | AA13: =SUM(AA9:AA12) -> 351 | AB13: =Z13/AA13 -> 0.42165242
A14: Bradford | B14: 11 | D14: 7 | E14: =SUM(B14:D14) -> 18 | F14: 27 | G14: =E14/F14 -> 0.66666667 | H14: 6 | K14: =SUM(H14:J14) -> 6 | L14: 31 | M14: =K14/L14 -> 0.19354839 | N14: 6 | Q14: =SUM(N14:P14) -> 6 | R14: 29 | S14: =Q14/R14 -> 0.20689655 | T14: =N14+H14+B14+O14+I14 -> 23 | U14: =P14+J14+D14 -> 7 | V14: =SUM(T14:U14) -> 30 | W14: =F14+L14+R14 -> 87 | X14: =W14-V14 -> 57 | Y14: =ROUND(X14/$Y$24*7,0) -> 5 | Z14: =V14 -> 30 | AA14: =W14 -> 87 | AB14: =Z14/AA14 -> 0.34482759 | AC14: 46306 | AD14: DH
A15: Huddersfield | B15: 23 | D15: 12 | E15: =SUM(B15:D15) -> 35 | F15: 25 | G15: =E15/F15 -> 1.4 | H15: 15 | J15: 3 | K15: =SUM(H15:J15) -> 18 | L15: 32 | M15: =K15/L15 -> 0.5625 | N15: 10 | P15: 2 | Q15: =SUM(N15:P15) -> 12 | R15: 31 | S15: =Q15/R15 -> 0.38709677 | T15: =N15+H15+B15+O15+I15 -> 48 | U15: =P15+J15+D15 -> 17 | V15: =SUM(T15:U15) -> 65 | W15: =F15+L15+R15 -> 88 | X15: =W15-V15 -> 23 | Y15: =ROUND(X15/$Y$24*7,0) -> 2 | Z15: =V15 -> 65 | AA15: =W15 -> 88 | AB15: =Z15/AA15 -> 0.73863636 | AC15: 46306 | AD15: CM
A16: Silsden | B16: 10 | E16: =SUM(B16:D16) -> 10 | F16: 9 | G16: =E16/F16 -> 1.1111111 | H16: 3 | K16: =SUM(H16:J16) -> 3 | L16: 8 | M16: =K16/L16 -> 0.375 | N16: 3 | Q16: =SUM(N16:P16) -> 3 | R16: 10 | S16: =Q16/R16 -> 0.3 | T16: =N16+H16+B16+O16+I16 -> 16 | U16: =P16+J16+D16 -> 0 | V16: =SUM(T16:U16) -> 16 | W16: =F16+L16+R16 -> 27 | X16: =W16-V16 -> 11 | Y16: =ROUND(X16/$Y$24*7,0) -> 1 | Z16: =V16 -> 16 | AA16: =W16 -> 27 | AB16: =Z16/AA16 -> 0.59259259 | AC16: 46306 | AD16: RM
A17: WY CDA | B17: =SUM(B14:B16) -> 44 | C17: =SUM(C14:C16) -> 0 | D17: =SUM(D14:D16) -> 19 | E17: =SUM(E14:E16) -> 63 | F17: =SUM(F14:F16) -> 61 | G17: =E17/F17 -> 1.0327869 | H17: =SUM(H14:H16) -> 24 | I17: =SUM(I14:I16) -> 0 | J17: =SUM(J14:J16) -> 3 | K17: =SUM(K14:K16) -> 27 | L17: =SUM(L14:L16) -> 71 | M17: =K17/L17 -> 0.38028169 | N17: =SUM(N14:N16) -> 19 | O17: =SUM(O14:O16) -> 0 | P17: =SUM(P14:P16) -> 2 | Q17: =SUM(Q14:Q16) -> 21 | R17: =SUM(R14:R16) -> 70 | S17: =Q17/R17 -> 0.3 | T17: =SUM(T14:T16) -> 87 | U17: =SUM(U14:U16) -> 24 | V17: =SUM(V14:V16) -> 111 | W17: =SUM(W14:W16) -> 202 | X17: =SUM(X14:X16) -> 91 | Y17: =ROUND(X17/Y24*7,0) -> 8 | Z17: =SUM(Z14:Z16) -> 111 | AA17: =SUM(AA14:AA16) -> 202 | AB17: =Z17/AA17 -> 0.54950495
A20: TOTAL | B20: =SUM(B8+B13+B17) -> 219 | C20: =SUM(C8+C13+C17) -> 0 | D20: =SUM(D8+D13+D17) -> 35 | E20: =SUM(E8+E13+E17) -> 254 | F20: =SUM(F8+F13+F17) -> 277 | G20: =E20/F20 -> 0.91696751 | H20: =SUM(H8+H13+H17) -> 102 | I20: =SUM(I8+I13+I17) -> 0 | J20: =SUM(J8+J13+J17) -> 3 | K20: =SUM(K8+K13+K17) -> 105 | L20: =SUM(L8+L13+L17) -> 324 | M20: =K20/L20 -> 0.32407407 | N20: =SUM(N8+N13+N17) -> 59 | O20: =SUM(O8+O13+O17) -> 0 | P20: =SUM(P8+P13+P17) -> 2 | Q20: =SUM(Q8+Q13+Q17) -> 61 | R20: =SUM(R8+R13+R17) -> 289 | S20: =Q20/R20 -> 0.21107266 | T20: =SUM(T8+T13+T17) -> 380 | U20: =SUM(U8+U13+U17) -> 40 | V20: =SUM(V8+V13+V17) -> 420 | W20: =SUM(W8+W13+W17) -> 890 | X20: =SUM(X8+X13+X17) -> 470 | Y20: =ROUND(X20/Y24*7,0) -> 42 | Z20: =Z8+Z13+Z17 -> 420 | AA20: =AA8+AA13+AA17 -> 890 | AB20: =Z20/AA20 -> 0.47191011
Y22: 46387 | AA22: =Z17-AA17 -> -91
Y23: =TODAY() -> 46308
Y24: =Y22-Y23 -> 79
A25: REGISTRATIONS (NON-COUNTING) | S25: Updated | T25: By
B26: OCT | H26: NOV | N26: DEC
B27: Non-Counting Fleet (Reg) | C27: Non-Counting Fleet (Unreg) | D27: Total | E27: Budget | F27: Non-Counting Fleet (Reg) | G27: Non-Counting Fleet (Unreg) | H27: Total | I27: Budget | J27: Non-Counting Fleet (Reg) | K27: Non-Counting Fleet (Unreg) | L27: Total | M27: Budget | O27: Non-Counting Fleet (Reg) | P27: Non-Counting Fleet (Unreg) | Q27: Total | R27: Budget
A28: Salford | B28: 18 | C28: 72 | D28: =SUM(B28:C28) -> 90 | F28: 0 | G28: 55 | H28: =SUM(F28:G28) -> 55 | J28: 0 | K28: 20 | L28: =J28+K28 -> 20 | O28: =J28+F28+B28 -> 18 | P28: =K28+G28+C28 -> 147 | Q28: =P28+O28 -> 165 | R28: =M28+I28+E28 -> 0 | S28: DP | T28: 46308
A29: NORTH CDA | B29: =SUM(B28) -> 18 | C29: =SUM(C28) -> 72 | D29: =SUM(D28) -> 90 | E29: =SUM(E28) -> 0 | F29: =SUM(F28) -> 0 | G29: =SUM(G28) -> 55 | H29: =SUM(H28) -> 55 | I29: =SUM(I28) -> 0 | ... M29: =SUM(M28) -> 0 | O29: =SUM(O28) -> 18 | P29: =SUM(P28) -> 147 | Q29: =SUM(Q28) -> 165 | R29: =SUM(R28) -> 0
A30: Denton | B30: 0 | C30: 20 | D30: =SUM(B30:C30) -> 20 | F30: 0 | G30: 20 | H30: =SUM(F30:G30) -> 20 | J30: 0 | K30: 20 | L30: =K30+J30 -> 20 | O30: =J30+F30+B30 -> 0 | P30: =C30+G30+K30 -> 60 | Q30: =P30+O30 -> 60 | R30: =M30+I30+E30 -> 0 | S30: NF | T30: 46306
A31: SOUTH CDA | B31: =SUM(B30) -> 0 | C31: =SUM(C30) -> 20 | D31: =SUM(D30) -> 20 | E31: =SUM(E30) -> 0 | F31: =SUM(F30) -> 0 | G31: =SUM(G30) -> 20 | H31: =SUM(H30) -> 20 | I31: =SUM(I30) -> 0 | ... M31: =SUM(M30) -> 0 | O31: =SUM(O30) -> 0 | P31: =SUM(P30) -> 60 | Q31: =SUM(Q30) -> 60 | R31: =SUM(R30) -> 0
A32: Bradford | B32: 7 | C32: 18 | D32: =SUM(B32:C32) -> 25 | F32: 0 | G32: 25 | H32: =SUM(F32:G32) -> 25 | J32: 0 | K32: 25 | L32: =K32+J32 -> 25 | O32: =J32+F32+B32 -> 7 | P32: =K32+G32+C32 -> 68 | Q32: =P32+O32 -> 75 | R32: =M32+I32+E32 -> 0 | S32: gb | T32: 46307
A33: Huddersfield | B33: 0 | C33: 0 | D33: =SUM(B33:C33) -> 0 | F33: 0 | G33: 0 | H33: =SUM(F33:G33) -> 0 | J33: 0 | K33: 0 | L33: =K33+J33 -> 0 | O33: =J33+F33+B33 -> 0 | P33: =K33+G33+C33 -> 0 | Q33: =P33+O33 -> 0 | R33: =M33+I33+E33 -> 0
A34: WY CDA | B34: =SUM(B32+B33) -> 7 | C34: =SUM(C32+C33) -> 18 | D34: =SUM(D32+D33) -> 25 | E34: =SUM(E32+E33) -> 0 | F34: =SUM(F32+F33) -> 0 | G34: =SUM(G32+G33) -> 25 | H34: =SUM(H32+H33) -> 25 | I34: =SUM(I32+I33) -> 0 | ... M34: =SUM(M32+M33) -> 0 | O34: =SUM(O32+O33) -> 7 | P34: =SUM(P32+P33) -> 68 | Q34: =SUM(Q32+Q33) -> 75 | R34: =SUM(R32+R33) -> 0
A37: TOTAL | B37: =B34+B31+B29 -> 25 | C37: =C34+C31+C29 -> 110 | D37: =D34+D31+D29 -> 135 | E37: =E34+E31+E29 -> 0 | F37: =F34+F31+F29 -> 0 | G37: =G34+G31+G29 -> 100 | H37: =H34+H31+H29 -> 100 | I37: =I34+I31+I29 -> 0 | ... M37: =M34+M31+M29 -> 0 | O37: =O34+O31+O29 -> 25 | P37: =P34+P31+P29 -> 275 | Q37: =Q34+Q31+Q29 -> 300 | R37: =R34+R31+R29 -> 0
R39: =Q37/R37 -> #DIV/0!
A41: USED COUNTING VOLUME | M41: Updated | N41: By
B42: OCT | E42: NOV | H42: DEC | K42: TOTAL
B43: Counting | C43: Target | E43: Counting | F43: Target | H43: Counting | I43: Target | K43: Counting | L43: Target
A44: Bolton | B44: 22 | C44: 62 | D44: =B44/C44 -> 0.35483871 | F44: 57 | G44: =E44/F44 -> 0 | I44: 41 | J44: =H44/I44 -> 0 | K44: =H44+E44+B44 -> 22 | L44: =I44+F44+C44 -> 160 | M44: GB | N44: 46307
A45: Bury | B45: 16 | C45: 54 | D45: =B45/C45 -> 0.2962963 | F45: 50 | G45: =E45/F45 -> 0 | I45: 36 | J45: =H45/I45 -> 0 | K45: =H45+E45+B45 -> 16 | L45: =I45+F45+C45 -> 140 | M45: GB | N45: 46307
A46: Rochdale | B46: 10 | C46: 50 | D46: =B46/C46 -> 0.2 | F46: 46 | G46: =E46/F46 -> 0 | I46: 33 | J46: =H46/I46 -> 0 | K46: =H46+E46+B46 -> 10 | L46: =I46+F46+C46 -> 129 | M46: GB | N46: 46307
A47: SQ | B47: 27 | C47: 59 | D47: =B47/C47 -> 0.45762712 | F47: 54 | G47: =E47/F47 -> 0 | I47: 39 | J47: =H47/I47 -> 0 | K47: =H47+E47+B47 -> 27 | L47: =I47+F47+C47 -> 152 | M47: GB | N47: 46307
A48: NORTH CDA | B48: =SUM(B44:B47) -> 75 | C48: =SUM(C44:C47) -> 225 | D48: =B48/C48 -> 0.33333333 | E48: =SUM(E44:E47) -> 0 | F48: =SUM(F44:F47) -> 207 | G48: =E48/F48 -> 0 | H48: =SUM(H44:H47) -> 0 | I48: =SUM(I44:I47) -> 149 | J48: =H48/I48 -> 0 | K48: =SUM(K44:K47) -> 75 | L48: =SUM(L44:L47) -> 581
A49: Altrincham | B49: 18 | C49: 50 | D49: =B49/C49 -> 0.36 | F49: 46 | G49: =E49/F49 -> 0 | I49: 33 | J49: =H49/I49 -> 0 | K49: =H49+E49+B49 -> 18 | L49: =I49+F49+C49 -> 129 | M49: NF | N49: 46306
A50: Denton | B50: 13 | C50: 44 | D50: =B50/C50 -> 0.29545455 | E50: 0 | F50: 41 | G50: =E50/F50 -> 0 | H50: 0 | I50: 29 | J50: =H50/I50 -> 0 | K50: =H50+E50+B50 -> 13 | L50: =I50+F50+C50 -> 114 | M50: NF | N50: 46306
A51: Macclesfield | B51: 17 | C51: 47 | D51: =B51/C51 -> 0.36170213 | E51: 0 | F51: 43 | G51: =E51/F51 -> 0 | H51: 0 | I51: 31 | J51: =H51/I51 -> 0 | K51: =H51+E51+B51 -> 17 | L51: =I51+F51+C51 -> 121 | M51: NF | N51: 46306
A52: Stockport | B52: 25 | C52: 90 | D52: =B52/C52 -> 0.27777778 | E52: 0 | F52: 83 | G52: =E52/F52 -> 0 | H52: 0 | I52: 59 | J52: =H52/I52 -> 0 | K52: =H52+E52+B52 -> 25 | L52: =I52+F52+C52 -> 232 | M52: NF | N52: 46306
A53: SOUTH CDA | B53: =SUM(B49:B52) -> 73 | C53: =SUM(C49:C52) -> 231 | D53: =B53/C53 -> 0.31601732 | E53: =SUM(E49:E52) -> 0 | F53: =SUM(F49:F52) -> 213 | G53: =E53/F53 -> 0 | H53: =SUM(H49:H52) -> 0 | I53: =SUM(I49:I52) -> 152 | J53: =H53/I53 -> 0 | K53: =SUM(K49:K52) -> 73 | L53: =SUM(L49:L52) -> 596
A54: Bradford | B54: 26 | C54: 36 | D54: =B54/C54 -> 0.72222222 | F54: 33 | G54: =E54/F54 -> 0 | I54: 24 | J54: =H54/I54 -> 0 | K54: =H54+E54+B54 -> 26 | L54: =I54+F54+C54 -> 93 | M54: GB | N54: 46307
A55: Huddersfield | B55: 14 | C55: 47 | D55: =B55/C55 -> 0.29787234 | F55: 43 | G55: =E55/F55 -> 0 | I55: 31 | J55: =H55/I55 -> 0 | K55: =H55+E55+B55 -> 14 | L55: =I55+F55+C55 -> 121 | M55: GB | N55: 46307
A56: Silsden | B56: 9 | C56: 21 | D56: =B56/C56 -> 0.42857143 | F56: 20 | G56: =E56/F56 -> 0 | I56: 14 | J56: =H56/I56 -> 0 | K56: =H56+E56+B56 -> 9 | L56: =I56+F56+C56 -> 55 | M56: GB | N56: 46307
A57: WY CDA | B57: =SUM(B54:B56) -> 49 | C57: =SUM(C54:C56) -> 104 | D57: =B57/C57 -> 0.47115385 | E57: =SUM(E54:E56) -> 0 | F57: =SUM(F54:F56) -> 96 | G57: =E57/F57 -> 0 | H57: =SUM(H54:H56) -> 0 | I57: =SUM(I54:I56) -> 69 | J57: =H57/I57 -> 0 | K57: =SUM(K54:K56) -> 49 | L57: =SUM(L54:L56) -> 269
A60: TOTAL | B60: =B57+B53+B48 -> 197 | C60: =C57+C53+C48 -> 560 | D60: =B60/C60 -> 0.35178571 | E60: =E57+E53+E48 -> 0 | F60: =F57+F53+F48 -> 516 | G60: =E60/F60 -> 0 | H60: =H57+H53+H48 -> 0 | I60: =I57+I53+I48 -> 370 | J60: =H60/I60 -> 0 | K60: =K57+K53+K48 -> 197 | L60: =L57+L53+L48 -> 1446
A63: CENTRE FLEET (BCH ) | G63: Updated | H63: By
B64: Q4 | E64: Active Orders
B65: Regs | C65: Target
A66: Bolton | C66: 6 | D66: =B66/C66 -> 0 | G66: 46306 | H66: GB
A67: Bury | C67: 4 | D67: =B67/C67 -> 0 | G67: 46306 | H67: GB
A68: Rochdale | C68: 4 | D68: =B68/C68 -> 0 | F68: 1 | G68: 46306 | H68: GB
A69: SQ | C69: 8 | D69: =B69/C69 -> 0 | F69: 13 | G69: 46306 | H69: GB
A70: NORTH CDA | B70: =SUM(B66:B69) -> 0 | C70: =SUM(C66:C69) -> 22 | D70: =B70/C70 -> 0 | F70: =SUM(F66:F69) -> 14
A71: Altrincham | C71: 4 | D71: =B71/C71 -> 0 | G71: 46306 | H71: NF
A72: Denton | B72: 1 | C72: 5 | D72: =B72/C72 -> 0.2 | F72: 2 | G72: 46306 | H72: NF
A73: Macclesfield | C73: 5 | D73: =B73/C73 -> 0 | F73: 1 | G73: 46306 | H73: NF
A74: Stockport | C74: 8 | D74: =B74/C74 -> 0 | F74: 2 | G74: 46306 | H74: NF
A75: SOUTH CDA | B75: =SUM(B71:B74) -> 1 | C75: =SUM(C71:C74) -> 22 | D75: =B75/C75 -> 0.045454545 | F75: =SUM(F71:F74) -> 5
A76: Bradford | B76: 2 | C76: 6 | D76: =B76/C76 -> 0.33333333 | F76: 12 | G76: 46306 | H76: GB
A77: Huddersfield | C77: 6 | D77: =B77/C77 -> 0 | F77: 3 | G77: 46306 | H77: GB
A78: Silsden | C78: 2 | D78: =B78/C78 -> 0 | G78: 46306 | H78: GB
A79: WY CDA | B79: =SUM(B76:B78) -> 2 | C79: =SUM(C76:C78) -> 14 | D79: =B79/C79 -> 0.14285714 | F79: =SUM(F76:F78) -> 15
A82: TOTAL | B82: =B70+B75+B79 -> 3 | C82: =C79+C75+C70 -> 58 | D82: =B82/C82 -> 0.051724138 | F82: =F70+F75+F79 -> 34

Sheet 2026 - Q3
A1: REGISTRATIONS (COUNTING) | AC1: Updated | AD1: By
B2: JULY | H2: AUG | N2: SEPT | T2: TOTAL
B3: Counting | C3: CLCP Regs | D3: Counting Fleet | E3: Total | F3: Target | H3: Counting | I3: CLCP Regs | J3: Counting Fleet | K3: Total | L3: Target | N3: Counting | O3: CLCP Regs | P3: Counting Fleet | Q3: Total | R3: Target | T3: Counting | U3: Counting Fleet | V3: Total | W3: Target | X3: TO GO | Y3: PER WEEK | Z3: QTR REGS | AA3: TARGET | AB3: REGS v TGT | AE3: BOOST VOUCHERS ALLOCATED | AF3: BOOST VOUCHERS USED | AG3: LEFT
A4: Bolton | B4: 39 | E4: =SUM(B4:D4) -> 39 | F4: 24 | G4: =E4/F4 -> 1.625 | H4: 13 | K4: =SUM(H4:J4) -> 13 | L4: 12 | M4: =K4/L4 -> 1.0833333 | N4: 66 | O4: 3 | P4: 1 | Q4: =SUM(N4:P4) -> 70 | R4: 69 | S4: =Q4/R4 -> 1.0144928 | T4: =N4+H4+B4+O4+I4 -> 121 | U4: =P4+J4+D4 -> 1 | V4: =SUM(T4:U4) -> 122 | W4: =F4+L4+R4 -> 105 | X4: =W4-V4 -> -17 | Y4: =ROUND(X4/$Y$24*7,0) -> 9 | Z4: =V4 -> 122 | AA4: =W4 -> 105 | AB4: =Z4/AA4 -> 1.1619048 | AC4: 46295 | AD4: GB | AE4: 25 | AF4: 27 | AG4: =AE4-AF4 -> -2
A5: Bury | B5: 25 | E5: =SUM(B5:D5) -> 25 | F5: 19 | G5: =E5/F5 -> 1.3157895 | H5: 9 | K5: =SUM(H5:J5) -> 9 | L5: 11 | M5: =K5/L5 -> 0.81818182 | N5: 50 | O5: 2 | Q5: =SUM(N5:P5) -> 52 | R5: 47 | S5: =Q5/R5 -> 1.106383 | T5: =N5+H5+B5+O5+I5 -> 86 | U5: =P5+J5+D5 -> 0 | V5: =SUM(T5:U5) -> 86 | W5: =F5+L5+R5 -> 77 | X5: =W5-V5 -> -9 | Y5: =ROUND(X5/$Y$24*7,0) -> 5 | Z5: =V5 -> 86 | AA5: =W5 -> 77 | AB5: =Z5/AA5 -> 1.1168831 | AC5: 46295 | AD5: gb | AE5: 20 | AF5: 20 | AG5: =AE5-AF5 -> 0
A6: Rochdale | B6: 34 | E6: =SUM(B6:D6) -> 34 | F6: 19 | G6: =E6/F6 -> 1.7894737 | H6: 13 | K6: =SUM(H6:J6) -> 13 | L6: 11 | M6: =K6/L6 -> 1.1818182 | N6: 82 | O6: 6 | Q6: =SUM(N6:P6) -> 88 | R6: 55 | S6: =Q6/R6 -> 1.6 | T6: =N6+H6+B6+O6+I6 -> 135 | U6: =P6+J6+D6 -> 0 | V6: =SUM(T6:U6) -> 135 | W6: =F6+L6+R6 -> 85 | X6: =W6-V6 -> -50 | Y6: =ROUND(X6/$Y$24*7,0) -> 27 | Z6: =V6 -> 135 | AA6: =W6 -> 85 | AB6: =Z6/AA6 -> 1.5882353 | AC6: 46295 | AD6: gb | AE6: 20 | AF6: 20 | AG6: =AE6-AF6 -> 0
A7: SQ | B7: 36 | D7: 8 | E7: =SUM(B7:D7) -> 44 | F7: 32 | G7: =E7/F7 -> 1.375 | H7: 14 | J7: 5 | K7: =SUM(H7:J7) -> 19 | L7: 18 | M7: =K7/L7 -> 1.0555556 | N7: 71 | O7: 6 | P7: 11 | Q7: =SUM(N7:P7) -> 88 | R7: 90 | S7: =Q7/R7 -> 0.97777778 | T7: =N7+H7+B7+O7+I7 -> 127 | U7: =P7+J7+D7 -> 24 | V7: =SUM(T7:U7) -> 151 | W7: =F7+L7+R7 -> 140 | X7: =W7-V7 -> -11 | Y7: =ROUND(X7/$Y$24*7,0) -> 6 | Z7: =V7 -> 151 | AA7: =W7 -> 140 | AB7: =Z7/AA7 -> 1.0785714 | AC7: 46295 | AD7: GB | AE7: 35 | AF7: 25 | AG7: =AE7-AF7 -> 10
A8: NORTH CDA | B8: =SUM(B4:B7) -> 134 | C8: =SUM(C4:C7) -> 0 | D8: =SUM(D4:D7) -> 8 | E8: =SUM(E4:E7) -> 142 | F8: =SUM(F4:F7) -> 94 | G8: =E8/F8 -> 1.5106383 | H8: =SUM(H3:H7) -> 49 | I8: =SUM(I4:I7) -> 0 | J8: =SUM(J4:J7) -> 5 | K8: =SUM(K4:K7) -> 54 | L8: =SUM(L4:L7) -> 52 | M8: =K8/L8 -> 1.0384615 | N8: =SUM(N4:N7) -> 269 | O8: =SUM(O4:O7) -> 17 | P8: =SUM(P4:P7) -> 12 | Q8: =SUM(Q4:Q7) -> 298 | R8: =SUM(R4:R7) -> 261 | S8: =Q8/R8 -> 1.1417625 | T8: =SUM(T4:T7) -> 469 | U8: =SUM(U4:U7) -> 25 | V8: =SUM(V4:V7) -> 494 | W8: =SUM(W4:W7) -> 407 | X8: =SUM(X4:X7) -> -87 | Y8: =ROUND(X8/Y24*7,0) -> 47 | Z8: =SUM(Z4:Z7) -> 494 | AA8: =SUM(AA4:AA7) -> 407 | AB8: =Z8/AA8 -> 1.2137592 | AE8: =SUM(AE4:AE7) -> 100 | AF8: =SUM(AF4:AF7) -> 92 | AG8: =SUM(AG4:AG7) -> 8
A9: Altrincham | B9: 27 | E9: =SUM(B9:D9) -> 27 | F9: 19 | G9: =E9/F9 -> 1.4210526 | H9: 13 | K9: =SUM(H9:J9) -> 13 | L9: 11 | M9: =K9/L9 -> 1.1818182 | N9: 36 | O9: 9 | Q9: =SUM(N9:P9) -> 45 | R9: 57 | S9: =Q9/R9 -> 0.78947368 | T9: =N9+H9+B9+O9+I9 -> 85 | U9: =P9+J9+D9 -> 0 | V9: =SUM(T9:U9) -> 85 | W9: =F9+L9+R9 -> 87 | X9: =W9-V9 -> 2 | Y9: =ROUND(X9/$Y$24*7,0) -> -1 | Z9: =V9 -> 85 | AA9: =W9 -> 87 | AB9: =Z9/AA9 -> 0.97701149 | AC9: 46295 | AD9: NF | AE9: 20 | AF9: 11 | AG9: =AE9-AF9 -> 9
A10: Denton | B10: 30 | D10: 4 | E10: =SUM(B10:D10) -> 34 | F10: 19 | G10: =E10/F10 -> 1.7894737 | H10: 21 | J10: 0 | K10: =SUM(H10:J10) -> 21 | L10: 11 | M10: =K10/L10 -> 1.9090909 | N10: 50 | O10: 3 | P10: 3 | Q10: =SUM(N10:P10) -> 56 | R10: 63 | S10: =Q10/R10 -> 0.88888889 | T10: =N10+H10+B10+O10+I10 -> 104 | U10: =P10+J10+D10 -> 7 | V10: =SUM(T10:U10) -> 111 | W10: =F10+L10+R10 -> 93 | X10: =W10-V10 -> -18 | Y10: =ROUND(X10/$Y$24*7,0) -> 10 | Z10: =V10 -> 111 | AA10: =W10 -> 93 | AB10: =Z10/AA10 -> 1.1935484 | AC10: 46295 | AD10: NF | AE10: 20 | AF10: 22 | AG10: =AE10-AF10 -> -2
A11: Macclesfield | B11: 23 | E11: =SUM(B11:D11) -> 23 | F11: 21 | G11: =E11/F11 -> 1.0952381 | H11: 19 | K11: =SUM(H11:J11) -> 19 | L11: 13 | M11: =K11/L11 -> 1.4615385 | N11: 59 | O11: 4 | Q11: =SUM(N11:P11) -> 63 | R11: 62 | S11: =Q11/R11 -> 1.016129 | T11: =N11+H11+B11+O11+I11 -> 105 | U11: =P11+J11+D11 -> 0 | V11: =SUM(T11:U11) -> 105 | W11: =F11+L11+R11 -> 96 | X11: =W11-V11 -> -9 | Y11: =ROUND(X11/$Y$24*7,0) -> 5 | Z11: =V11 -> 105 | AA11: =W11 -> 96 | AB11: =Z11/AA11 -> 1.09375 | AC11: 46295 | AD11: NF | AE11: 20 | AF11: 25 | AG11: =AE11-AF11 -> -5
A12: Stockport | B12: 48 | E12: =SUM(B12:D12) -> 48 | F12: 34 | G12: =E12/F12 -> 1.4117647 | H12: 25 | K12: =SUM(H12:J12) -> 25 | L12: 20 | M12: =K12/L12 -> 1.25 | N12: 82 | Q12: =SUM(N12:P12) -> 82 | R12: 97 | S12: =Q12/R12 -> 0.84536082 | T12: =N12+H12+B12+O12+I12 -> 155 | U12: =P12+J12+D12 -> 0 | V12: =SUM(T12:U12) -> 155 | W12: =F12+L12+R12 -> 151 | X12: =W12-V12 -> -4 | Y12: =ROUND(X12/$Y$24*7,0) -> 2 | Z12: =V12 -> 155 | AA12: =W12 -> 151 | AB12: =Z12/AA12 -> 1.0264901 | AC12: 46295 | AD12: NF | AE12: 35 | AF12: 23 | AG12: =AE12-AF12 -> 12
A13: SOUTH CDA | B13: =SUM(B9:B12) -> 128 | C13: =SUM(C9:C12) -> 0 | D13: =SUM(D9:D12) -> 4 | E13: =SUM(E9:E12) -> 132 | F13: =SUM(F9:F12) -> 93 | G13: =E13/F13 -> 1.4193548 | H13: =SUM(H9:H12) -> 78 | I13: =SUM(I9:I12) -> 0 | J13: =SUM(J9:J12) -> 0 | K13: =SUM(K9:K12) -> 78 | L13: =SUM(L9:L12) -> 55 | M13: =K13/L13 -> 1.4181818 | N13: =SUM(N9:N12) -> 227 | O13: =SUM(O9:O12) -> 16 | P13: =SUM(P9:P12) -> 3 | Q13: =SUM(Q9:Q12) -> 246 | R13: =SUM(R9:R12) -> 279 | S13: =Q13/R13 -> 0.88172043 | T13: =SUM(T9:T12) -> 449 | U13: =SUM(U9:U12) -> 7 | V13: =SUM(V9:V12) -> 456 | W13: =SUM(W9:W12) -> 427 | X13: =SUM(X9:X12) -> -29 | Y13: =ROUND(X13/Y24*7,0) -> 16 | Z13: =SUM(Z9:Z12) -> 456 | AA13: =SUM(AA9:AA12) -> 427 | AB13: =Z13/AA13 -> 1.0679157 | AE13: =SUM(AE9:AE12) -> 95 | AF13: =SUM(AF9:AF12) -> 81 | AG13: =SUM(AG9:AG12) -> 14
A14: Bradford | B14: 26 | D14: 13 | E14: =SUM(B14:D14) -> 39 | F14: 22 | G14: =E14/F14 -> 1.7727273 | H14: 17 | J14: 8 | K14: =SUM(H14:J14) -> 25 | L14: 13 | M14: =K14/L14 -> 1.9230769 | N14: 54 | O14: 7 | P14: 4 | Q14: =SUM(N14:P14) -> 65 | R14: 70 | S14: =Q14/R14 -> 0.92857143 | T14: =N14+H14+B14+O14+I14 -> 104 | U14: =P14+J14+D14 -> 25 | V14: =SUM(T14:U14) -> 129 | W14: =F14+L14+R14 -> 105 | X14: =W14-V14 -> -24 | Y14: =ROUND(X14/$Y$24*7,0) -> 13 | Z14: =V14 -> 129 | AA14: =W14 -> 105 | AB14: =Z14/AA14 -> 1.2285714 | AC14: 46295 | AD14: gb | AE14: 25 | AF14: 17 | AG14: =AE14-AF14 -> 8
A15: Huddersfield | B15: 30 | C15: 0 | D15: 2 | E15: =SUM(B15:D15) -> 32 | F15: 23 | G15: =E15/F15 -> 1.3913043 | H15: 18 | J15: 1 | K15: =SUM(H15:J15) -> 19 | L15: 13 | M15: =K15/L15 -> 1.4615385 | N15: 57 | O15: 5 | P15: 3 | Q15: =SUM(N15:P15) -> 65 | R15: 72 | S15: =Q15/R15 -> 0.90277778 | T15: =N15+H15+B15+O15+I15 -> 110 | U15: =P15+J15+D15 -> 6 | V15: =SUM(T15:U15) -> 116 | W15: =F15+L15+R15 -> 108 | X15: =W15-V15 -> -8 | Y15: =ROUND(X15/$Y$24*7,0) -> 4 | Z15: =V15 -> 116 | AA15: =W15 -> 108 | AB15: =Z15/AA15 -> 1.0740741 | AC15: 46295 | AD15: gb | AE15: 25 | AF15: 23 | AG15: =AE15-AF15 -> 2
A16: Silsden | B16: 8 | E16: =SUM(B16:D16) -> 8 | F16: 8 | G16: =E16/F16 -> 1 | H16: 9 | K16: =SUM(H16:J16) -> 9 | L16: 3 | M16: =K16/L16 -> 3 | N16: 21 | O16: 1 | Q16: =SUM(N16:P16) -> 22 | R16: 23 | S16: =Q16/R16 -> 0.95652174 | T16: =N16+H16+B16+O16+I16 -> 39 | U16: =P16+J16+D16 -> 0 | V16: =SUM(T16:U16) -> 39 | W16: =F16+L16+R16 -> 34 | X16: =W16-V16 -> -5 | Y16: =ROUND(X16/$Y$24*7,0) -> 3 | Z16: =V16 -> 39 | AA16: =W16 -> 34 | AB16: =Z16/AA16 -> 1.1470588 | AC16: 46295 | AD16: gb | AE16: 10 | AF16: 13 | AG16: =AE16-AF16 -> -3
A17: WY CDA | B17: =SUM(B14:B16) -> 64 | C17: =SUM(C14:C16) -> 0 | D17: =SUM(D14:D16) -> 15 | E17: =SUM(E14:E16) -> 79 | F17: =SUM(F14:F16) -> 53 | G17: =E17/F17 -> 1.490566 | H17: =SUM(H14:H16) -> 44 | I17: =SUM(I14:I16) -> 0 | J17: =SUM(J14:J16) -> 9 | K17: =SUM(K14:K16) -> 53 | L17: =SUM(L14:L16) -> 29 | M17: =K17/L17 -> 1.8275862 | N17: =SUM(N14:N16) -> 132 | O17: =SUM(O14:O16) -> 13 | P17: =SUM(P14:P16) -> 7 | Q17: =SUM(Q14:Q16) -> 152 | R17: =SUM(R14:R16) -> 165 | S17: =Q17/R17 -> 0.92121212 | T17: =SUM(T14:T16) -> 253 | U17: =SUM(U14:U16) -> 31 | V17: =SUM(V14:V16) -> 284 | W17: =SUM(W14:W16) -> 247 | X17: =SUM(X14:X16) -> -37 | Y17: =ROUND(X17/Y24*7,0) -> 20 | Z17: =SUM(Z14:Z16) -> 284 | AA17: =SUM(AA14:AA16) -> 247 | AB17: =Z17/AA17 -> 1.1497976 | AE17: =SUM(AE14:AE16) -> 60 | AF17: =SUM(AF14:AF16) -> 53 | AG17: =SUM(AG14:AG16) -> 7
AG18: =AE18-AF18 -> 0
AG19: =AE19-AF19 -> 0
A20: TOTAL | B20: =SUM(B8+B13+B17) -> 326 | C20: =SUM(C8+C13+C17) -> 0 | D20: =SUM(D8+D13+D17) -> 27 | E20: =SUM(E8+E13+E17) -> 353 | F20: =SUM(F8+F13+F17) -> 240 | G20: =E20/F20 -> 1.4708333 | H20: =SUM(H8+H13+H17) -> 171 | I20: =SUM(I8+I13+I17) -> 0 | J20: =SUM(J8+J13+J17) -> 14 | K20: =SUM(K8+K13+K17) -> 185 | L20: =SUM(L8+L13+L17) -> 136 | M20: =K20/L20 -> 1.3602941 | N20: =SUM(N8+N13+N17) -> 628 | O20: =SUM(O8+O13+O17) -> 46 | P20: =SUM(P8+P13+P17) -> 22 | Q20: =SUM(Q8+Q13+Q17) -> 696 | R20: =SUM(R8+R13+R17) -> 705 | S20: =Q20/R20 -> 0.98723404 | T20: =SUM(T8+T13+T17) -> 1171 | U20: =SUM(U8+U13+U17) -> 63 | V20: =SUM(V8+V13+V17) -> 1234 | W20: =SUM(W8+W13+W17) -> 1081 | X20: =SUM(X8+X13+X17) -> -153 | Y20: =ROUND(X20/Y24*7,0) -> 82 | Z20: =Z8+Z13+Z17 -> 1234 | AA20: =AA8+AA13+AA17 -> 1081 | AB20: =Z20/AA20 -> 1.1415356 | AE20: =AE17+AE13+AE8 -> 255 | AF20: =AF17+AF13+AF8 -> 226 | AG20: =AG17+AG13+AG8 -> 29
AE21: =AE20*750 -> 191250 | AF21: =AF20*750 -> 169500 | AG21: =AG20*750 -> 21750
Y22: 46295 | AA22: =Z17-AA17 -> 37
Y23: =TODAY() -> 46308
Y24: =Y22-Y23 -> -13
A25: REGISTRATIONS (NON-COUNTING) | S25: Updated | T25: By
B26: JULY | F26: AUGUST | J26: SEPT | O26: TOTAL
B27: Non-Counting Fleet (Reg) | C27: Non-Counting Fleet (Unreg) | D27: Total | E27: Budget | F27: Non-Counting Fleet (Reg) | G27: Non-Counting Fleet (Unreg) | H27: Total | I27: Budget | J27: Non-Counting Fleet (Reg) | K27: Non-Counting Fleet (Unreg) | L27: Total | M27: Budget | O27: Non-Counting Fleet (Reg) | P27: Non-Counting Fleet (Unreg) | Q27: Total | R27: Budget
A28: Salford | B28: 114 | C28: 0 | D28: =SUM(B28:C28) -> 114 | E28: 126 | F28: 55 | G28: 0 | H28: =SUM(F28:G28) -> 55 | I28: 55 | J28: 232 | K28: 0 | L28: =J28+K28 -> 232 | M28: 240 | O28: =J28+F28+B28 -> 401 | P28: =K28+G28+C28 -> 0 | Q28: =P28+O28 -> 401 | R28: =M28+I28+E28 -> 421 | S28: 46295 | T28: GB
A29: NORTH CDA | B29: =SUM(B28) -> 114 | C29: =SUM(C28) -> 0 | D29: =SUM(D28) -> 114 | E29: =SUM(E28) -> 126 | F29: =SUM(F28) -> 55 | G29: =SUM(G28) -> 0 | H29: =SUM(H28) -> 55 | I29: =SUM(I28) -> 55 | ... M29: =SUM(M28) -> 240 | O29: =SUM(O28) -> 401 | P29: =SUM(P28) -> 0 | Q29: =SUM(Q28) -> 401 | R29: =SUM(R28) -> 421
A30: Denton | B30: 9 | C30: 0 | D30: =SUM(B30:C30) -> 9 | E30: 35 | F30: 31 | G30: 0 | H30: =SUM(F30:G30) -> 31 | I30: 10 | J30: 47 | K30: 30 | L30: =K30+J30 -> 77 | M30: 85 | O30: 82 | P30: 0 | Q30: =P30+O30 -> 82 | R30: =M30+I30+E30 -> 130 | S30: 46295 | T30: NF
A31: SOUTH CDA | B31: =SUM(B30) -> 9 | C31: =SUM(C30) -> 0 | D31: =SUM(D30) -> 9 | E31: =SUM(E30) -> 35 | F31: =SUM(F30) -> 31 | G31: =SUM(G30) -> 0 | H31: =SUM(H30) -> 31 | I31: =SUM(I30) -> 10 | ... M31: =SUM(M30) -> 85 | O31: =SUM(O30) -> 82 | P31: =SUM(P30) -> 0 | Q31: =SUM(Q30) -> 82 | R31: =SUM(R30) -> 130
A32: Bradford | B32: 41 | C32: 0 | D32: =SUM(B32:C32) -> 41 | E32: 58 | F32: 62 | G32: 0 | H32: =SUM(F32:G32) -> 62 | I32: 32 | J32: 91 | K32: 0 | L32: =K32+J32 -> 91 | M32: 91 | O32: =J32+F32+B32 -> 194 | P32: =K32+G32+C32 -> 0 | Q32: =P32+O32 -> 194 | R32: =M32+I32+E32 -> 181 | S32: 46295 | T32: WR
A33: Huddersfield | B33: 4 | C33: 0 | D33: =SUM(B33:C33) -> 4 | F33: 2 | G33: 0 | H33: =SUM(F33:G33) -> 2 | L33: =K33+J33 -> 0 | O33: =J33+F33+B33 -> 6 | P33: =K33+G33+C33 -> 0 | Q33: =P33+O33 -> 6 | R33: =M33+I33+E33 -> 0 | S33: 46293 | T33: CM
A34: WY CDA | B34: =SUM(B32+B33) -> 45 | C34: =SUM(C32+C33) -> 0 | D34: =SUM(D32+D33) -> 45 | E34: =SUM(E32+E33) -> 58 | F34: =SUM(F32+F33) -> 64 | G34: =SUM(G32+G33) -> 0 | H34: =SUM(H32+H33) -> 64 | I34: =SUM(I32+I33) -> 32 | ... M34: =SUM(M32+M33) -> 91 | O34: =SUM(O32+O33) -> 200 | P34: =SUM(P32+P33) -> 0 | Q34: =SUM(Q32+Q33) -> 200 | R34: =SUM(R32+R33) -> 181
A37: TOTAL | B37: =B34+B31+B29 -> 168 | C37: =C34+C31+C29 -> 0 | D37: =D34+D31+D29 -> 168 | E37: =E34+E31+E29 -> 219 | F37: =F34+F31+F29 -> 150 | G37: =G34+G31+G29 -> 0 | H37: =H34+H31+H29 -> 150 | I37: =I34+I31+I29 -> 97 | ... M37: =M34+M31+M29 -> 416 | O37: =O34+O31+O29 -> 683 | P37: =P34+P31+P29 -> 0 | Q37: =Q34+Q31+Q29 -> 683 | R37: =R34+R31+R29 -> 732
R39: =Q37/R37 -> 0.93306011
A41: USED COUNTING VOLUME | M41: Updated | N41: By
B42: JULY | E42: AUG | H42: SEPT | K42: TOTAL
B43: Counting | C43: Target | E43: Counting | F43: Target | H43: Counting | I43: Target | K43: Counting | L43: Target
A44: Bolton | B44: 56 | C44: 63 | D44: =B44/C44 -> 0.88888889 | E44: 59 | F44: 62 | G44: =E44/F44 -> 0.9516129 | H44: 59 | I44: 62 | J44: =H44/I44 -> 0.9516129 | K44: =H44+E44+B44 -> 174 | L44: =I44+F44+C44 -> 187 | M44: 46295 | N44: GB
A45: Bury | B45: 51 | C45: 55 | D45: =B45/C45 -> 0.92727273 | E45: 41 | F45: 54 | G45: =E45/F45 -> 0.75925926 | H45: 43 | I45: 54 | J45: =H45/I45 -> 0.7962963 | K45: =H45+E45+B45 -> 135 | L45: =I45+F45+C45 -> 163 | M45: 46295 | N45: GB
A46: Rochdale | B46: 44 | C46: 51 | D46: =B46/C46 -> 0.8627451 | E46: 36 | F46: 50 | G46: =E46/F46 -> 0.72 | H46: 52 | I46: 50 | J46: =H46/I46 -> 1.04 | K46: =H46+E46+B46 -> 132 | L46: =I46+F46+C46 -> 151 | M46: 46295 | N46: GB
A47: SQ | B47: 61 | C47: 60 | D47: =B47/C47 -> 1.0166667 | E47: 60 | F47: 59 | G47: =E47/F47 -> 1.0169492 | H47: 56 | I47: 59 | J47: =H47/I47 -> 0.94915254 | K47: =H47+E47+B47 -> 177 | L47: =I47+F47+C47 -> 178 | M47: 46295 | N47: GB
A48: NORTH CDA | B48: =SUM(B44:B47) -> 212 | C48: =SUM(C44:C47) -> 229 | D48: =B48/C48 -> 0.92576419 | E48: =SUM(E44:E47) -> 196 | F48: =SUM(F44:F47) -> 225 | G48: =E48/F48 -> 0.87111111 | H48: =SUM(H44:H47) -> 210 | I48: =SUM(I44:I47) -> 225 | J48: =H48/I48 -> 0.93333333 | K48: =SUM(K44:K47) -> 618 | L48: =SUM(L44:L47) -> 679
A49: Altrincham | B49: 62 | C49: 51 | D49: =B49/C49 -> 1.2156863 | E49: 43 | F49: 50 | G49: =E49/F49 -> 0.86 | H49: 50 | I49: 50 | J49: =H49/I49 -> 1 | K49: =H49+E49+B49 -> 155 | L49: =I49+F49+C49 -> 151 | M49: 46295 | N49: NF
A50: Denton | B50: 70 | C50: 45 | D50: =B50/C50 -> 1.5555556 | E50: 53 | F50: 44 | G50: =E50/F50 -> 1.2045455 | H50: 50 | I50: 44 | J50: =H50/I50 -> 1.1363636 | K50: =H50+E50+B50 -> 173 | L50: =I50+F50+C50 -> 133 | M50: 46295 | N50: NF
A51: Macclesfield | B51: 36 | C51: 47 | D51: =B51/C51 -> 0.76595745 | E51: 33 | F51: 46 | G51: =E51/F51 -> 0.7173913 | H51: 53 | I51: 46 | J51: =H51/I51 -> 1.1521739 | K51: =H51+E51+B51 -> 122 | L51: =I51+F51+C51 -> 139 | M51: 46295 | N51: NF
A52: Stockport | B52: 90 | C52: 91 | D52: =B52/C52 -> 0.98901099 | E52: 92 | F52: 89 | G52: =E52/F52 -> 1.0337079 | H52: 98 | I52: 89 | J52: =H52/I52 -> 1.1011236 | K52: =H52+E52+B52 -> 280 | L52: =I52+F52+C52 -> 269 | M52: 46295 | N52: NF
A53: SOUTH CDA | B53: =SUM(B49:B52) -> 258 | C53: =SUM(C49:C52) -> 234 | D53: =B53/C53 -> 1.1025641 | E53: =SUM(E49:E52) -> 221 | F53: =SUM(F49:F52) -> 229 | G53: =E53/F53 -> 0.9650655 | H53: =SUM(H49:H52) -> 251 | I53: =SUM(I49:I52) -> 229 | J53: =H53/I53 -> 1.0960699 | K53: =SUM(K49:K52) -> 730 | L53: =SUM(L49:L52) -> 692
A54: Bradford | B54: 45 | C54: 36 | D54: =B54/C54 -> 1.25 | E54: 58 | F54: 36 | G54: =E54/F54 -> 1.6111111 | H54: 40 | I54: 36 | J54: =H54/I54 -> 1.1111111 | K54: =H54+E54+B54 -> 143 | L54: =I54+F54+C54 -> 108 | M54: 46295 | N54: GB
A55: Huddersfield | B55: 54 | C55: 47 | D55: =B55/C55 -> 1.1489362 | E55: 37 | F55: 46 | G55: =E55/F55 -> 0.80434783 | H55: 46 | I55: 46 | J55: =H55/I55 -> 1 | K55: =H55+E55+B55 -> 137 | L55: =I55+F55+C55 -> 139 | M55: 46295 | N55: GB
A56: Silsden | B56: 23 | C56: 22 | D56: =B56/C56 -> 1.0454545 | E56: 27 | F56: 21 | G56: =E56/F56 -> 1.2857143 | H56: 24 | I56: 21 | J56: =H56/I56 -> 1.1428571 | K56: =H56+E56+B56 -> 74 | L56: =I56+F56+C56 -> 64 | M56: 46295 | N56: GB
A57: WY CDA | B57: =SUM(B54:B56) -> 122 | C57: =SUM(C54:C56) -> 105 | D57: =B57/C57 -> 1.1619048 | E57: =SUM(E54:E56) -> 122 | F57: =SUM(F54:F56) -> 103 | G57: =E57/F57 -> 1.184466 | H57: =SUM(H54:H56) -> 110 | I57: =SUM(I54:I56) -> 103 | J57: =H57/I57 -> 1.0679612 | K57: =SUM(K54:K56) -> 354 | L57: =SUM(L54:L56) -> 311
A60: TOTAL | B60: =B57+B53+B48 -> 592 | C60: =C57+C53+C48 -> 568 | D60: =B60/C60 -> 1.0422535 | E60: =E57+E53+E48 -> 539 | F60: =F57+F53+F48 -> 557 | G60: =E60/F60 -> 0.96768402 | H60: =H57+H53+H48 -> 571 | I60: =I57+I53+I48 -> 557 | J60: =H60/I60 -> 1.0251346 | K60: =K57+K53+K48 -> 1702 | L60: =L57+L53+L48 -> 1682 | M60: =K60/L60 -> 1.0118906
A63: CENTRE FLEET (BCH ) | G63: Updated | H63: By
B64: Q3 | E64: Active Orders
B65: Regs | C65: Target
A66: Bolton | B66: 2 | C66: 7 | D66: =B66/C66 -> 0.28571429 | G66: 46293 | H66: GB
A67: Bury | B67: 0 | C67: 5 | D67: =B67/C67 -> 0 | G67: 46293 | H67: GB
A68: Rochdale | B68: 1 | C68: 6 | D68: =B68/C68 -> 0.16666667 | G68: 46293 | H68: GB
A69: SQ | B69: 3 | C69: 8 | D69: =B69/C69 -> 0.375 | F69: 5 | G69: 46293 | H69: GB
A70: NORTH CDA | B70: =SUM(B66:B69) -> 6 | C70: =SUM(C66:C69) -> 26 | D70: =B70/C70 -> 0.23076923 | F70: =SUM(F66:F69) -> 5
A71: Altrincham | B71: 0 | C71: 6 | D71: =B71/C71 -> 0 | G71: 46295 | H71: NF
A72: Denton | B72: 5 | C72: 5 | D72: =B72/C72 -> 1 | G72: 46295 | H72: NF
A73: Macclesfield | B73: 2 | C73: 5 | D73: =B73/C73 -> 0.4 | F73: 1 | G73: 46295 | H73: NF
A74: Stockport | B74: 0 | C74: 9 | D74: =B74/C74 -> 0 | F74: 1 | G74: 46295 | H74: NF
A75: SOUTH CDA | B75: =SUM(B71:B74) -> 7 | C75: =SUM(C71:C74) -> 25 | D75: =B75/C75 -> 0.28 | F75: =SUM(F71:F74) -> 2
A76: Bradford | B76: 11 | C76: 6 | D76: =B76/C76 -> 1.8333333 | F76: 6 | G76: 46293 | H76: GB
A77: Huddersfield | B77: 4 | C77: 7 | D77: =B77/C77 -> 0.57142857 | G77: 46293 | H77: GB
A78: Silsden | B78: 0 | C78: 2 | D78: =B78/C78 -> 0 | G78: 46293 | H78: GB
A79: WY CDA | B79: =SUM(B76:B78) -> 15 | C79: =SUM(C76:C78) -> 15 | D79: =B79/C79 -> 1 | F79: =SUM(F76:F78) -> 6
A82: TOTAL | B82: =B70+B75+B79 -> 28 | C82: =C79+C75+C70 -> 66 | D82: =B82/C82 -> 0.42424242 | F82: =F70+F75+F79 -> 13

Sheet 2026 - Q2
A3: REGISTRATIONS (COUNTING) | AC3: Updated | AD3: By
B4: APR | G4: MAY | M4: JUNE | T4: TOTAL
B5: Counting | C5: Counting Fleet | D5: Total | E5: Target | G5: Counting | H5: CLCP Regs | I5: Counting Fleet | J5: Total | K5: Target | M5: Counting | N5: CLCP Regs | O5: Counting Fleet | P5: Total | Q5: Target | S5: B/FWD | T5: Counting | U5: Counting Fleet | V5: Total | W5: Target | X5: TO GO | Y5: PER WEEK | Z5: QTR REGS | AA5: TARGET | AB5: REGS v TGT
A6: Bolton | B6: 26 | D6: =SUM(B6:C6) -> 26 | E6: 21 | F6: =D6/E6 -> 1.2380952 | G6: 31 | I6: 1 | J6: =SUM(G6:I6) -> 32 | K6: 27 | L6: =J6/K6 -> 1.1851852 | M6: 42 | N6: 0 | O6: 1 | P6: =SUM(M6:O6) -> 43 | Q6: 48 | R6: =P6/Q6 -> 0.89583333 | T6: =M6+G6+B6+N6+H6 -> 99 | U6: =O6+I6+C6 -> 2 | V6: =SUM(S6:U6) -> 101 | W6: =E6+K6+Q6 -> 96 | X6: =W6-V6 -> -5 | Y6: =ROUND(X6/$Y$26*7,0) -> 0 | Z6: =U6+T6 -> 101 | AA6: =W6 -> 96 | AB6: =(T6+U6)/W6 -> 1.0520833 | AC6: 46203 | AD6: GB
A7: Bury | B7: 23 | D7: =SUM(B7:C7) -> 23 | E7: 15 | F7: =D7/E7 -> 1.5333333 | G7: 27 | I7: 1 | J7: =SUM(G7:I7) -> 28 | K7: 20 | L7: =J7/K7 -> 1.4 | M7: 25 | O7: 1 | P7: =SUM(M7:O7) -> 26 | Q7: 36 | R7: =P7/Q7 -> 0.72222222 | T7: =M7+G7+B7+N7+H7 -> 75 | U7: =O7+I7+C7 -> 2 | V7: =SUM(S7:U7) -> 77 | W7: =E7+K7+Q7 -> 71 | X7: =W7-V7 -> -6 | Y7: =ROUND(X7/$Y$26*7,0) -> 0 | Z7: =U7+T7 -> 77 | AA7: =W7 -> 71 | AB7: =(T7+U7)/W7 -> 1.084507 | AC7: 46203 | AD7: GB
A8: Rochdale | B8: 22 | D8: =SUM(B8:C8) -> 22 | E8: 17 | F8: =D8/E8 -> 1.2941176 | G8: 41 | J8: =SUM(G8:I8) -> 41 | K8: 23 | L8: =J8/K8 -> 1.7826087 | M8: 25 | N8: 2 | P8: =SUM(M8:O8) -> 27 | Q8: 40 | R8: =P8/Q8 -> 0.675 | T8: =M8+G8+B8+N8+H8 -> 90 | U8: =O8+I8+C8 -> 0 | V8: =SUM(S8:U8) -> 90 | W8: =E8+K8+Q8 -> 80 | X8: =W8-V8 -> -10 | Y8: =ROUND(X8/$Y$26*7,0) -> 1 | Z8: =U8+T8 -> 90 | AA8: =W8 -> 80 | AB8: =(T8+U8)/W8 -> 1.125 | AC8: 46203 | AD8: GB
A9: SQ | B9: 43 | C9: 9 | D9: =SUM(B9:C9) -> 52 | E9: 29 | F9: =D9/E9 -> 1.7931034 | G9: 38 | H9: 0 | I9: 7 | J9: =SUM(G9:I9) -> 45 | K9: 37 | L9: =J9/K9 -> 1.2162162 | M9: 43 | N9: 1 | O9: 6 | P9: =SUM(M9:O9) -> 50 | Q9: 60 | R9: =P9/Q9 -> 0.83333333 | T9: =M9+G9+B9+N9+H9 -> 125 | U9: =O9+I9+C9 -> 22 | V9: =SUM(S9:U9) -> 147 | W9: =E9+K9+Q9 -> 126 | X9: =W9-V9 -> -21 | Y9: =ROUND(X9/$Y$26*7,0) -> 1 | Z9: =U9+T9 -> 147 | AA9: =W9 -> 126 | AB9: =(T9+U9)/W9 -> 1.1666667 | AC9: 46203 | AD9: GB
A10: NORTH CDA | B10: =SUM(B6:B9) -> 114 | C10: =SUM(C6:C9) -> 9 | D10: =SUM(D6:D9) -> 123 | E10: =SUM(E6:E9) -> 82 | F10: =D10/E10 -> 1.5 | G10: =SUM(G6:G9) -> 137 | H10: =SUM(H6:H9) -> 0 | I10: =SUM(I6:I9) -> 9 | J10: =SUM(J6:J9) -> 146 | K10: =SUM(K6:K9) -> 107 | L10: =J10/K10 -> 1.364486 | M10: =SUM(M6:M9) -> 135 | N10: =SUM(N6:N9) -> 3 | O10: =SUM(O6:O9) -> 8 | P10: =SUM(P6:P9) -> 146 | Q10: =SUM(Q6:Q9) -> 184 | R10: =P10/Q10 -> 0.79347826 | S10: =SUM(S6:S9) -> 0 | T10: =SUM(T6:T9) -> 389 | U10: =SUM(U6:U9) -> 26 | V10: =SUM(V6:V9) -> 415 | W10: =SUM(W6:W9) -> 373 | X10: =SUM(X6:X9) -> -42 | Y10: =ROUND(X10/Y26*7,0) -> 3 | Z10: =SUM(Z6:Z9) -> 415 | AA10: =SUM(AA6:AA9) -> 373 | AB10: =Z10/AA10 -> 1.1126005
A11: Altrincham | B11: 10 | D11: =SUM(B11:C11) -> 10 | E11: 16 | F11: =D11/E11 -> 0.625 | G11: 31 | J11: =SUM(G11:I11) -> 31 | K11: 21 | L11: =J11/K11 -> 1.4761905 | M11: 32 | P11: =SUM(M11:O11) -> 32 | Q11: 36 | R11: =P11/Q11 -> 0.88888889 | T11: =M11+G11+B11+N11+H11 -> 73 | U11: =O11+I11+C11 -> 0 | V11: =SUM(S11:U11) -> 73 | W11: =E11+K11+Q11 -> 73 | X11: =W11-V11 -> 0 | Y11: =ROUND(X11/$Y$26*7,0) -> 0 | Z11: =U11+T11 -> 73 | AA11: =W11 -> 73 | AB11: =(T11+U11)/W11 -> 1 | AC11: 46204 | AD11: NF
A12: Denton | B12: 27 | C12: 1 | D12: =SUM(B12:C12) -> 28 | E12: 17 | F12: =D12/E12 -> 1.6470588 | G12: 25 | I12: 1 | J12: =SUM(G12:I12) -> 26 | K12: 24 | L12: =J12/K12 -> 1.0833333 | M12: 28 | O12: 5 | P12: =SUM(M12:O12) -> 33 | Q12: 42 | R12: =P12/Q12 -> 0.78571429 | T12: =M12+G12+B12+N12+H12 -> 80 | U12: =O12+I12+C12 -> 7 | V12: =SUM(S12:U12) -> 87 | W12: =E12+K12+Q12 -> 83 | X12: =W12-V12 -> -4 | Y12: =ROUND(X12/$Y$26*7,0) -> 0 | Z12: =U12+T12 -> 87 | AA12: =W12 -> 83 | AB12: =(T12+U12)/W12 -> 1.0481928 | AC12: 46204 | AD12: NF
A13: Macclesfield | B13: 18 | D13: =SUM(B13:C13) -> 18 | E13: 18 | F13: =D13/E13 -> 1 | G13: 26 | J13: =SUM(G13:I13) -> 26 | K13: 23 | L13: =J13/K13 -> 1.1304348 | M13: 39 | P13: =SUM(M13:O13) -> 39 | Q13: 40 | R13: =P13/Q13 -> 0.975 | T13: =M13+G13+B13+N13+H13 -> 83 | U13: =O13+I13+C13 -> 0 | V13: =SUM(S13:U13) -> 83 | W13: =E13+K13+Q13 -> 81 | X13: =W13-V13 -> -2 | Y13: =ROUND(X13/$Y$26*7,0) -> 0 | Z13: =U13+T13 -> 83 | AA13: =W13 -> 81 | AB13: =(T13+U13)/W13 -> 1.0246914 | AC13: 46204 | AD13: NF
A14: Stockport | B14: 30 | D14: =SUM(B14:C14) -> 30 | E14: 30 | F14: =D14/E14 -> 1 | G14: 40 | J14: =SUM(G14:I14) -> 40 | K14: 39 | L14: =J14/K14 -> 1.025641 | M14: 62 | P14: =SUM(M14:O14) -> 62 | Q14: 66 | R14: =P14/Q14 -> 0.93939394 | T14: =M14+G14+B14+N14+H14 -> 132 | U14: =O14+I14+C14 -> 0 | V14: =SUM(S14:U14) -> 132 | W14: =E14+K14+Q14 -> 135 | X14: =W14-V14 -> 3 | Y14: =ROUND(X14/$Y$26*7,0) -> 0 | Z14: =U14+T14 -> 132 | AA14: =W14 -> 135 | AB14: =(T14+U14)/W14 -> 0.97777778 | AC14: 46204 | AD14: NF
A15: SOUTH CDA | B15: =SUM(B11:B14) -> 85 | C15: =SUM(C11:C14) -> 1 | D15: =SUM(D11:D14) -> 86 | E15: =SUM(E11:E14) -> 81 | F15: =D15/E15 -> 1.0617284 | G15: =SUM(G11:G14) -> 122 | H15: =SUM(H11:H14) -> 0 | I15: =SUM(I11:I14) -> 1 | J15: =SUM(J11:J14) -> 123 | K15: =SUM(K11:K14) -> 107 | L15: =J15/K15 -> 1.1495327 | M15: =SUM(M11:M14) -> 161 | N15: =SUM(N11:N14) -> 0 | O15: =SUM(O11:O14) -> 5 | P15: =SUM(P11:P14) -> 166 | Q15: =SUM(Q11:Q14) -> 184 | R15: =P15/Q15 -> 0.90217391 | S15: =SUM(S11:S14) -> 0 | T15: =SUM(T11:T14) -> 368 | U15: =SUM(U11:U14) -> 7 | V15: =SUM(V11:V14) -> 375 | W15: =SUM(W11:W14) -> 372 | X15: =SUM(X11:X14) -> -3 | Y15: =ROUND(X15/Y26*7,0) -> 0 | Z15: =SUM(Z11:Z14) -> 375 | AA15: =SUM(AA11:AA14) -> 372 | AB15: =Z15/AA15 -> 1.0080645
A16: Bradford | B16: 18 | C16: 4 | D16: =SUM(B16:C16) -> 22 | E16: 22 | F16: =D16/E16 -> 1 | G16: 21 | I16: 6 | J16: =SUM(G16:I16) -> 27 | K16: 26 | L16: =J16/K16 -> 1.0384615 | M16: 23 | N16: 4 | O16: 3 | P16: =SUM(M16:O16) -> 30 | Q16: 44 | R16: =P16/Q16 -> 0.68181818 | T16: =M16+G16+B16+N16+H16 -> 66 | U16: =O16+I16+C16 -> 13 | V16: =SUM(S16:U16) -> 79 | W16: =E16+K16+Q16 -> 92 | X16: =W16-V16 -> 13 | Y16: =ROUND(X16/$Y$26*7,0) -> -1 | Z16: =U16+T16 -> 79 | AA16: =W16 -> 92 | AB16: =(T16+U16)/W16 -> 0.85869565 | AC16: 46203 | AD16: GB
A17: Huddersfield | B17: 19 | C17: 6 | D17: =SUM(B17:C17) -> 25 | E17: 21 | F17: =D17/E17 -> 1.1904762 | G17: 37 | H17: 1 | I17: 0 | J17: =SUM(G17:I17) -> 38 | K17: 27 | L17: =J17/K17 -> 1.4074074 | M17: 31 | N17: 1 | O17: 2 | P17: =SUM(M17:O17) -> 34 | Q17: 49 | R17: =P17/Q17 -> 0.69387755 | T17: =M17+G17+B17+N17+H17 -> 89 | U17: =O17+I17+C17 -> 8 | V17: =SUM(S17:U17) -> 97 | W17: =E17+K17+Q17 -> 97 | X17: =W17-V17 -> 0 | Y17: =ROUND(X17/$Y$26*7,0) -> 0 | Z17: =U17+T17 -> 97 | AA17: =W17 -> 97 | AB17: =(T17+U17)/W17 -> 1 | AC17: 46203 | AD17: GB
A18: Silsden | B18: 6 | D18: =SUM(B18:C18) -> 6 | E18: 6 | F18: =D18/E18 -> 1 | G18: 7 | J18: =SUM(G18:I18) -> 7 | K18: 9 | L18: =J18/K18 -> 0.77777778 | M18: 15 | N18: 2 | P18: =SUM(M18:O18) -> 17 | Q18: 13 | R18: =P18/Q18 -> 1.3076923 | T18: =M18+G18+B18+N18+H18 -> 30 | U18: =O18+I18+C18 -> 0 | V18: =SUM(S18:U18) -> 30 | W18: =E18+K18+Q18 -> 28 | X18: =W18-V18 -> -2 | Y18: =ROUND(X18/$Y$26*7,0) -> 0 | Z18: =U18+T18 -> 30 | AA18: =W18 -> 28 | AB18: =(T18+U18)/W18 -> 1.0714286 | AC18: 46203 | AD18: GB
A19: WY CDA | B19: =SUM(B16:B18) -> 43 | C19: =SUM(C16:C18) -> 10 | D19: =SUM(D16:D18) -> 53 | E19: =SUM(E16:E18) -> 49 | F19: =D19/E19 -> 1.0816327 | G19: =SUM(G16:G18) -> 65 | H19: =SUM(H16:H18) -> 1 | I19: =SUM(I16:I18) -> 6 | J19: =SUM(J16:J18) -> 72 | K19: =SUM(K16:K18) -> 62 | L19: =J19/K19 -> 1.1612903 | M19: =SUM(M16:M18) -> 69 | N19: =SUM(N16:N18) -> 7 | O19: =SUM(O16:O18) -> 5 | P19: =SUM(P16:P18) -> 81 | Q19: =SUM(Q16:Q18) -> 106 | R19: =P19/Q19 -> 0.76415094 | S19: =SUM(S16:S18) -> 0 | T19: =SUM(T16:T18) -> 185 | U19: =SUM(U16:U18) -> 21 | V19: =SUM(V16:V18) -> 206 | W19: =SUM(W16:W18) -> 217 | X19: =SUM(X16:X18) -> 11 | Y19: =ROUND(X19/Y26*7,0) -> -1 | Z19: =SUM(Z16:Z18) -> 206 | AA19: =SUM(AA16:AA18) -> 217 | AB19: =Z19/AA19 -> 0.94930876
A22: TOTAL | B22: =B19+B15+B10 -> 242 | C22: =C19+C15+C10 -> 20 | D22: =D19+D15+D10 -> 262 | E22: =E19+E15+E10 -> 212 | F22: =D22/E22 -> 1.2358491 | G22: =G19+G15+G10 -> 324 | H22: =H19+H15+H10 -> 1 | I22: =I19+I15+I10 -> 16 | J22: =J19+J15+J10 -> 341 | K22: =K19+K15+K10 -> 276 | L22: =J22/K22 -> 1.2355072 | M22: =M19+M15+M10 -> 365 | N22: =N19+N15+N10 -> 10 | O22: =O19+O15+O10 -> 18 | P22: =P19+P15+P10 -> 393 | Q22: =Q19+Q15+Q10 -> 474 | R22: =P22/Q22 -> 0.82911392 | S22: =S19+S15+S10 -> 0 | T22: =T19+T15+T10 -> 942 | U22: =U19+U15+U10 -> 54 | V22: =V19+V15+V10 -> 996 | W22: =W19+W15+W10 -> 962 | X22: =X19+X15+X10 -> -34 | Y22: =ROUND(X22/Y26*7,0) -> 2 | Z22: =Z19+Z15+Z10 -> 996 | AA22: =AA19+AA15+AA10 -> 962 | AB22: =(T22+U22)/W22 -> 1.035343
Y24: 46203 | AA24: =AA22-Z22 -> -34
A25: REGISTRATIONS (NON-COUNTING) | S25: Updated | T25: By | Y25: =TODAY() -> 46308
B26: APRIL | F26: MAY | J26: JUNE | O26: TOTAL | Y26: =Y24-Y25 -> -105
B27: Non-Counting Fleet (Reg) | C27: Non-Counting Fleet (Unreg) | D27: Total | E27: Budget | F27: Non-Counting Fleet (Reg) | G27: Non-Counting Fleet (Unreg) | H27: Total | I27: Budget | J27: Non-Counting Fleet (Reg) | K27: Non-Counting Fleet (Unreg) | L27: Total | M27: Budget | O27: Non-Counting Fleet (Reg) | P27: Non-Counting Fleet (Unreg) | Q27: Total | R27: Budget
A28: Salford | B28: 198 | C28: 0 | D28: =SUM(B28:C28) -> 198 | E28: 100 | F28: 128 | G28: 0 | H28: =SUM(F28:G28) -> 128 | I28: 100 | J28: 328 | K28: 0 | L28: 0 | M28: 157 | O28: =J28+F28+B28 -> 654 | P28: =K28+G28+C28 -> 0 | Q28: =P28+O28 -> 654 | R28: =M28+I28+E28 -> 357 | S28: 46203 | T28: GB | Z28: `
A29: NORTH CDA | B29: =SUM(B28) -> 198 | C29: =SUM(C28) -> 0 | D29: =SUM(D28) -> 198 | E29: =SUM(E28) -> 100 | F29: =SUM(F28) -> 128 | G29: =SUM(G28) -> 0 | H29: =SUM(H28) -> 128 | I29: =SUM(I28) -> 100 | ... M29: =SUM(M28) -> 157 | O29: =SUM(O28) -> 654 | P29: =SUM(P28) -> 0 | Q29: =SUM(Q28) -> 654 | R29: =SUM(R28) -> 357
A30: Denton | B30: 27 | D30: =SUM(B30:C30) -> 27 | E30: 20 | F30: 8 | G30: 0 | H30: =SUM(F30:G30) -> 8 | I30: 20 | J30: 45 | K30: 0 | L30: =K30+J30 -> 45 | M30: 47 | O30: =J30+F30+B30 -> 80 | P30: =C30+G30+K30 -> 0 | Q30: =P30+O30 -> 80 | R30: =M30+I30+E30 -> 87 | S30: 46204 | T30: NF
A31: SOUTH CDA | B31: =SUM(B30) -> 27 | C31: =SUM(C30) -> 0 | D31: =SUM(D30) -> 27 | E31: =SUM(E30) -> 20 | F31: =SUM(F30) -> 8 | G31: =SUM(G30) -> 0 | H31: =SUM(H30) -> 8 | I31: =SUM(I30) -> 20 | ... M31: =SUM(M30) -> 47 | O31: =SUM(O30) -> 80 | P31: =SUM(P30) -> 0 | Q31: =SUM(Q30) -> 80 | R31: =SUM(R30) -> 87
A32: Bradford | B32: 13 | C32: 0 | D32: =SUM(B32:C32) -> 13 | E32: 27 | F32: 237 | G32: 0 | H32: =SUM(F32:G32) -> 237 | I32: 45 | J32: 34 | K32: 0 | L32: =K32+J32 -> 34 | M32: 57 | O32: =J32+F32+B32 -> 284 | P32: =K32+G32+C32 -> 0 | Q32: =P32+O32 -> 284 | R32: =M32+I32+E32 -> 129 | S32: 46203 | T32: GB
A33: WY CDA | B33: =SUM(B32) -> 13 | C33: =SUM(C32) -> 0 | D33: =SUM(D32) -> 13 | E33: =SUM(E32) -> 27 | F33: =SUM(F32) -> 237 | G33: =SUM(G32) -> 0 | H33: =SUM(H32) -> 237 | I33: =SUM(I32) -> 45 | ... M33: =SUM(M32) -> 57 | O33: =SUM(O32) -> 284 | P33: =SUM(P32) -> 0 | Q33: =SUM(Q32) -> 284 | R33: =SUM(R32) -> 129
A36: TOTAL | B36: =B33+B31+B29 -> 238 | C36: =C33+C31+C29 -> 0 | D36: =D33+D31+D29 -> 238 | E36: =E33+E31+E29 -> 147 | F36: =F33+F31+F29 -> 373 | G36: =G33+G31+G29 -> 0 | H36: =H33+H31+H29 -> 373 | I36: =I33+I31+I29 -> 165 | ... M36: =M33+M31+M29 -> 261 | O36: =O33+O31+O29 -> 1018 | P36: =P33+P31+P29 -> 0 | Q36: =Q33+Q31+Q29 -> 1018 | R36: =R33+R31+R29 -> 573
R38: =Q36/R36 -> 1.7766143
A40: USED COUNTING VOLUME | M40: Updated | N40: By
B41: APRIL | E41: MAY | H41: JUNE | K41: TOTAL
B42: Counting | C42: Target | E42: Counting | F42: Target | H42: Counting | I42: Target | K42: Counting | L42: Target
A43: Bolton | B43: 68 | C43: 59 | D43: =B43/C43 -> 1.1525424 | E43: 57 | F43: 59 | G43: =E43/F43 -> 0.96610169 | H43: 56 | I43: 62 | J43: =H43/I43 -> 0.90322581 | K43: =H43+E43+B43 -> 181 | L43: =I43+F43+C43 -> 180 | M43: 46203 | N43: GB
A44: Bury | B44: 59 | C44: 51 | D44: =B44/C44 -> 1.1568627 | E44: 42 | F44: 51 | G44: =E44/F44 -> 0.82352941 | H44: 42 | I44: 54 | J44: =H44/I44 -> 0.77777778 | K44: =H44+E44+B44 -> 143 | L44: =I44+F44+C44 -> 156 | M44: 46203 | N44: GB
A45: Rochdale | B45: 49 | C45: 47 | D45: =B45/C45 -> 1.0425532 | E45: 47 | F45: 47 | G45: =E45/F45 -> 1 | H45: 44 | I45: 50 | J45: =H45/I45 -> 0.88 | K45: =H45+E45+B45 -> 140 | L45: =I45+F45+C45 -> 144 | M45: 46203 | N45: GB
A46: SQ | B46: 59 | C46: 56 | D46: =B46/C46 -> 1.0535714 | E46: 52 | F46: 56 | G46: =E46/F46 -> 0.92857143 | H46: 49 | I46: 59 | J46: =H46/I46 -> 0.83050847 | K46: =H46+E46+B46 -> 160 | L46: =I46+F46+C46 -> 171 | M46: 46203 | N46: GB | O46: =K47/L47 -> 0.95852535 | Q46: =K47-L47 -> -27
A47: NORTH CDA | B47: =SUM(B43:B46) -> 235 | C47: =SUM(C43:C46) -> 213 | D47: =B47/C47 -> 1.1032864 | E47: =SUM(E43:E46) -> 198 | F47: =SUM(F43:F46) -> 213 | G47: =E47/F47 -> 0.92957746 | H47: =SUM(H43:H46) -> 191 | I47: =SUM(I43:I46) -> 225 | J47: =H47/I47 -> 0.84888889 | K47: =SUM(K43:K46) -> 624 | L47: =SUM(L43:L46) -> 651
A48: Altrincham | B48: 49 | C48: 47 | D48: =B48/C48 -> 1.0425532 | E48: 41 | F48: 47 | G48: =E48/F48 -> 0.87234043 | H48: 48 | I48: 50 | J48: =H48/I48 -> 0.96 | K48: =H48+E48+B48 -> 138 | L48: =I48+F48+C48 -> 144 | M48: 46204 | N48: NF
A49: Denton | B49: 41 | C49: 42 | D49: =B49/C49 -> 0.97619048 | E49: 42 | F49: 42 | G49: =E49/F49 -> 1 | H49: 39 | I49: 44 | J49: =H49/I49 -> 0.88636364 | K49: =H49+E49+B49 -> 122 | L49: =I49+F49+C49 -> 128 | M49: 46204 | N49: NF
A50: Macclesfield | B50: 44 | C50: 44 | D50: =B50/C50 -> 1 | E50: 44 | F50: 44 | G50: =E50/F50 -> 1 | H50: 49 | I50: 46 | J50: =H50/I50 -> 1.0652174 | K50: =H50+E50+B50 -> 137 | L50: =I50+F50+C50 -> 134 | M50: 46204 | N50: NF
A51: Stockport | B51: 94 | C51: 85 | D51: =B51/C51 -> 1.1058824 | E51: 79 | F51: 85 | G51: =E51/F51 -> 0.92941176 | H51: 98 | I51: 89 | J51: =H51/I51 -> 1.1011236 | K51: =H51+E51+B51 -> 271 | L51: =I51+F51+C51 -> 259 | M51: 46204 | N51: NF | O51: =K52/L52 -> 1.0045113 | Q51: =K52-L52 -> 3
A52: SOUTH CDA | B52: =SUM(B48:B51) -> 228 | C52: =SUM(C48:C51) -> 218 | D52: =B52/C52 -> 1.0458716 | E52: =SUM(E48:E51) -> 206 | F52: =SUM(F48:F51) -> 218 | G52: =E52/F52 -> 0.94495413 | H52: =SUM(H48:H51) -> 234 | I52: =SUM(I48:I51) -> 229 | J52: =H52/I52 -> 1.0218341 | K52: =SUM(K48:K51) -> 668 | L52: =SUM(L48:L51) -> 665
A53: Bradford | B53: 40 | C53: 34 | D53: =B53/C53 -> 1.1764706 | E53: 37 | F53: 34 | G53: =E53/F53 -> 1.0882353 | H53: 40 | I53: 36 | J53: =H53/I53 -> 1.1111111 | K53: =H53+E53+B53 -> 117 | L53: =I53+F53+C53 -> 104 | M53: 46203 | N53: GB
A54: Huddersfield | B54: 32 | C54: 44 | D54: =B54/C54 -> 0.72727273 | E54: 52 | F54: 44 | G54: =E54/F54 -> 1.1818182 | H54: 35 | I54: 46 | J54: =H54/I54 -> 0.76086957 | K54: =H54+E54+B54 -> 119 | L54: =I54+F54+C54 -> 134 | M54: 46203 | N54: GB
A55: Silsden | B55: 20 | C55: 20 | D55: =B55/C55 -> 1 | E55: 20 | F55: 20 | G55: =E55/F55 -> 1 | H55: 31 | I55: 21 | J55: =H55/I55 -> 1.4761905 | K55: =H55+E55+B55 -> 71 | L55: =I55+F55+C55 -> 61 | M55: 46203 | N55: GB | O55: =K56/L56 -> 1.0267559 | Q55: =K56-L56 -> 8
A56: WY CDA | B56: =SUM(B53:B55) -> 92 | C56: =SUM(C53:C55) -> 98 | D56: =B56/C56 -> 0.93877551 | E56: =SUM(E53:E55) -> 109 | F56: =SUM(F53:F55) -> 98 | G56: =E56/F56 -> 1.1122449 | H56: =SUM(H53:H55) -> 106 | I56: =SUM(I53:I55) -> 103 | J56: =H56/I56 -> 1.0291262 | K56: =SUM(K53:K55) -> 307 | L56: =SUM(L53:L55) -> 299
O58: =K59/L59 -> 0.99009288 | Q58: =L59-K59 -> 16 | R58: =Q58/1.2 -> 13.333333
A59: TOTAL | B59: =B56+B52+B47 -> 555 | C59: =C56+C52+C47 -> 529 | D59: =B59/C59 -> 1.0491493 | E59: =E56+E52+E47 -> 513 | F59: =F56+F52+F47 -> 529 | G59: =E59/F59 -> 0.96975425 | H59: =H56+H52+H47 -> 531 | I59: =I56+I52+I47 -> 557 | J59: =H59/I59 -> 0.95332136 | K59: =K56+K52+K47 -> 1599 | L59: =L56+L52+L47 -> 1615

Sheet 2026 - Q1
A3: REGISTRATIONS (COUNTING) | AE3: Updated | AF3: By
B4: JAN | G4: FEB | L4: MAR | S4: TOTAL
B5: Counting | C5: Counting Fleet | D5: Total | E5: Target | G5: Counting | H5: CLCP Regs | I5: Counting Fleet | J5: Total | K5: Target | L5: Counting | M5: CLCP Regs | N5: Counting Fleet | O5: Total | P5: Target | R5: B/FWD | S5: Counting | T5: Counting Fleet | U5: Total | V5: Target | W5: TO GO | X5: PER WEEK | Y5: QTR REGS | Z5: TARGET | AA5: REGS v TGT | AB5: BOOST VOUCHERS ALLOCATED | AC5: BOOST VOUCHERS USED | AD5: LEFT
A6: Bolton | B6: 25 | D6: =SUM(B6:C6) -> 25 | E6: 22 | F6: =D6/E6 -> 1.1363636 | G6: 10 | J6: =SUM(G6:I6) -> 10 | K6: 11 | L6: 80 | O6: =SUM(L6:N6) -> 80 | P6: 90 | Q6: =O6/P6 -> 0.88888889 | S6: =L6+G6+B6+M6+H6 -> 115 | T6: =N6+I6+C6 -> 0 | U6: =SUM(R6:T6) -> 115 | V6: =E6+K6+P6 -> 123 | W6: =V6-U6 -> 8 | X6: =ROUND(W6/$X$26*7,0) -> 0 | Y6: =T6+S6 -> 115 | Z6: =V6 -> 123 | AA6: =(S6+T6)/V6 -> 0.93495935 | AB6: 20 | AC6: 17 | AD6: =AB6-AC6 -> 3 | AE6: 46112 | AF6: gb | AG6: ALL TAXED
A7: Bury | B7: 17 | D7: =SUM(B7:C7) -> 17 | E7: 15 | F7: =D7/E7 -> 1.1333333 | G7: 7 | J7: =SUM(G7:I7) -> 7 | K7: 9 | L7: 71 | O7: =SUM(L7:N7) -> 71 | P7: 64 | Q7: =O7/P7 -> 1.109375 | S7: =L7+G7+B7+M7+H7 -> 95 | T7: =N7+I7+C7 -> 0 | U7: =SUM(R7:T7) -> 95 | V7: =E7+K7+P7 -> 88 | W7: =V7-U7 -> -7 | X7: =ROUND(W7/$X$26*7,0) -> 0 | Y7: =T7+S7 -> 95 | Z7: =V7 -> 88 | AA7: =(S7+T7)/V7 -> 1.0795455 | AB7: 15 | AC7: 15 | AD7: =AB7-AC7 -> 0 | AE7: 46112 | AF7: gb | AG7: ALL TAXED
A8: Rochdale | B8: 28 | D8: =SUM(B8:C8) -> 28 | E8: 16 | F8: =D8/E8 -> 1.75 | G8: 6 | J8: =SUM(G8:I8) -> 6 | K8: 9 | L8: 83 | O8: =SUM(L8:N8) -> 83 | P8: 74 | Q8: =O8/P8 -> 1.1216216 | S8: =L8+G8+B8+M8+H8 -> 117 | T8: =N8+I8+C8 -> 0 | U8: =SUM(R8:T8) -> 117 | V8: =E8+K8+P8 -> 99 | W8: =V8-U8 -> -18 | X8: =ROUND(W8/$X$26*7,0) -> 1 | Y8: =T8+S8 -> 117 | Z8: =V8 -> 99 | AA8: =(S8+T8)/V8 -> 1.1818182 | AB8: 20 | AC8: 20 | AD8: =AB8-AC8 -> 0 | AE8: 46112 | AF8: gb | AG8: ALL TAXED
A9: SQ | B9: 30 | C9: 9 | D9: =SUM(B9:C9) -> 39 | E9: 31 | F9: =D9/E9 -> 1.2580645 | G9: 25 | I9: 2 | J9: =SUM(G9:I9) -> 27 | K9: 15 | L9: 75 | N9: 7 | O9: =SUM(L9:N9) -> 82 | P9: 109 | Q9: =O9/P9 -> 0.75229358 | S9: =L9+G9+B9+M9+H9 -> 130 | T9: =N9+I9+C9 -> 18 | U9: =SUM(R9:T9) -> 148 | V9: =E9+K9+P9 -> 155 | W9: =V9-U9 -> 7 | X9: =ROUND(W9/$X$26*7,0) -> 0 | Y9: =T9+S9 -> 148 | Z9: =V9 -> 155 | AA9: =(S9+T9)/V9 -> 0.95483871 | AB9: 30 | AC9: 30 | AD9: =AB9-AC9 -> 0 | AE9: 46112 | AF9: gb | AG9: ALL TAXED
A10: NORTH CDA | B10: =SUM(B6:B9) -> 100 | C10: =SUM(C6:C9) -> 9 | D10: =SUM(D6:D9) -> 109 | E10: =SUM(E6:E9) -> 84 | F10: =D10/E10 -> 1.297619 | G10: =SUM(G6:G9) -> 48 | H10: =SUM(H6:H9) -> 0 | I10: =SUM(I6:I9) -> 2 | J10: =SUM(J6:J9) -> 50 | K10: =SUM(K6:K9) -> 44 | L10: =SUM(L6:L9) -> 309 | M10: =SUM(M6:M9) -> 0 | N10: =SUM(N6:N9) -> 7 | ... P10: =SUM(P6:P9) -> 337 | Q10: =O10/P10 -> 0.93768546 | R10: =SUM(R6:R9) -> 0 | S10: =SUM(S6:S9) -> 457 | T10: =SUM(T6:T9) -> 18 | U10: =SUM(U6:U9) -> 475 | V10: =SUM(V6:V9) -> 465 | W10: =SUM(W6:W9) -> -10 | X10: =ROUND(W10/X26*7,0) -> 0 | Y10: =SUM(Y6:Y9) -> 475 | Z10: =SUM(Z6:Z9) -> 465 | AA10: =Y10/Z10 -> 1.0215054 | AB10: =SUM(AB6:AB9) -> 85 | AC10: =SUM(AC6:AC9) -> 82 | AD10: =SUM(AD6:AD9) -> 3
A11: Altrincham | B11: 20 | D11: =SUM(B11:C11) -> 20 | E11: 16 | F11: =D11/E11 -> 1.25 | G11: 14 | J11: =SUM(G11:I11) -> 14 | K11: 9 | L11: 58 | N11: 1 | O11: =SUM(L11:N11) -> 59 | P11: 68 | Q11: =O11/P11 -> 0.86764706 | S11: =L11+G11+B11+M11+H11 -> 92 | T11: =N11+I11+C11 -> 1 | U11: =SUM(R11:T11) -> 93 | V11: =E11+K11+P11 -> 93 | W11: =V11-U11 -> 0 | X11: =ROUND(W11/$X$26*7,0) -> 0 | Y11: =T11+S11 -> 93 | Z11: =V11 -> 93 | AA11: =(S11+T11)/V11 -> 1 | AB11: 15 | AC11: 15 | AD11: =AB11-AC11 -> 0 | AE11: 46112 | AF11: NF | AG11: ALL TAXED
A12: Denton | B12: 21 | C12: 2 | D12: =SUM(B12:C12) -> 23 | E12: 17 | F12: =D12/E12 -> 1.3529412 | G12: 16 | I12: 0 | J12: =SUM(G12:I12) -> 16 | K12: 9 | L12: 60 | N12: 3 | O12: =SUM(L12:N12) -> 63 | P12: 76 | Q12: =O12/P12 -> 0.82894737 | S12: =L12+G12+B12+M12+H12 -> 97 | T12: =N12+I12+C12 -> 5 | U12: =SUM(R12:T12) -> 102 | V12: =E12+K12+P12 -> 102 | W12: =V12-U12 -> 0 | X12: =ROUND(W12/$X$26*7,0) -> 0 | Y12: =T12+S12 -> 102 | Z12: =V12 -> 102 | AA12: =(S12+T12)/V12 -> 1 | AB12: 20 | AC12: 20 | AD12: =AB12-AC12 -> 0 | AE12: 46112 | AF12: NF | AG12: ALL TAXED
A13: Macclesfield | B13: 19 | D13: =SUM(B13:C13) -> 19 | E13: 18 | F13: =D13/E13 -> 1.0555556 | G13: 11 | J13: =SUM(G13:I13) -> 11 | K13: 9 | L13: 89 | O13: =SUM(L13:N13) -> 89 | P13: 75 | Q13: =O13/P13 -> 1.1866667 | S13: 119 | T13: =N13+I13+C13 -> 0 | U13: =SUM(R13:T13) -> 119 | V13: =E13+K13+P13 -> 102 | W13: =V13-U13 -> -17 | X13: =ROUND(W13/$X$26*7,0) -> 1 | Y13: =T13+S13 -> 119 | Z13: =V13 -> 102 | AA13: =(S13+T13)/V13 -> 1.1666667 | AB13: 20 | AC13: 20 | AD13: =AB13-AC13 -> 0 | AE13: 46112 | AF13: NF | AG13: ALL TAXED
A14: Stockport | B14: 46 | D14: =SUM(B14:C14) -> 46 | E14: 31 | F14: =D14/E14 -> 1.483871 | G14: 8 | J14: =SUM(G14:I14) -> 8 | K14: 15 | L14: 103 | O14: =SUM(L14:N14) -> 103 | P14: 117 | Q14: =O14/P14 -> 0.88034188 | S14: =L14+G14+B14+M14+H14 -> 157 | T14: =N14+I14+C14 -> 0 | U14: =SUM(R14:T14) -> 157 | V14: =E14+K14+P14 -> 163 | W14: =V14-U14 -> 6 | X14: =ROUND(W14/$X$26*7,0) -> 0 | Y14: =T14+S14 -> 157 | Z14: =V14 -> 163 | AA14: =(S14+T14)/V14 -> 0.96319018 | AB14: 30 | AC14: 30 | AD14: =AB14-AC14 -> 0 | AE14: 46112 | AF14: NF | AG14: ALL TAXED
A15: SOUTH CDA | B15: =SUM(B11:B14) -> 106 | C15: =SUM(C11:C14) -> 2 | D15: =SUM(D11:D14) -> 108 | E15: =SUM(E11:E14) -> 82 | F15: =D15/E15 -> 1.3170732 | G15: =SUM(G11:G14) -> 49 | H15: =SUM(H11:H14) -> 0 | I15: =SUM(I11:I14) -> 0 | J15: =SUM(J11:J14) -> 49 | K15: =SUM(K11:K14) -> 42 | L15: =SUM(L11:L14) -> 310 | M15: =SUM(M11:M14) -> 0 | N15: =SUM(N11:N14) -> 4 | ... P15: =SUM(P11:P14) -> 336 | Q15: =O15/P15 -> 0.93452381 | R15: =SUM(R11:R14) -> 0 | S15: =SUM(S11:S14) -> 465 | T15: =SUM(T11:T14) -> 6 | U15: =SUM(U11:U14) -> 471 | V15: =SUM(V11:V14) -> 460 | W15: =SUM(W11:W14) -> -11 | X15: =ROUND(W15/X26*7,0) -> 0 | Y15: =SUM(Y11:Y14) -> 471 | Z15: =SUM(Z11:Z14) -> 460 | AA15: =Y15/Z15 -> 1.023913 | AB15: =SUM(AB11:AB14) -> 85 | AC15: =SUM(AC11:AC14) -> 85 | AD15: =SUM(AD11:AD14) -> 0
A16: Bradford | B16: 13 | C16: 4 | D16: =SUM(B16:C16) -> 17 | E16: 22 | F16: =D16/E16 -> 0.77272727 | G16: 9 | I16: 2 | J16: =SUM(G16:I16) -> 11 | K16: 9 | L16: 55 | N16: 9 | O16: =SUM(L16:N16) -> 64 | P16: 82 | Q16: =O16/P16 -> 0.7804878 | S16: =L16+G16+B16+M16+H16 -> 77 | T16: =N16+I16+C16 -> 15 | U16: =SUM(R16:T16) -> 92 | V16: =E16+K16+P16 -> 113 | W16: =V16-U16 -> 21 | X16: =ROUND(W16/$X$26*7,0) -> -1 | Y16: =T16+S16 -> 92 | Z16: =V16 -> 113 | AA16: =(S16+T16)/V16 -> 0.81415929 | AB16: 20 | AC16: 20 | AE16: 46112 | AF16: PS | AG16: ALL TAXED
A17: Huddersfield | B17: 23 | C17: 1 | D17: =SUM(B17:C17) -> 24 | E17: 21 | F17: =D17/E17 -> 1.1428571 | G17: 8 | I17: 1 | J17: =SUM(G17:I17) -> 9 | K17: 11 | L17: 86 | N17: 1 | O17: =SUM(L17:N17) -> 87 | P17: 86 | Q17: =O17/P17 -> 1.0116279 | S17: =L17+G17+B17+M17+H17 -> 117 | T17: =N17+I17+C17 -> 3 | U17: =SUM(R17:T17) -> 120 | V17: =E17+K17+P17 -> 118 | W17: =V17-U17 -> -2 | X17: =ROUND(W17/$X$26*7,0) -> 0 | Y17: =T17+S17 -> 120 | Z17: =V17 -> 118 | AA17: =(S17+T17)/V17 -> 1.0169492 | AB17: 20 | AC17: 20 | AD17: =AB17-AC17 -> 0 | AE17: 46112 | AF17: PS | AG17: ALL TAXED
A18: Silsden | B18: 15 | D18: =SUM(B18:C18) -> 15 | E18: 9 | F18: =D18/E18 -> 1.6666667 | G18: 13 | J18: =SUM(G18:I18) -> 13 | K18: 3 | L18: 26 | O18: =SUM(L18:N18) -> 26 | P18: 31 | Q18: =O18/P18 -> 0.83870968 | S18: =L18+G18+B18+M18+H18 -> 54 | T18: =N18+I18+C18 -> 0 | U18: =SUM(R18:T18) -> 54 | V18: =E18+K18+P18 -> 43 | W18: =V18-U18 -> -11 | X18: =ROUND(W18/$X$26*7,0) -> 0 | Y18: =T18+S18 -> 54 | Z18: =V18 -> 43 | AA18: =(S18+T18)/V18 -> 1.255814 | AB18: 5 | AC18: 5 | AD18: =AB18-AC18 -> 0 | AE18: 46112 | AF18: PS | AG18: ALL TAXED
A19: WY CDA | B19: =SUM(B16:B18) -> 51 | C19: =SUM(C16:C18) -> 5 | D19: =SUM(D16:D18) -> 56 | E19: =SUM(E16:E18) -> 52 | F19: =D19/E19 -> 1.0769231 | G19: =SUM(G16:G18) -> 30 | H19: =SUM(H16:H18) -> 0 | I19: =SUM(I16:I18) -> 3 | J19: =SUM(J16:J18) -> 33 | K19: =SUM(K16:K18) -> 23 | L19: =SUM(L16:L18) -> 167 | M19: =SUM(M16:M18) -> 0 | N19: =SUM(N16:N18) -> 10 | ... P19: =SUM(P16:P18) -> 199 | Q19: =O19/P19 -> 0.88944724 | R19: =SUM(R16:R18) -> 0 | S19: =SUM(S16:S18) -> 248 | T19: =SUM(T16:T18) -> 18 | U19: =SUM(U16:U18) -> 266 | V19: =SUM(V16:V18) -> 274 | W19: =SUM(W16:W18) -> 8 | X19: =ROUND(W19/X26*7,0) -> 0 | Y19: =SUM(Y16:Y18) -> 266 | Z19: =SUM(Z16:Z18) -> 274 | AA19: =Y19/Z19 -> 0.97080292 | AB19: =SUM(AB16:AB18) -> 45 | AC19: =SUM(AC16:AC18) -> 45 | AD19: =SUM(AD16:AD18) -> 0
AD20: =AB20-AC20 -> 0
AD21: =AB21-AC21 -> 0
A22: TOTAL | B22: =B19+B15+B10 -> 257 | C22: =C19+C15+C10 -> 16 | D22: =D19+D15+D10 -> 273 | E22: =E19+E15+E10 -> 218 | F22: =D22/E22 -> 1.2522936 | G22: =G19+G15+G10 -> 127 | H22: =H19+H15+H10 -> 0 | I22: =I19+I15+I10 -> 5 | J22: =J19+J15+J10 -> 132 | K22: =K19+K15+K10 -> 109 | L22: =L19+L15+L10 -> 786 | M22: =M19+M15+M10 -> 0 | N22: =N19+N15+N10 -> 21 | ... P22: =P19+P15+P10 -> 872 | Q22: =O22/P22 -> 0.92545872 | R22: =R19+R15+R10 -> 0 | S22: =S19+S15+S10 -> 1170 | T22: =T19+T15+T10 -> 42 | U22: =U19+U15+U10 -> 1212 | V22: =V19+V15+V10 -> 1199 | W22: =W19+W15+W10 -> -13 | X22: =ROUND(W22/X26*7,0) -> 0 | Y22: =Y19+Y15+Y10 -> 1212 | Z22: =Z19+Z15+Z10 -> 1199 | AA22: =(S22+T22)/V22 -> 1.0108424 | AB22: =AB19+AB15+AB10 -> 215 | AC22: =AC19+AC15+AC10 -> 212 | AD22: =AD19+AD15+AD10 -> 3
AB23: =AB22*250 -> 53750 | AC23: =AC22*250 -> 53000 | AD23: =AD22*250 -> 750
X24: 46112 | Z24: =Z22-Y22 -> -13
X25: =TODAY() -> 46308
A26: REGISTRATIONS (NON-COUNTING) | U26: Updated | V26: By | X26: =X24-X25 -> -196
B27: ='2026 - Q1'!B4 -> JAN | F27: ='2026 - Q1'!G4 -> FEB | J27: ='2026 - Q1'!L4 -> MAR | O27: TOTAL
B28: Non-Counting Fleet (Reg) | C28: Non-Counting Fleet (Unreg) | D28: Total | E28: Budget | F28: Non-Counting Fleet (Reg) | G28: Non-Counting Fleet (Unreg) | H28: Total | I28: Budget | J28: Non-Counting Fleet (Reg) | K28: Non-Counting Fleet (Unreg) | L28: Total | M28: Budget | O28: Non-Counting Fleet (Reg) | P28: Non-Counting Fleet (Unreg) | Q28: Total | R28: Budget | Y28: `
A29: Salford | B29: 124 | C29: 0 | D29: =SUM(B29:C29) -> 124 | E29: 134 | F29: 55 | G29: 0 | H29: =SUM(F29:G29) -> 55 | I29: 78 | J29: 230 | K29: 0 | L29: 0 | M29: 315 | O29: =J29+F29+B29 -> 409 | P29: =K29+G29+C29 -> 0 | Q29: =P29+O29 -> 409 | R29: =M29+I29+E29 -> 527 | U29: 46112 | V29: gb | W29: ALL TAXED
A30: NORTH CDA | B30: =SUM(B29) -> 124 | C30: =SUM(C29) -> 0 | D30: =SUM(D29) -> 124 | E30: =SUM(E29) -> 134 | F30: =SUM(F29) -> 55 | G30: =SUM(G29) -> 0 | H30: =SUM(H29) -> 55 | I30: =SUM(I29) -> 78 | ... M30: =SUM(M29) -> 315 | O30: =SUM(O29) -> 409 | P30: =SUM(P29) -> 0 | Q30: =SUM(Q29) -> 409 | R30: =SUM(R29) -> 527
A31: Denton | B31: 29 | C31: 0 | D31: =SUM(B31:C31) -> 29 | E31: 26 | F31: 16 | H31: 20 | I31: 15 | J31: 42 | K31: 0 | L31: =K31+J31 -> 42 | M31: 72 | O31: =J31+F31+B31 -> 87 | P31: =C31+G31+K31 -> 0 | Q31: =P31+O31 -> 87 | R31: =M31+I31+E31 -> 113 | U31: 46112 | V31: NF | W31: ALL TAXED
A32: SOUTH CDA | B32: =SUM(B31) -> 29 | C32: =SUM(C31) -> 0 | D32: =SUM(D31) -> 29 | E32: =SUM(E31) -> 26 | F32: =SUM(F31) -> 16 | G32: =SUM(G31) -> 0 | H32: =SUM(H31) -> 20 | I32: =SUM(I31) -> 15 | ... M32: =SUM(M31) -> 72 | O32: =SUM(O31) -> 87 | P32: =SUM(P31) -> 0 | Q32: =SUM(Q31) -> 87 | R32: =SUM(R31) -> 113
A33: Bradford | B33: 34 | C33: 0 | D33: =SUM(B33:C33) -> 34 | E33: 20 | F33: 89 | G33: 0 | H33: =SUM(F33:G33) -> 89 | I33: 12 | J33: 110 | K33: 0 | L33: =K33+J33 -> 110 | M33: 79 | O33: =J33+F33+B33 -> 233 | P33: =K33+G33+C33 -> 0 | Q33: =P33+O33 -> 233 | R33: =M33+I33+E33 -> 111 | U33: 31/032 | V33: PS | W33: ALL TAXED
A34: WY CDA | B34: =SUM(B33) -> 34 | C34: =SUM(C33) -> 0 | D34: =SUM(D33) -> 34 | E34: =SUM(E33) -> 20 | F34: =SUM(F33) -> 89 | G34: =SUM(G33) -> 0 | H34: =SUM(H33) -> 89 | I34: =SUM(I33) -> 12 | ... M34: =SUM(M33) -> 79 | O34: =SUM(O33) -> 233 | P34: =SUM(P33) -> 0 | Q34: =SUM(Q33) -> 233 | R34: =SUM(R33) -> 111
A37: TOTAL | B37: =B34+B32+B30 -> 187 | C37: =C34+C32+C30 -> 0 | D37: =D34+D32+D30 -> 187 | E37: =E34+E32+E30 -> 180 | F37: =F34+F32+F30 -> 160 | G37: =G34+G32+G30 -> 0 | H37: =H34+H32+H30 -> 164 | I37: =I34+I32+I30 -> 105 | ... M37: =M34+M32+M30 -> 466 | O37: =O34+O32+O30 -> 729 | P37: =P34+P32+P30 -> 0 | Q37: =Q34+Q32+Q30 -> 729 | R37: =R34+R32+R30 -> 751
A41: USED COUNTING VOLUME | N41: By
E42: ='2026 - Q1'!F27 -> FEB | I42: ='2026 - Q1'!J27 -> MAR | L42: TOTAL
B43: Counting | C43: Target | E43: Counting | F43: Target | I43: Counting | J43: Target | L43: Counting | M43: Target
A44: Bolton | B44: 53 | C44: 66 | D44: =B44/C44 -> 0.8030303 | E44: 67 | F44: 61 | G44: =E44/F44 -> 1.0983607 | I44: 58 | J44: 64 | K44: =I44/J44 -> 0.90625 | L44: =I44+E44+B44 -> 178 | M44: =J44+F44+C44 -> 191 | N44: gb | O44: 46112
A45: Bury | B45: 40 | C45: 57 | D45: =B45/C45 -> 0.70175439 | E45: 39 | F45: 53 | G45: =E45/F45 -> 0.73584906 | I45: 47 | J45: 56 | K45: =I45/J45 -> 0.83928571 | L45: =I45+E45+B45 -> 126 | M45: =J45+F45+C45 -> 166 | N45: gb | O45: 46112
A46: Rochdale | B46: 48 | C46: 53 | D46: =B46/C46 -> 0.90566038 | E46: 56 | F46: 50 | G46: =E46/F46 -> 1.12 | I46: 54 | J46: 51 | K46: =I46/J46 -> 1.0588235 | L46: =I46+E46+B46 -> 158 | M46: =J46+F46+C46 -> 154 | N46: gb | O46: 46112
A47: SQ | B47: 55 | C47: 63 | D47: =B47/C47 -> 0.87301587 | E47: 46 | F47: 59 | G47: =E47/F47 -> 0.77966102 | I47: 61 | J47: 61 | K47: =I47/J47 -> 1 | L47: =I47+E47+B47 -> 162 | M47: =J47+F47+C47 -> 183 | N47: gb | O47: 46112
A48: NORTH CDA | B48: =SUM(B44:B47) -> 196 | C48: =SUM(C44:C47) -> 239 | D48: =B48/C48 -> 0.82008368 | E48: =SUM(E44:E47) -> 208 | F48: =SUM(F44:F47) -> 223 | G48: =E48/F48 -> 0.93273543 | I48: =SUM(I44:I47) -> 220 | J48: =SUM(J44:J47) -> 232 | K48: =I48/J48 -> 0.94827586 | L48: =SUM(L44:L47) -> 624 | M48: =SUM(M44:M47) -> 694 | N48: =L48/M48 -> 0.89913545 | P48: =L48-M48 -> -70
A49: Altrincham | B49: 49 | C49: 53 | D49: =B49/C49 -> 0.9245283 | E49: 35 | F49: 50 | G49: =E49/F49 -> 0.7 | I49: 49 | J49: 51 | K49: =I49/J49 -> 0.96078431 | L49: =I49+E49+B49 -> 133 | M49: =J49+F49+C49 -> 154 | N49: NF | O49: 46112
A50: Denton | B50: 33 | C50: 47 | D50: =B50/C50 -> 0.70212766 | E50: 36 | F50: 44 | G50: =E50/F50 -> 0.81818182 | I50: 35 | J50: 45 | K50: =I50/J50 -> 0.77777778 | L50: =I50+E50+B50 -> 104 | M50: =J50+F50+C50 -> 136 | N50: NF | O50: 46112
A51: Macclesfield | B51: 60 | C51: 49 | D51: =B51/C51 -> 1.2244898 | E51: 35 | F51: 46 | G51: =E51/F51 -> 0.76086957 | I51: 56 | J51: 48 | K51: =I51/J51 -> 1.1666667 | L51: =I51+E51+B51 -> 151 | M51: =J51+F51+C51 -> 143 | N51: NF | O51: 46112
A52: Stockport | B52: 64 | C52: 95 | D52: =B52/C52 -> 0.67368421 | E52: 71 | F52: 89 | G52: =E52/F52 -> 0.79775281 | I52: 100 | J52: 92 | K52: =I52/J52 -> 1.0869565 | L52: =I52+E52+B52 -> 235 | M52: =J52+F52+C52 -> 276 | N52: NF | O52: 46112
A53: SOUTH CDA | B53: =SUM(B49:B52) -> 206 | C53: =SUM(C49:C52) -> 244 | D53: =B53/C53 -> 0.8442623 | E53: =SUM(E49:E52) -> 177 | F53: =SUM(F49:F52) -> 229 | G53: =E53/F53 -> 0.77292576 | I53: =SUM(I49:I52) -> 240 | J53: =SUM(J49:J52) -> 236 | K53: =I53/J53 -> 1.0169492 | L53: =SUM(L49:L52) -> 623 | M53: =SUM(M49:M52) -> 709 | N53: =L53/M53 -> 0.8787024 | P53: =L53-M53 -> -86
A54: Bradford | B54: 27 | C54: 38 | D54: =B54/C54 -> 0.71052632 | E54: 31 | F54: 35 | G54: =E54/F54 -> 0.88571429 | I54: 30 | J54: 36 | K54: =I54/J54 -> 0.83333333 | L54: =I54+E54+B54 -> 88 | M54: =J54+F54+C54 -> 109 | N54: PS | O54: 46112
A55: Huddersfield | B55: 38 | C55: 50 | D55: =B55/C55 -> 0.76 | E55: 43 | F55: 46 | G55: =E55/F55 -> 0.93478261 | I55: 41 | J55: 48 | K55: =I55/J55 -> 0.85416667 | L55: =I55+E55+B55 -> 122 | M55: =J55+F55+C55 -> 144 | N55: PS | O55: 46112
A56: Silsden | B56: 27 | C56: 23 | D56: =B56/C56 -> 1.173913 | E56: 25 | F56: 21 | G56: =E56/F56 -> 1.1904762 | I56: 28 | J56: 22 | K56: =I56/J56 -> 1.2727273 | L56: =I56+E56+B56 -> 80 | M56: =J56+F56+C56 -> 66 | N56: PS | O56: 46112
A57: WY CDA | B57: =SUM(B54:B56) -> 92 | C57: =SUM(C54:C56) -> 111 | D57: =B57/C57 -> 0.82882883 | E57: =SUM(E54:E56) -> 99 | F57: =SUM(F54:F56) -> 102 | G57: =E57/F57 -> 0.97058824 | I57: =SUM(I54:I56) -> 99 | J57: =SUM(J54:J56) -> 106 | K57: =I57/J57 -> 0.93396226 | L57: =SUM(L54:L56) -> 290 | M57: =SUM(M54:M56) -> 319 | N57: =L57/M57 -> 0.90909091 | P57: =L57-M57 -> -29
A60: TOTAL | B60: =B57+B53+B48 -> 494 | C60: =C57+C53+C48 -> 594 | D60: =B60/C60 -> 0.83164983 | E60: =E57+E53+E48 -> 484 | F60: =F57+F53+F48 -> 554 | G60: =E60/F60 -> 0.87364621 | I60: =I57+I53+I48 -> 559 | J60: =J57+J53+J48 -> 574 | K60: =I60/J60 -> 0.9738676 | L60: =L57+L53+L48 -> 1537 | M60: =M57+M53+M48 -> 1722 | N60: =L60/M60 -> 0.89256678 | P60: =M60-L60 -> 185 | Q60: =P60/1.2 -> 154.16667

Sheet 2025 - Q4
A3: REGISTRATIONS (COUNTING) | AE3: Updated | AF3: By
C4: OCT | H4: NOV | N4: DEC | V4: TOTAL
B5: B/FWD | C5: Counting | D5: Counting Fleet | E5: Total | F5: Target | H5: Counting | I5: CLCP Regs | J5: Counting Fleet | K5: Total | L5: Target | N5: Counting | O5: CLCP Regs | P5: Double Counters | Q5: Counting Fleet | R5: Total | S5: Target | U5: B/FWD | V5: Counting | W5: Counting Fleet | X5: Total | Y5: Target | Z5: TO GO | AA5: PER WEEK | AB5: QTR REGS | AC5: TARGET | AD5: REGS v TGT
A6: Bolton | C6: 24 | E6: =SUM(C6:D6) -> 24 | F6: 31 | G6: =E6/F6 -> 0.77419355 | H6: 26 | I6: 4 | K6: =SUM(H6:J6) -> 30 | L6: 29 | M6: =K6/L6 -> 1.0344828 | N6: 21 | O6: 2 | R6: =SUM(N6:Q6) -> 23 | S6: 30 | T6: =R6/S6 -> 0.76666667 | V6: =N6+H6+C6+O6+P6+I6 -> 77 | W6: =Q6+J6+D6 -> 0 | X6: =SUM(U6:W6) -> 77 | Y6: =S6+L6+F6 -> 90 | Z6: =Y6-X6 -> 13 | AA6: =ROUND(Z6/$AA$26*7,0) -> 0 | AB6: =W6+V6 -> 77 | AC6: =Y6 -> 90 | AD6: =(V6+W6)/Y6 -> 0.85555556 | AE6: 46024 | AF6: gb
A7: Bury | C7: 26 | E7: =SUM(C7:D7) -> 26 | F7: 26 | G7: =E7/F7 -> 1 | H7: 20 | I7: 3 | K7: =SUM(H7:J7) -> 23 | L7: 26 | M7: =K7/L7 -> 0.88461538 | N7: 13 | O7: 1 | R7: =SUM(N7:Q7) -> 14 | S7: 25 | T7: =R7/S7 -> 0.56 | V7: =N7+H7+C7+O7+P7+I7 -> 63 | W7: =Q7+J7+D7 -> 0 | X7: =SUM(U7:W7) -> 63 | Y7: =S7+L7+F7 -> 77 | Z7: =Y7-X7 -> 14 | AA7: =ROUND(Z7/$AA$26*7,0) -> 0 | AB7: =W7+V7 -> 63 | AC7: =Y7 -> 77 | AD7: =(V7+W7)/Y7 -> 0.81818182 | AE7: 46024 | AF7: gb
A8: Rochdale | C8: 24 | D8: 2 | E8: =SUM(C8:D8) -> 26 | F8: 35 | G8: =E8/F8 -> 0.74285714 | H8: 14 | I8: 3 | K8: =SUM(H8:J8) -> 17 | L8: 31 | M8: =K8/L8 -> 0.5483871 | N8: 18 | O8: 1 | R8: =SUM(N8:Q8) -> 19 | S8: 30 | T8: =R8/S8 -> 0.63333333 | V8: =N8+H8+C8+O8+P8+I8 -> 60 | W8: =Q8+J8+D8 -> 2 | X8: =SUM(U8:W8) -> 62 | Y8: =S8+L8+F8 -> 96 | Z8: =Y8-X8 -> 34 | AA8: =ROUND(Z8/$AA$26*7,0) -> -1 | AB8: =W8+V8 -> 62 | AC8: =Y8 -> 96 | AD8: =(V8+W8)/Y8 -> 0.64583333 | AE8: 46024 | AF8: gb
A9: SQ | C9: 49 | D9: 6 | E9: =SUM(C9:D9) -> 55 | F9: 40 | G9: =E9/F9 -> 1.375 | H9: 37 | I9: 6 | K9: =SUM(H9:J9) -> 43 | L9: 38 | M9: =K9/L9 -> 1.1315789 | N9: 36 | O9: 3 | R9: =SUM(N9:Q9) -> 39 | S9: 39 | T9: =R9/S9 -> 1 | V9: =N9+H9+C9+O9+P9+I9 -> 131 | W9: =Q9+J9+D9 -> 6 | X9: =SUM(U9:W9) -> 137 | Y9: =S9+L9+F9 -> 117 | Z9: =Y9-X9 -> -20 | AA9: =ROUND(Z9/$AA$26*7,0) -> 0 | AB9: =W9+V9 -> 137 | AC9: =Y9 -> 117 | AD9: =(V9+W9)/Y9 -> 1.1709402 | AE9: 46024 | AF9: gb
A10: NORTH CDA | B10: =SUM(B6:B9) -> 0 | C10: =SUM(C6:C9) -> 123 | D10: =SUM(D6:D9) -> 8 | E10: =SUM(E6:E9) -> 131 | F10: =SUM(F6:F9) -> 132 | G10: =E10/F10 -> 0.99242424 | H10: =SUM(H6:H9) -> 97 | I10: =SUM(I6:I9) -> 16 | J10: =SUM(J6:J9) -> 0 | K10: =SUM(K6:K9) -> 113 | L10: =SUM(L6:L9) -> 124 | M10: =K10/L10 -> 0.91129032 | N10: =SUM(N6:N9) -> 88 | O10: =SUM(O6:O9) -> 7 | P10: =SUM(P6:P9) -> 0 | Q10: =SUM(Q6:Q9) -> 0 | R10: =SUM(R6:R9) -> 95 | S10: =SUM(S6:S9) -> 124 | T10: =R10/S10 -> 0.76612903 | U10: =SUM(U6:U9) -> 0 | V10: =SUM(V6:V9) -> 331 | W10: =SUM(W6:W9) -> 8 | X10: =SUM(X6:X9) -> 339 | Y10: =SUM(Y6:Y9) -> 380 | Z10: =SUM(Z6:Z9) -> 41 | AA10: =ROUND(Z10/$AA$26*7,0) -> -1 | AB10: =SUM(AB6:AB9) -> 339 | AC10: =SUM(AC6:AC9) -> 380 | AD10: =AB10/AC10 -> 0.89210526
A11: Altrincham | C11: 23 | E11: =SUM(C11:D11) -> 23 | F11: 30 | G11: =E11/F11 -> 0.76666667 | H11: 18 | I11: 4 | K11: =SUM(H11:J11) -> 22 | L11: 24 | M11: =K11/L11 -> 0.91666667 | N11: 17 | O11: 1 | R11: =SUM(N11:Q11) -> 18 | S11: 22 | T11: =R11/S11 -> 0.81818182 | V11: =N11+H11+C11+O11+P11+I11 -> 63 | W11: =Q11+J11+D11 -> 0 | X11: =SUM(U11:W11) -> 63 | Y11: =S11+L11+F11 -> 76 | Z11: =Y11-X11 -> 13 | AA11: =ROUND(Z11/$AA$26*7,0) -> 0 | AB11: =W11+V11 -> 63 | AC11: =Y11 -> 76 | AD11: =(V11+W11)/Y11 -> 0.82894737 | AE11: 46022 | AF11: NF
A12: Denton | C12: 18 | D12: 2 | E12: =SUM(C12:D12) -> 20 | F12: 29 | G12: =E12/F12 -> 0.68965517 | H12: 41 | I12: 4 | K12: =SUM(H12:J12) -> 45 | L12: 30 | M12: =K12/L12 -> 1.5 | N12: 16 | O12: 3 | R12: =SUM(N12:Q12) -> 19 | S12: 28 | T12: =R12/S12 -> 0.67857143 | V12: =N12+H12+C12+O12+P12+I12 -> 82 | W12: =Q12+J12+D12 -> 2 | X12: =SUM(U12:W12) -> 84 | Y12: =S12+L12+F12 -> 87 | Z12: =Y12-X12 -> 3 | AA12: =ROUND(Z12/$AA$26*7,0) -> 0 | AB12: =W12+V12 -> 84 | AC12: =Y12 -> 87 | AD12: =(V12+W12)/Y12 -> 0.96551724 | AE12: 46022 | AF12: NF
A13: Macclesfield | C13: 16 | E13: =SUM(C13:D13) -> 16 | F13: 34 | G13: =E13/F13 -> 0.47058824 | H13: 27 | I13: 4 | K13: =SUM(H13:J13) -> 31 | L13: 29 | M13: =K13/L13 -> 1.0689655 | N13: 16 | O13: 1 | R13: =SUM(N13:Q13) -> 17 | S13: 27 | T13: =R13/S13 -> 0.62962963 | V13: =N13+H13+C13+O13+P13+I13 -> 64 | W13: =Q13+J13+D13 -> 0 | X13: =SUM(U13:W13) -> 64 | Y13: =S13+L13+F13 -> 90 | Z13: =Y13-X13 -> 26 | AA13: =ROUND(Z13/$AA$26*7,0) -> -1 | AB13: =W13+V13 -> 64 | AC13: =Y13 -> 90 | AD13: =(V13+W13)/Y13 -> 0.71111111 | AE13: 46022 | AF13: NF
A14: Stockport | C14: 40 | E14: =SUM(C14:D14) -> 40 | F14: 43 | G14: =E14/F14 -> 0.93023256 | H14: 36 | I14: 4 | K14: =SUM(H14:J14) -> 40 | L14: 43 | M14: =K14/L14 -> 0.93023256 | N14: 32 | O14: 2 | R14: =SUM(N14:Q14) -> 34 | S14: 42 | T14: =R14/S14 -> 0.80952381 | V14: =N14+H14+C14+O14+P14+I14 -> 114 | W14: =Q14+J14+D14 -> 0 | X14: =SUM(U14:W14) -> 114 | Y14: =S14+L14+F14 -> 128 | Z14: =Y14-X14 -> 14 | AA14: =ROUND(Z14/$AA$26*7,0) -> 0 | AB14: =W14+V14 -> 114 | AC14: =Y14 -> 128 | AD14: =(V14+W14)/Y14 -> 0.890625 | AE14: 46022 | AF14: NF
A15: SOUTH CDA | B15: =SUM(B11:B14) -> 0 | C15: =SUM(C11:C14) -> 97 | D15: =SUM(D11:D14) -> 2 | E15: =SUM(E11:E14) -> 99 | F15: =SUM(F11:F14) -> 136 | G15: =E15/F15 -> 0.72794118 | H15: =SUM(H11:H14) -> 122 | I15: =SUM(I11:I14) -> 16 | J15: =SUM(J11:J14) -> 0 | K15: =SUM(K11:K14) -> 138 | L15: =SUM(L11:L14) -> 126 | M15: =K15/L15 -> 1.0952381 | N15: =SUM(N11:N14) -> 81 | O15: =SUM(O11:O14) -> 7 | P15: =SUM(P11:P14) -> 0 | Q15: =SUM(Q11:Q14) -> 0 | R15: =SUM(R11:R14) -> 88 | S15: =SUM(S11:S14) -> 119 | T15: =R15/S15 -> 0.7394958 | U15: =SUM(U11:U14) -> 0 | V15: =SUM(V11:V14) -> 323 | W15: =SUM(W11:W14) -> 2 | X15: =SUM(X11:X14) -> 325 | Y15: =SUM(Y11:Y14) -> 381 | Z15: =SUM(Z11:Z14) -> 56 | AA15: =ROUND(Z15/$AA$26*7,0) -> -1 | AB15: =SUM(AB11:AB14) -> 325 | AC15: =SUM(AC11:AC14) -> 381 | AD15: =AB15/AC15 -> 0.85301837
A16: Bradford | C16: 18 | D16: 5 | E16: =SUM(C16:D16) -> 23 | F16: 30 | G16: =E16/F16 -> 0.76666667 | H16: 28 | I16: 3 | J16: 3 | K16: =SUM(H16:J16) -> 34 | L16: 33 | M16: =K16/L16 -> 1.030303 | N16: 14 | O16: 4 | Q16: 12 | R16: =SUM(N16:Q16) -> 30 | S16: 30 | T16: =R16/S16 -> 1 | V16: =N16+H16+C16+O16+P16+I16 -> 67 | W16: =Q16+J16+D16 -> 20 | X16: =SUM(U16:W16) -> 87 | Y16: =S16+L16+F16 -> 93 | Z16: =Y16-X16 -> 6 | AA16: =ROUND(Z16/$AA$26*7,0) -> 0 | AB16: =W16+V16 -> 87 | AC16: =Y16 -> 93 | AD16: =(V16+W16)/Y16 -> 0.93548387 | AE16: 46022 | AF16: PS
A17: Huddersfield | C17: 39 | E17: =SUM(C17:D17) -> 39 | F17: 28 | G17: =E17/F17 -> 1.3928571 | H17: 18 | I17: 2 | J17: 3 | K17: =SUM(H17:J17) -> 23 | L17: 27 | M17: =K17/L17 -> 0.85185185 | N17: 21 | O17: 1 | Q17: 4 | R17: =SUM(N17:Q17) -> 26 | S17: 25 | T17: =R17/S17 -> 1.04 | V17: =N17+H17+C17+O17+P17+I17 -> 81 | W17: =Q17+J17+D17 -> 7 | X17: =SUM(U17:W17) -> 88 | Y17: =S17+L17+F17 -> 80 | Z17: =Y17-X17 -> -8 | AA17: =ROUND(Z17/$AA$26*7,0) -> 0 | AB17: =W17+V17 -> 88 | AC17: =Y17 -> 80 | AD17: =(V17+W17)/Y17 -> 1.1 | AE17: 46022 | AF17: PS
A18: Silsden | C18: 12 | E18: =SUM(C18:D18) -> 12 | F18: 13 | G18: =E18/F18 -> 0.92307692 | H18: 9 | I18: 3 | K18: =SUM(H18:J18) -> 12 | L18: 10 | M18: =K18/L18 -> 1.2 | N18: 5 | O18: 1 | Q18: 1 | R18: =SUM(N18:Q18) -> 7 | S18: 10 | T18: =R18/S18 -> 0.7 | V18: =N18+H18+C18+O18+P18+I18 -> 30 | W18: =Q18+J18+D18 -> 1 | X18: =SUM(U18:W18) -> 31 | Y18: =S18+L18+F18 -> 33 | Z18: =Y18-X18 -> 2 | AA18: =ROUND(Z18/$AA$26*7,0) -> 0 | AB18: =W18+V18 -> 31 | AC18: =Y18 -> 33 | AD18: =(V18+W18)/Y18 -> 0.93939394 | AE18: 46020 | AF18: PS
A19: WY CDA | B19: =SUM(B16:B18) -> 0 | C19: =SUM(C16:C18) -> 69 | D19: =SUM(D16:D18) -> 5 | E19: =SUM(E16:E18) -> 74 | F19: =SUM(F16:F18) -> 71 | G19: =E19/F19 -> 1.0422535 | H19: =SUM(H16:H18) -> 55 | I19: =SUM(I16:I18) -> 8 | J19: =SUM(J16:J18) -> 6 | K19: =SUM(K16:K18) -> 69 | L19: =SUM(L16:L18) -> 70 | M19: =K19/L19 -> 0.98571429 | N19: =SUM(N16:N18) -> 40 | O19: =SUM(O16:O18) -> 6 | P19: =SUM(P16:P18) -> 0 | Q19: =SUM(Q16:Q18) -> 17 | R19: =SUM(R16:R18) -> 63 | S19: =SUM(S16:S18) -> 65 | T19: =R19/S19 -> 0.96923077 | U19: =SUM(U16:U18) -> 0 | V19: =SUM(V16:V18) -> 178 | W19: =SUM(W16:W18) -> 28 | X19: =SUM(X16:X18) -> 206 | Y19: =SUM(Y16:Y18) -> 206 | Z19: =SUM(Z16:Z18) -> 0 | AA19: =ROUND(Z19/$AA$26*7,0) -> 0 | AB19: =SUM(AB16:AB18) -> 206 | AC19: =SUM(AC16:AC18) -> 206 | AD19: =AB19/AC19 -> 1
A22: TOTAL | B22: =B19+B15+B10 -> 0 | C22: =C19+C15+C10 -> 289 | D22: =D19+D15+D10 -> 15 | E22: =E19+E15+E10 -> 304 | F22: =F19+F15+F10 -> 339 | G22: =E22/F22 -> 0.89675516 | H22: =H19+H15+H10 -> 274 | I22: =I19+I15+I10 -> 40 | J22: =J19+J15+J10 -> 6 | K22: =K19+K15+K10 -> 320 | L22: =L19+L15+L10 -> 320 | M22: =K22/L22 -> 1 | N22: =N19+N15+N10 -> 209 | O22: =O19+O15+O10 -> 20 | P22: =P19+P15+P10 -> 0 | Q22: =Q19+Q15+Q10 -> 17 | R22: =R19+R15+R10 -> 246 | S22: =S19+S15+S10 -> 308 | T22: =R22/S22 -> 0.7987013 | U22: =U19+U15+U10 -> 0 | V22: =V19+V15+V10 -> 832 | W22: =W19+W15+W10 -> 38 | X22: =X19+X15+X10 -> 870 | Y22: =Y19+Y15+Y10 -> 967 | Z22: =Z19+Z15+Z10 -> 97 | AA22: =ROUND(Z22/$AA$26*7,0) -> -2 | AB22: =AB19+AB15+AB10 -> 870 | AC22: =AC19+AC15+AC10 -> 967 | AD22: =(V22+W22)/Y22 -> 0.89968976
AA24: 46022 | AC24: =AC22-AB22 -> 97
A25: SEPT-DEC - FLEET TARGETS | AA25: =TODAY()-1 -> 46307
L26: INPUT HERE | AA26: =AA24-AA25 -> -285
B27: Total | C27: Target | D27: TO GO (100%) | F27: UNREG ORDERS | L27: Sept | M27: Oct | N27: Nov | O27: Dec | P27: Total
A28: Salford | B28: =P28 -> 7 | C28: =12+11 -> 23 | D28: =C28-B28 -> 16 | J28: Kinto One | K28: Salford | L28: 5 | M28: 2 | P28: =SUM(L28:O28) -> 7
A29: Bolton | B29: =P29 -> 4 | C29: =6+7 -> 13 | D29: =C29-B29 -> 9 | F29: 4 | J29: Kinto Fleet Partnership | K29: Bolton | L29: 1 | N29: 3 | P29: =SUM(L29:O29) -> 4
A30: Bury | B30: =P30 -> 0 | C30: =5+6 -> 11 | D30: =C30-B30 -> 11 | J30: Kinto PCH | K30: Bury | P30: =SUM(L30:O30) -> 0
A31: Rochdale | B31: =P31 -> 2 | C31: =7+7 -> 14 | D31: =C31-B31 -> 12 | J31: Centre Fleet | K31: Rochdale | M31: 2 | P31: =SUM(L31:O31) -> 2
A32: NORTH CDA | B32: =SUM(B28:B31) -> 13 | C32: =SUM(C28:C31) -> 61 | D32: =SUM(D28:D31) -> 48 | F32: =SUM(F28:F31) -> 4 | K32: NORTH CDA | L32: =SUM(L28:L31) -> 6 | M32: =SUM(M28:M31) -> 4 | N32: =SUM(N28:N31) -> 3 | O32: =SUM(O28:O31) -> 0 | P32: =SUM(P28:P31) -> 13
A34: Macclesfield | B34: =P34 -> 1 | C34: =7+6 -> 13 | D34: =C34-B34 -> 12 | K34: Macclesfield | L34: 1 | P34: =SUM(L34:O34) -> 1
A35: Denton | B35: 2 | C35: =9+9 -> 18 | D35: =C35-B35 -> 16 | F35: 2 | K35: Denton | M35: 1 | P35: =SUM(L35:O35) -> 1
A36: Altrincham | B36: 1 | C36: =5+6 -> 11 | D36: =C36-B36 -> 10 | F36: 1 | K36: Altrincham | P36: =SUM(L36:O36) -> 0
A37: Stockport | B37: 1 | C37: =9+9 -> 18 | D37: =C37-B37 -> 17 | F37: 1 | K37: Stockport | O37: 1 | P37: =SUM(L37:O37) -> 1
A38: SOUTH CDA | B38: =SUM(B34:B37) -> 5 | C38: =SUM(C34:C37) -> 60 | D38: =SUM(D34:D37) -> 55 | F38: =SUM(F34:F37) -> 4 | K38: SOUTH CDA | L38: =SUM(L34:L37) -> 1 | M38: =SUM(M34:M37) -> 1 | N38: =SUM(N34:N37) -> 0 | O38: =SUM(O34:O37) -> 1 | P38: =SUM(P34:P37) -> 3
A40: Bradford | B40: 22 | C40: =9+9 -> 18 | D40: =C40-B40 -> -4 | F40: 0 | K40: Bradford | L40: 3 | M40: 4 | N40: 3 | O40: 12 | P40: =SUM(L40:O40) -> 22
A41: Huddersfield | B41: 3 | C41: =5+6 -> 11 | D41: =C41-B41 -> 8 | F41: 0 | K41: Huddersfield | N41: 2 | O41: 1 | P41: =SUM(L41:O41) -> 3
A42: Silsden | B42: =P42 -> 0 | C42: =2+3 -> 5 | D42: =C42-B42 -> 5 | F42: 0 | K42: Silsden | P42: =SUM(L42:O42) -> 0
A43: WY CDA | B43: =SUM(B40:B42) -> 25 | C43: =SUM(C40:C42) -> 34 | D43: =SUM(D40:D42) -> 9 | F43: =SUM(F40:F42) -> 0 | K43: WY CDA | L43: =SUM(L40:L42) -> 3 | M43: =SUM(M40:M42) -> 4 | N43: =SUM(N40:N42) -> 5 | O43: =SUM(O40:O42) -> 13 | P43: =SUM(P40:P42) -> 25
A46: TOTAL | B46: =B43+B38+B32 -> 43 | C46: =C43+C38+C32 -> 155 | D46: =D43+D38+D32 -> 112 | F46: =F43+F38+F32 -> 8 | K46: TOTAL | L46: =L43+L38+L32 -> 10 | M46: =M43+M38+M32 -> 9 | N46: =N43+N38+N32 -> 8 | O46: =O43+O38+O32 -> 14 | P46: =P43+P38+P32 -> 41
A49: REGISTRATIONS (NON-COUNTING) | X49: Updated | Y49: By
C50: =C4 -> OCT | G50: =H4 -> NOV | L50: =N4 -> DEC | R50: TOTAL
C51: Non-Counting Fleet (Reg) | D51: Non-Counting Fleet (Unreg) | E51: Total | F51: Budget | G51: Non-Counting Fleet (Reg) | H51: Non-Counting Fleet (Unreg) | J51: Total | K51: Budget | L51: Non-Counting Fleet (Reg) | M51: Non-Counting Fleet (Unreg) | N51: Total | O51: Budget | R51: Non-Counting Fleet (Reg) | S51: Non-Counting Fleet (Unreg) | T51: Total | U51: Budget
A52: Salford | C52: 127 | D52: 0 | E52: =SUM(C52:D52) -> 127 | F52: 170 | G52: 199 | H52: 0 | J52: =SUM(G52:H52) -> 199 | K52: 159 | L52: 192 | M52: 0 | N52: =SUM(L52:M52) -> 192 | O52: 128 | Q52: =B52 -> 0 | R52: =L52+G52+C52 -> 518 | S52: =M52+H52+D52 -> 0 | T52: =SUM(Q52:S52) -> 518 | U52: =O52+K52+F52 -> 457 | X52: 46006 | Y52: gb
A53: NORTH CDA | C53: =SUM(C52) -> 127 | D53: =SUM(D52) -> 0 | E53: =SUM(E52) -> 127 | F53: =SUM(F52) -> 170 | G53: =SUM(G52) -> 199 | H53: =SUM(H52) -> 0 | J53: =SUM(J52) -> 199 | K53: =SUM(K52) -> 159 | L53: =SUM(L52) -> 192 | M53: =SUM(M52) -> 0 | N53: =SUM(N52) -> 192 | O53: =SUM(O52) -> 128 | Q53: =B53 -> 0 | R53: =SUM(R52) -> 518 | S53: =SUM(S52) -> 0 | T53: =SUM(T52) -> 518 | U53: =SUM(U52) -> 457
A54: Denton | C54: 14 | D54: 0 | E54: =SUM(C54:D54) -> 14 | F54: 32 | G54: 6 | H54: 0 | J54: =SUM(G54:H54) -> 6 | K54: 25 | L54: 24 | M54: 0 | N54: 10 | O54: 40 | Q54: =B54 -> 0 | R54: =L54+G54+P58+C54 -> 44 | S54: =M54+H54+D54 -> 0 | T54: =SUM(Q54:S54) -> 44 | U54: =O54+K54+F54 -> 97 | X54: 46022 | Y54: NF
A55: SOUTH CDA | C55: =SUM(C54) -> 14 | D55: =SUM(D54) -> 0 | E55: =SUM(E54) -> 14 | F55: =SUM(F54) -> 32 | G55: =SUM(G54) -> 6 | H55: =SUM(H54) -> 0 | J55: =SUM(J54) -> 6 | K55: =SUM(K54) -> 25 | L55: =SUM(L54) -> 24 | M55: =SUM(M54) -> 0 | N55: =SUM(N54) -> 10 | O55: =SUM(O54) -> 40 | Q55: =B55 -> 0 | R55: =SUM(R54) -> 44 | S55: =SUM(S54) -> 0 | T55: =SUM(T54) -> 44 | U55: =SUM(U54) -> 97
A56: Bradford | C56: 144 | D56: 0 | E56: =SUM(C56:D56) -> 144 | F56: 49 | G56: 61 | H56: 0 | J56: =SUM(G56:H56) -> 61 | K56: 40 | L56: 49 | M56: 0 | N56: =SUM(L56:M56) -> 49 | O56: 32 | Q56: =B56 -> 0 | R56: =L56+G56+C56 -> 254 | S56: =M56+H56+D56 -> 0 | T56: =SUM(Q56:S56) -> 254 | U56: =O56+K56+F56 -> 121
C57: =SUM(C56) -> 144 | D57: =SUM(D56) -> 0 | E57: =SUM(E56) -> 144 | F57: =SUM(F56) -> 49 | G57: =SUM(G56) -> 61 | H57: =SUM(H56) -> 0 | J57: =SUM(J56) -> 61 | K57: =SUM(K56) -> 40 | L57: =SUM(L56) -> 49 | M57: =SUM(M56) -> 0 | N57: =SUM(N56) -> 49 | O57: =SUM(O56) -> 32 | Q57: =B57 -> 0 | R57: =SUM(R56) -> 254 | S57: =SUM(S56) -> 0 | T57: =SUM(T56) -> 254 | U57: =SUM(U56) -> 121 | X57: 46022 | Y57: PS
Q58: =B58 -> 0
A60: TOTAL | C60: =C57+C55+C53 -> 285 | D60: =D57+D55+D53 -> 0 | E60: =E57+E55+E53 -> 285 | F60: =F57+F55+F53 -> 251 | G60: =G57+G55+G53 -> 266 | H60: =H57+H55+H53 -> 0 | J60: =J57+J55+J53 -> 266 | K60: =K57+K55+K53 -> 224 | L60: =L57+L55+L53 -> 265 | M60: =M57+M55+M53 -> 0 | N60: =N57+N55+N53 -> 251 | O60: =O57+O55+O53 -> 200 | R60: =R57+R55+R53 -> 816 | S60: =S57+S55+S53 -> 0 | T60: =T57+T55+T53 -> 816 | U60: =U57+U55+U53 -> 675
A62: USED COUNTING VOLUME | P62: Updated | Q62: By
B63: =C50 -> OCT | F63: =G50 -> NOV | J63: =L50 -> DEC | N63: TOTAL
B64: B/FWD | C64: Counting | D64: Target | F64: Counting | G64: Target | J64: Counting | K64: Target | M64: B/FWD | N64: Counting | O64: Target
A65: Bolton | C65: 69 | D65: 48 | E65: =C65/D65 -> 1.4375 | F65: 49 | G65: 45 | H65: =F65/G65 -> 1.0888889 | J65: 23 | K65: 32 | L65: =J65/K65 -> 0.71875 | M65: =B65 -> 0 | N65: =J65+F65+C65 -> 141 | O65: =K65+G65+D65 -> 125 | Q65: gb
A66: Bury | C66: 47 | D66: 47 | E66: =C66/D66 -> 1 | F66: 36 | G66: 43 | H66: =F66/G66 -> 0.8372093 | J66: 29 | K66: 31 | L66: =J66/K66 -> 0.93548387 | M66: =B66 -> 0 | N66: =J66+F66+C66 -> 112 | O66: =K66+G66+D66 -> 121 | Q66: gb
A67: Rochdale | C67: 46 | D67: 59 | E67: =C67/D67 -> 0.77966102 | F67: 40 | G67: 54 | H67: =F67/G67 -> 0.74074074 | J67: 23 | K67: 39 | L67: =J67/K67 -> 0.58974359 | M67: =B67 -> 0 | N67: =J67+F67+C67 -> 109 | O67: =K67+G67+D67 -> 152 | P67: 46024 | Q67: gb
A68: SQ | C68: 64 | D68: 62 | E68: =C68/D68 -> 1.0322581 | F68: 50 | G68: 57 | H68: =F68/G68 -> 0.87719298 | J68: 32 | K68: 40 | L68: =J68/K68 -> 0.8 | M68: =B68 -> 0 | N68: =J68+F68+C68 -> 146 | O68: =K68+G68+D68 -> 159 | P68: 46024 | Q68: gb
A69: NORTH CDA | B69: =SUM(B65:B68) -> 0 | C69: =SUM(C65:C68) -> 226 | D69: =SUM(D65:D68) -> 216 | E69: =C69/D69 -> 1.0462963 | F69: =SUM(F65:F68) -> 175 | G69: =SUM(G65:G68) -> 199 | H69: =F69/G69 -> 0.87939698 | J69: =SUM(J65:J68) -> 107 | K69: =SUM(K65:K68) -> 142 | L69: =J69/K69 -> 0.75352113 | M69: =SUM(M65:M68) -> 0 | N69: =SUM(N65:N68) -> 508 | O69: =SUM(O65:O68) -> 557
A70: Altrincham | C70: 43 | D70: 44 | E70: =C70/D70 -> 0.97727273 | F70: 42 | G70: 41 | H70: =F70/G70 -> 1.0243902 | J70: 28 | K70: 28 | L70: =J70/K70 -> 1 | M70: =B70 -> 0 | N70: =J70+F70+C70 -> 113 | O70: =K70+G70+D70 -> 113 | P70: 46020 | Q70: NF
A71: Denton | C71: 36 | D71: 51 | E71: =C71/D71 -> 0.70588235 | F71: 27 | G71: 47 | H71: =F71/G71 -> 0.57446809 | J71: 31 | K71: 33 | L71: =J71/K71 -> 0.93939394 | M71: =B71 -> 0 | N71: =J71+F71+C71 -> 94 | O71: =K71+G71+D71 -> 131 | P71: 46020 | Q71: NF
A72: Macclesfield | C72: 44 | D72: 41 | E72: =C72/D72 -> 1.0731707 | F72: 27 | G72: 38 | H72: =F72/G72 -> 0.71052632 | J72: 28 | K72: 25 | L72: =J72/K72 -> 1.12 | M72: =B72 -> 0 | N72: =J72+F72+C72 -> 99 | O72: =K72+G72+D72 -> 104 | P72: 46020 | Q72: NF
A73: Stockport | C73: 88 | D73: 94 | E73: =C73/D73 -> 0.93617021 | F73: 63 | G73: 86 | H73: =F73/G73 -> 0.73255814 | J73: 54 | K73: 60 | L73: =J73/K73 -> 0.9 | M73: =B73 -> 0 | N73: =J73+F73+C73 -> 205 | O73: =K73+G73+D73 -> 240 | P73: 46020 | Q73: NF
A74: SOUTH CDA | B74: =SUM(B70:B73) -> 0 | C74: =SUM(C70:C73) -> 211 | D74: =SUM(D70:D73) -> 230 | E74: =C74/D74 -> 0.9173913 | F74: =SUM(F70:F73) -> 159 | G74: =SUM(G70:G73) -> 212 | H74: =F74/G74 -> 0.75 | J74: =SUM(J70:J73) -> 141 | K74: =SUM(K70:K73) -> 146 | L74: =J74/K74 -> 0.96575342 | M74: =SUM(M70:M73) -> 0 | N74: =SUM(N70:N73) -> 511 | O74: =SUM(O70:O73) -> 588
A75: Bradford | C75: 33 | D75: 38 | E75: =C75/D75 -> 0.86842105 | F75: 25 | G75: 35 | H75: =F75/G75 -> 0.71428571 | J75: 23 | K75: 25 | L75: =J75/K75 -> 0.92 | M75: =B75 -> 0 | N75: =J75+F75+C75 -> 81 | O75: =K75+G75+D75 -> 98 | P75: 46020 | Q75: PS
A76: Huddersfield | C76: 39 | D76: 51 | E76: =C76/D76 -> 0.76470588 | F76: 27 | G76: 47 | H76: =F76/G76 -> 0.57446809 | J76: 23 | K76: 33 | L76: =J76/K76 -> 0.6969697 | M76: =B76 -> 0 | N76: =J76+F76+C76 -> 89 | O76: =K76+G76+D76 -> 131 | P76: 46020 | Q76: PS
A77: Silsden | C77: 24 | D77: 23 | E77: =C77/D77 -> 1.0434783 | F77: 11 | G77: 21 | H77: =F77/G77 -> 0.52380952 | J77: 7 | K77: 15 | L77: =J77/K77 -> 0.46666667 | M77: =B77 -> 0 | N77: =J77+F77+C77 -> 42 | O77: =K77+G77+D77 -> 59 | P77: 46020 | Q77: PS
A78: WY CDA | B78: =SUM(B75:B77) -> 0 | C78: =SUM(C75:C77) -> 96 | D78: =SUM(D75:D77) -> 112 | E78: =C78/D78 -> 0.85714286 | F78: =SUM(F75:F77) -> 63 | G78: =SUM(G75:G77) -> 103 | H78: =F78/G78 -> 0.61165049 | J78: =SUM(J75:J77) -> 53 | K78: =SUM(K75:K77) -> 73 | L78: =J78/K78 -> 0.7260274 | M78: =SUM(M75:M77) -> 0 | N78: =SUM(N75:N77) -> 212 | O78: =SUM(O75:O77) -> 288
A81: TOTAL | B81: =B78+B74+B69 -> 0 | C81: =C78+C74+C69 -> 533 | D81: =D78+D74+D69 -> 558 | E81: =C81/D81 -> 0.95519713 | F81: =F78+F74+F69 -> 397 | G81: =G78+G74+G69 -> 514 | H81: =F81/G81 -> 0.77237354 | J81: =J78+J74+J69 -> 301 | K81: =K78+K74+K69 -> 361 | L81: =J81/K81 -> 0.83379501 | M81: =M78+M74+M69 -> 0 | N81: =N78+N74+N69 -> 1231 | O81: =O78+O74+O69 -> 1433

Sheet Copy of 2025 - Q4
A3: REGISTRATIONS (COUNTING) | AE3: Updated | AF3: By
C4: OCT | H4: NOV | N4: DEC | V4: TOTAL
B5: B/FWD | C5: Counting | D5: Counting Fleet | E5: Total | F5: Target | H5: Counting | I5: CLCP Regs | J5: Counting Fleet | K5: Total | L5: Target | N5: Counting | O5: CLCP Regs | P5: Double Counters | Q5: Counting Fleet | R5: Total | S5: Target | U5: B/FWD | V5: Counting | W5: Counting Fleet | X5: Total | Y5: Target | Z5: TO GO | AA5: PER WEEK | AB5: QTR REGS | AC5: TARGET | AD5: REGS v TGT
A6: Bolton | C6: 24 | E6: =SUM(C6:D6) -> 24 | F6: 31 | G6: =E6/F6 -> 0.77419355 | H6: 26 | I6: 4 | K6: =SUM(H6:J6) -> 30 | L6: 29 | M6: =K6/L6 -> 1.0344828 | N6: 21 | O6: 2 | R6: =SUM(N6:Q6) -> 23 | S6: 30 | T6: =R6/S6 -> 0.76666667 | V6: =N6+H6+C6+O6+P6+I6 -> 77 | W6: =Q6+J6+D6 -> 0 | X6: =SUM(U6:W6) -> 77 | Y6: =S6+L6+F6 -> 90 | Z6: =Y6-X6 -> 13 | AA6: =ROUND(Z6/$AA$26*7,0) -> 0 | AB6: =W6+V6 -> 77 | AC6: =Y6 -> 90 | AD6: =(V6+W6)/Y6 -> 0.85555556 | AE6: 46024 | AF6: gb
A7: Bury | C7: 26 | E7: =SUM(C7:D7) -> 26 | F7: 26 | G7: =E7/F7 -> 1 | H7: 20 | I7: 3 | K7: =SUM(H7:J7) -> 23 | L7: 26 | M7: =K7/L7 -> 0.88461538 | N7: 13 | O7: 1 | R7: =SUM(N7:Q7) -> 14 | S7: 25 | T7: =R7/S7 -> 0.56 | V7: =N7+H7+C7+O7+P7+I7 -> 63 | W7: =Q7+J7+D7 -> 0 | X7: =SUM(U7:W7) -> 63 | Y7: =S7+L7+F7 -> 77 | Z7: =Y7-X7 -> 14 | AA7: =ROUND(Z7/$AA$26*7,0) -> 0 | AB7: =W7+V7 -> 63 | AC7: =Y7 -> 77 | AD7: =(V7+W7)/Y7 -> 0.81818182 | AE7: 46024 | AF7: gb
A8: Rochdale | C8: 24 | D8: 2 | E8: =SUM(C8:D8) -> 26 | F8: 35 | G8: =E8/F8 -> 0.74285714 | H8: 14 | I8: 3 | K8: =SUM(H8:J8) -> 17 | L8: 31 | M8: =K8/L8 -> 0.5483871 | N8: 18 | O8: 1 | R8: =SUM(N8:Q8) -> 19 | S8: 30 | T8: =R8/S8 -> 0.63333333 | V8: =N8+H8+C8+O8+P8+I8 -> 60 | W8: =Q8+J8+D8 -> 2 | X8: =SUM(U8:W8) -> 62 | Y8: =S8+L8+F8 -> 96 | Z8: =Y8-X8 -> 34 | AA8: =ROUND(Z8/$AA$26*7,0) -> -1 | AB8: =W8+V8 -> 62 | AC8: =Y8 -> 96 | AD8: =(V8+W8)/Y8 -> 0.64583333 | AE8: 46024 | AF8: gb
A9: SQ | C9: 49 | D9: 6 | E9: =SUM(C9:D9) -> 55 | F9: 40 | G9: =E9/F9 -> 1.375 | H9: 37 | I9: 6 | K9: =SUM(H9:J9) -> 43 | L9: 38 | M9: =K9/L9 -> 1.1315789 | N9: 36 | O9: 3 | R9: =SUM(N9:Q9) -> 39 | S9: 39 | T9: =R9/S9 -> 1 | V9: =N9+H9+C9+O9+P9+I9 -> 131 | W9: =Q9+J9+D9 -> 6 | X9: =SUM(U9:W9) -> 137 | Y9: =S9+L9+F9 -> 117 | Z9: =Y9-X9 -> -20 | AA9: =ROUND(Z9/$AA$26*7,0) -> 0 | AB9: =W9+V9 -> 137 | AC9: =Y9 -> 117 | AD9: =(V9+W9)/Y9 -> 1.1709402 | AE9: 46024 | AF9: gb
A10: NORTH CDA | B10: =SUM(B6:B9) -> 0 | C10: =SUM(C6:C9) -> 123 | D10: =SUM(D6:D9) -> 8 | E10: =SUM(E6:E9) -> 131 | F10: =SUM(F6:F9) -> 132 | G10: =E10/F10 -> 0.99242424 | H10: =SUM(H6:H9) -> 97 | I10: =SUM(I6:I9) -> 16 | J10: =SUM(J6:J9) -> 0 | K10: =SUM(K6:K9) -> 113 | L10: =SUM(L6:L9) -> 124 | M10: =K10/L10 -> 0.91129032 | N10: =SUM(N6:N9) -> 88 | O10: =SUM(O6:O9) -> 7 | P10: =SUM(P6:P9) -> 0 | Q10: =SUM(Q6:Q9) -> 0 | R10: =SUM(R6:R9) -> 95 | S10: =SUM(S6:S9) -> 124 | T10: =R10/S10 -> 0.76612903 | U10: =SUM(U6:U9) -> 0 | V10: =SUM(V6:V9) -> 331 | W10: =SUM(W6:W9) -> 8 | X10: =SUM(X6:X9) -> 339 | Y10: =SUM(Y6:Y9) -> 380 | Z10: =SUM(Z6:Z9) -> 41 | AA10: =ROUND(Z10/$AA$26*7,0) -> -1 | AB10: =SUM(AB6:AB9) -> 339 | AC10: =SUM(AC6:AC9) -> 380 | AD10: =AB10/AC10 -> 0.89210526
A11: Altrincham | C11: 23 | E11: =SUM(C11:D11) -> 23 | F11: 30 | G11: =E11/F11 -> 0.76666667 | H11: 18 | I11: 4 | K11: =SUM(H11:J11) -> 22 | L11: 24 | M11: =K11/L11 -> 0.91666667 | N11: 17 | O11: 1 | R11: =SUM(N11:Q11) -> 18 | S11: 22 | T11: =R11/S11 -> 0.81818182 | V11: =N11+H11+C11+O11+P11+I11 -> 63 | W11: =Q11+J11+D11 -> 0 | X11: =SUM(U11:W11) -> 63 | Y11: =S11+L11+F11 -> 76 | Z11: =Y11-X11 -> 13 | AA11: =ROUND(Z11/$AA$26*7,0) -> 0 | AB11: =W11+V11 -> 63 | AC11: =Y11 -> 76 | AD11: =(V11+W11)/Y11 -> 0.82894737 | AE11: 46022 | AF11: NF
A12: Denton | C12: 18 | D12: 2 | E12: =SUM(C12:D12) -> 20 | F12: 29 | G12: =E12/F12 -> 0.68965517 | H12: 41 | I12: 4 | K12: =SUM(H12:J12) -> 45 | L12: 30 | M12: =K12/L12 -> 1.5 | N12: 16 | O12: 3 | R12: =SUM(N12:Q12) -> 19 | S12: 28 | T12: =R12/S12 -> 0.67857143 | V12: =N12+H12+C12+O12+P12+I12 -> 82 | W12: =Q12+J12+D12 -> 2 | X12: =SUM(U12:W12) -> 84 | Y12: =S12+L12+F12 -> 87 | Z12: =Y12-X12 -> 3 | AA12: =ROUND(Z12/$AA$26*7,0) -> 0 | AB12: =W12+V12 -> 84 | AC12: =Y12 -> 87 | AD12: =(V12+W12)/Y12 -> 0.96551724 | AE12: 46022 | AF12: NF
A13: Macclesfield | C13: 16 | E13: =SUM(C13:D13) -> 16 | F13: 34 | G13: =E13/F13 -> 0.47058824 | H13: 27 | I13: 4 | K13: =SUM(H13:J13) -> 31 | L13: 29 | M13: =K13/L13 -> 1.0689655 | N13: 16 | O13: 1 | R13: =SUM(N13:Q13) -> 17 | S13: 27 | T13: =R13/S13 -> 0.62962963 | V13: =N13+H13+C13+O13+P13+I13 -> 64 | W13: =Q13+J13+D13 -> 0 | X13: =SUM(U13:W13) -> 64 | Y13: =S13+L13+F13 -> 90 | Z13: =Y13-X13 -> 26 | AA13: =ROUND(Z13/$AA$26*7,0) -> -1 | AB13: =W13+V13 -> 64 | AC13: =Y13 -> 90 | AD13: =(V13+W13)/Y13 -> 0.71111111 | AE13: 46022 | AF13: NF
A14: Stockport | C14: 40 | E14: =SUM(C14:D14) -> 40 | F14: 43 | G14: =E14/F14 -> 0.93023256 | H14: 36 | I14: 4 | K14: =SUM(H14:J14) -> 40 | L14: 43 | M14: =K14/L14 -> 0.93023256 | N14: 32 | O14: 2 | R14: =SUM(N14:Q14) -> 34 | S14: 42 | T14: =R14/S14 -> 0.80952381 | V14: =N14+H14+C14+O14+P14+I14 -> 114 | W14: =Q14+J14+D14 -> 0 | X14: =SUM(U14:W14) -> 114 | Y14: =S14+L14+F14 -> 128 | Z14: =Y14-X14 -> 14 | AA14: =ROUND(Z14/$AA$26*7,0) -> 0 | AB14: =W14+V14 -> 114 | AC14: =Y14 -> 128 | AD14: =(V14+W14)/Y14 -> 0.890625 | AE14: 46022 | AF14: NF
A15: SOUTH CDA | B15: =SUM(B11:B14) -> 0 | C15: =SUM(C11:C14) -> 97 | D15: =SUM(D11:D14) -> 2 | E15: =SUM(E11:E14) -> 99 | F15: =SUM(F11:F14) -> 136 | G15: =E15/F15 -> 0.72794118 | H15: =SUM(H11:H14) -> 122 | I15: =SUM(I11:I14) -> 16 | J15: =SUM(J11:J14) -> 0 | K15: =SUM(K11:K14) -> 138 | L15: =SUM(L11:L14) -> 126 | M15: =K15/L15 -> 1.0952381 | N15: =SUM(N11:N14) -> 81 | O15: =SUM(O11:O14) -> 7 | P15: =SUM(P11:P14) -> 0 | Q15: =SUM(Q11:Q14) -> 0 | R15: =SUM(R11:R14) -> 88 | S15: =SUM(S11:S14) -> 119 | T15: =R15/S15 -> 0.7394958 | U15: =SUM(U11:U14) -> 0 | V15: =SUM(V11:V14) -> 323 | W15: =SUM(W11:W14) -> 2 | X15: =SUM(X11:X14) -> 325 | Y15: =SUM(Y11:Y14) -> 381 | Z15: =SUM(Z11:Z14) -> 56 | AA15: =ROUND(Z15/$AA$26*7,0) -> -1 | AB15: =SUM(AB11:AB14) -> 325 | AC15: =SUM(AC11:AC14) -> 381 | AD15: =AB15/AC15 -> 0.85301837
A16: Bradford | C16: 18 | D16: 5 | E16: =SUM(C16:D16) -> 23 | F16: 30 | G16: =E16/F16 -> 0.76666667 | H16: 28 | I16: 3 | J16: 3 | K16: =SUM(H16:J16) -> 34 | L16: 33 | M16: =K16/L16 -> 1.030303 | N16: 14 | O16: 4 | Q16: 12 | R16: =SUM(N16:Q16) -> 30 | S16: 30 | T16: =R16/S16 -> 1 | V16: =N16+H16+C16+O16+P16+I16 -> 67 | W16: =Q16+J16+D16 -> 20 | X16: =SUM(U16:W16) -> 87 | Y16: =S16+L16+F16 -> 93 | Z16: =Y16-X16 -> 6 | AA16: =ROUND(Z16/$AA$26*7,0) -> 0 | AB16: =W16+V16 -> 87 | AC16: =Y16 -> 93 | AD16: =(V16+W16)/Y16 -> 0.93548387 | AE16: 46022 | AF16: PS
A17: Huddersfield | C17: 39 | E17: =SUM(C17:D17) -> 39 | F17: 28 | G17: =E17/F17 -> 1.3928571 | H17: 18 | I17: 2 | J17: 3 | K17: =SUM(H17:J17) -> 23 | L17: 27 | M17: =K17/L17 -> 0.85185185 | N17: 21 | O17: 1 | Q17: 4 | R17: =SUM(N17:Q17) -> 26 | S17: 25 | T17: =R17/S17 -> 1.04 | V17: =N17+H17+C17+O17+P17+I17 -> 81 | W17: =Q17+J17+D17 -> 7 | X17: =SUM(U17:W17) -> 88 | Y17: =S17+L17+F17 -> 80 | Z17: =Y17-X17 -> -8 | AA17: =ROUND(Z17/$AA$26*7,0) -> 0 | AB17: =W17+V17 -> 88 | AC17: =Y17 -> 80 | AD17: =(V17+W17)/Y17 -> 1.1 | AE17: 46022 | AF17: PS
A18: Silsden | C18: 12 | E18: =SUM(C18:D18) -> 12 | F18: 13 | G18: =E18/F18 -> 0.92307692 | H18: 9 | I18: 3 | K18: =SUM(H18:J18) -> 12 | L18: 10 | M18: =K18/L18 -> 1.2 | N18: 5 | O18: 1 | Q18: 1 | R18: =SUM(N18:Q18) -> 7 | S18: 10 | T18: =R18/S18 -> 0.7 | V18: =N18+H18+C18+O18+P18+I18 -> 30 | W18: =Q18+J18+D18 -> 1 | X18: =SUM(U18:W18) -> 31 | Y18: =S18+L18+F18 -> 33 | Z18: =Y18-X18 -> 2 | AA18: =ROUND(Z18/$AA$26*7,0) -> 0 | AB18: =W18+V18 -> 31 | AC18: =Y18 -> 33 | AD18: =(V18+W18)/Y18 -> 0.93939394 | AE18: 46020 | AF18: PS
A19: WY CDA | B19: =SUM(B16:B18) -> 0 | C19: =SUM(C16:C18) -> 69 | D19: =SUM(D16:D18) -> 5 | E19: =SUM(E16:E18) -> 74 | F19: =SUM(F16:F18) -> 71 | G19: =E19/F19 -> 1.0422535 | H19: =SUM(H16:H18) -> 55 | I19: =SUM(I16:I18) -> 8 | J19: =SUM(J16:J18) -> 6 | K19: =SUM(K16:K18) -> 69 | L19: =SUM(L16:L18) -> 70 | M19: =K19/L19 -> 0.98571429 | N19: =SUM(N16:N18) -> 40 | O19: =SUM(O16:O18) -> 6 | P19: =SUM(P16:P18) -> 0 | Q19: =SUM(Q16:Q18) -> 17 | R19: =SUM(R16:R18) -> 63 | S19: =SUM(S16:S18) -> 65 | T19: =R19/S19 -> 0.96923077 | U19: =SUM(U16:U18) -> 0 | V19: =SUM(V16:V18) -> 178 | W19: =SUM(W16:W18) -> 28 | X19: =SUM(X16:X18) -> 206 | Y19: =SUM(Y16:Y18) -> 206 | Z19: =SUM(Z16:Z18) -> 0 | AA19: =ROUND(Z19/$AA$26*7,0) -> 0 | AB19: =SUM(AB16:AB18) -> 206 | AC19: =SUM(AC16:AC18) -> 206 | AD19: =AB19/AC19 -> 1
A22: TOTAL | B22: =B19+B15+B10 -> 0 | C22: =C19+C15+C10 -> 289 | D22: =D19+D15+D10 -> 15 | E22: =E19+E15+E10 -> 304 | F22: =F19+F15+F10 -> 339 | G22: =E22/F22 -> 0.89675516 | H22: =H19+H15+H10 -> 274 | I22: =I19+I15+I10 -> 40 | J22: =J19+J15+J10 -> 6 | K22: =K19+K15+K10 -> 320 | L22: =L19+L15+L10 -> 320 | M22: =K22/L22 -> 1 | N22: =N19+N15+N10 -> 209 | O22: =O19+O15+O10 -> 20 | P22: =P19+P15+P10 -> 0 | Q22: =Q19+Q15+Q10 -> 17 | R22: =R19+R15+R10 -> 246 | S22: =S19+S15+S10 -> 308 | T22: =R22/S22 -> 0.7987013 | U22: =U19+U15+U10 -> 0 | V22: =V19+V15+V10 -> 832 | W22: =W19+W15+W10 -> 38 | X22: =X19+X15+X10 -> 870 | Y22: =Y19+Y15+Y10 -> 967 | Z22: =Z19+Z15+Z10 -> 97 | AA22: =ROUND(Z22/$AA$26*7,0) -> -2 | AB22: =AB19+AB15+AB10 -> 870 | AC22: =AC19+AC15+AC10 -> 967 | AD22: =(V22+W22)/Y22 -> 0.89968976
AA24: 46022 | AC24: =AC22-AB22 -> 97
A25: SEPT-DEC - FLEET TARGETS | AA25: =TODAY()-1 -> 46307
L26: INPUT HERE | AA26: =AA24-AA25 -> -285
B27: Total | C27: Target | D27: TO GO (100%) | F27: UNREG ORDERS | L27: Sept | M27: Oct | N27: Nov | O27: Dec | P27: Total
A28: Salford | B28: =P28 -> 7 | C28: =12+11 -> 23 | D28: =C28-B28 -> 16 | J28: Kinto One | K28: Salford | L28: 5 | M28: 2 | P28: =SUM(L28:O28) -> 7
A29: Bolton | B29: =P29 -> 4 | C29: =6+7 -> 13 | D29: =C29-B29 -> 9 | F29: 4 | J29: Kinto Fleet Partnership | K29: Bolton | L29: 1 | N29: 3 | P29: =SUM(L29:O29) -> 4
A30: Bury | B30: =P30 -> 0 | C30: =5+6 -> 11 | D30: =C30-B30 -> 11 | J30: Kinto PCH | K30: Bury | P30: =SUM(L30:O30) -> 0
A31: Rochdale | B31: =P31 -> 2 | C31: =7+7 -> 14 | D31: =C31-B31 -> 12 | J31: Centre Fleet | K31: Rochdale | M31: 2 | P31: =SUM(L31:O31) -> 2
A32: NORTH CDA | B32: =SUM(B28:B31) -> 13 | C32: =SUM(C28:C31) -> 61 | D32: =SUM(D28:D31) -> 48 | F32: =SUM(F28:F31) -> 4 | K32: NORTH CDA | L32: =SUM(L28:L31) -> 6 | M32: =SUM(M28:M31) -> 4 | N32: =SUM(N28:N31) -> 3 | O32: =SUM(O28:O31) -> 0 | P32: =SUM(P28:P31) -> 13
A34: Macclesfield | B34: =P34 -> 1 | C34: =7+6 -> 13 | D34: =C34-B34 -> 12 | K34: Macclesfield | L34: 1 | P34: =SUM(L34:O34) -> 1
A35: Denton | B35: 2 | C35: =9+9 -> 18 | D35: =C35-B35 -> 16 | F35: 2 | K35: Denton | M35: 1 | P35: =SUM(L35:O35) -> 1
A36: Altrincham | B36: 1 | C36: =5+6 -> 11 | D36: =C36-B36 -> 10 | F36: 1 | K36: Altrincham | P36: =SUM(L36:O36) -> 0
A37: Stockport | B37: 1 | C37: =9+9 -> 18 | D37: =C37-B37 -> 17 | F37: 1 | K37: Stockport | O37: 1 | P37: =SUM(L37:O37) -> 1
A38: SOUTH CDA | B38: =SUM(B34:B37) -> 5 | C38: =SUM(C34:C37) -> 60 | D38: =SUM(D34:D37) -> 55 | F38: =SUM(F34:F37) -> 4 | K38: SOUTH CDA | L38: =SUM(L34:L37) -> 1 | M38: =SUM(M34:M37) -> 1 | N38: =SUM(N34:N37) -> 0 | O38: =SUM(O34:O37) -> 1 | P38: =SUM(P34:P37) -> 3
A40: Bradford | B40: 22 | C40: =9+9 -> 18 | D40: =C40-B40 -> -4 | F40: 0 | K40: Bradford | L40: 3 | M40: 4 | N40: 3 | O40: 12 | P40: =SUM(L40:O40) -> 22
A41: Huddersfield | B41: 3 | C41: =5+6 -> 11 | D41: =C41-B41 -> 8 | F41: 0 | K41: Huddersfield | N41: 2 | O41: 1 | P41: =SUM(L41:O41) -> 3
A42: Silsden | B42: =P42 -> 0 | C42: =2+3 -> 5 | D42: =C42-B42 -> 5 | F42: 0 | K42: Silsden | P42: =SUM(L42:O42) -> 0
A43: WY CDA | B43: =SUM(B40:B42) -> 25 | C43: =SUM(C40:C42) -> 34 | D43: =SUM(D40:D42) -> 9 | F43: =SUM(F40:F42) -> 0 | K43: WY CDA | L43: =SUM(L40:L42) -> 3 | M43: =SUM(M40:M42) -> 4 | N43: =SUM(N40:N42) -> 5 | O43: =SUM(O40:O42) -> 13 | P43: =SUM(P40:P42) -> 25
A46: TOTAL | B46: =B43+B38+B32 -> 43 | C46: =C43+C38+C32 -> 155 | D46: =D43+D38+D32 -> 112 | F46: =F43+F38+F32 -> 8 | K46: TOTAL | L46: =L43+L38+L32 -> 10 | M46: =M43+M38+M32 -> 9 | N46: =N43+N38+N32 -> 8 | O46: =O43+O38+O32 -> 14 | P46: =P43+P38+P32 -> 41
A49: REGISTRATIONS (NON-COUNTING) | X49: Updated | Y49: By
C50: =C4 -> OCT | G50: =H4 -> NOV | L50: =N4 -> DEC | R50: TOTAL
C51: Non-Counting Fleet (Reg) | D51: Non-Counting Fleet (Unreg) | E51: Total | F51: Budget | G51: Non-Counting Fleet (Reg) | H51: Non-Counting Fleet (Unreg) | J51: Total | K51: Budget | L51: Non-Counting Fleet (Reg) | M51: Non-Counting Fleet (Unreg) | N51: Total | O51: Budget | R51: Non-Counting Fleet (Reg) | S51: Non-Counting Fleet (Unreg) | T51: Total | U51: Budget
A52: Salford | C52: 127 | D52: 0 | E52: =SUM(C52:D52) -> 127 | F52: 170 | G52: 199 | H52: 0 | J52: =SUM(G52:H52) -> 199 | K52: 159 | L52: 192 | M52: 0 | N52: =SUM(L52:M52) -> 192 | O52: 128 | Q52: =B52 -> 0 | R52: =L52+G52+C52 -> 518 | S52: =M52+H52+D52 -> 0 | T52: =SUM(Q52:S52) -> 518 | U52: =O52+K52+F52 -> 457 | X52: 46006 | Y52: gb
A53: NORTH CDA | C53: =SUM(C52) -> 127 | D53: =SUM(D52) -> 0 | E53: =SUM(E52) -> 127 | F53: =SUM(F52) -> 170 | G53: =SUM(G52) -> 199 | H53: =SUM(H52) -> 0 | J53: =SUM(J52) -> 199 | K53: =SUM(K52) -> 159 | L53: =SUM(L52) -> 192 | M53: =SUM(M52) -> 0 | N53: =SUM(N52) -> 192 | O53: =SUM(O52) -> 128 | Q53: =B53 -> 0 | R53: =SUM(R52) -> 518 | S53: =SUM(S52) -> 0 | T53: =SUM(T52) -> 518 | U53: =SUM(U52) -> 457
A54: Denton | C54: 14 | D54: 0 | E54: =SUM(C54:D54) -> 14 | F54: 32 | G54: 6 | H54: 0 | J54: =SUM(G54:H54) -> 6 | K54: 25 | L54: 24 | M54: 0 | N54: 10 | O54: 40 | Q54: =B54 -> 0 | R54: =L54+G54+P58+C54 -> 44 | S54: =M54+H54+D54 -> 0 | T54: =SUM(Q54:S54) -> 44 | U54: =O54+K54+F54 -> 97 | X54: 46022 | Y54: NF
A55: SOUTH CDA | C55: =SUM(C54) -> 14 | D55: =SUM(D54) -> 0 | E55: =SUM(E54) -> 14 | F55: =SUM(F54) -> 32 | G55: =SUM(G54) -> 6 | H55: =SUM(H54) -> 0 | J55: =SUM(J54) -> 6 | K55: =SUM(K54) -> 25 | L55: =SUM(L54) -> 24 | M55: =SUM(M54) -> 0 | N55: =SUM(N54) -> 10 | O55: =SUM(O54) -> 40 | Q55: =B55 -> 0 | R55: =SUM(R54) -> 44 | S55: =SUM(S54) -> 0 | T55: =SUM(T54) -> 44 | U55: =SUM(U54) -> 97
A56: Bradford | C56: 144 | D56: 0 | E56: =SUM(C56:D56) -> 144 | F56: 49 | G56: 61 | H56: 0 | J56: =SUM(G56:H56) -> 61 | K56: 40 | L56: 49 | M56: 0 | N56: =SUM(L56:M56) -> 49 | O56: 32 | Q56: =B56 -> 0 | R56: =L56+G56+C56 -> 254 | S56: =M56+H56+D56 -> 0 | T56: =SUM(Q56:S56) -> 254 | U56: =O56+K56+F56 -> 121
C57: =SUM(C56) -> 144 | D57: =SUM(D56) -> 0 | E57: =SUM(E56) -> 144 | F57: =SUM(F56) -> 49 | G57: =SUM(G56) -> 61 | H57: =SUM(H56) -> 0 | J57: =SUM(J56) -> 61 | K57: =SUM(K56) -> 40 | L57: =SUM(L56) -> 49 | M57: =SUM(M56) -> 0 | N57: =SUM(N56) -> 49 | O57: =SUM(O56) -> 32 | Q57: =B57 -> 0 | R57: =SUM(R56) -> 254 | S57: =SUM(S56) -> 0 | T57: =SUM(T56) -> 254 | U57: =SUM(U56) -> 121 | X57: 46022 | Y57: PS
Q58: =B58 -> 0
A60: TOTAL | C60: =C57+C55+C53 -> 285 | D60: =D57+D55+D53 -> 0 | E60: =E57+E55+E53 -> 285 | F60: =F57+F55+F53 -> 251 | G60: =G57+G55+G53 -> 266 | H60: =H57+H55+H53 -> 0 | J60: =J57+J55+J53 -> 266 | K60: =K57+K55+K53 -> 224 | L60: =L57+L55+L53 -> 265 | M60: =M57+M55+M53 -> 0 | N60: =N57+N55+N53 -> 251 | O60: =O57+O55+O53 -> 200 | R60: =R57+R55+R53 -> 816 | S60: =S57+S55+S53 -> 0 | T60: =T57+T55+T53 -> 816 | U60: =U57+U55+U53 -> 675
A62: USED COUNTING VOLUME | P62: Updated | Q62: By
B63: =C50 -> OCT | F63: =G50 -> NOV | J63: =L50 -> DEC | N63: TOTAL
B64: B/FWD | C64: Counting | D64: Target | F64: Counting | G64: Target | J64: Counting | K64: Target | M64: B/FWD | N64: Counting | O64: Target
A65: Bolton | C65: 69 | D65: 48 | E65: =C65/D65 -> 1.4375 | F65: 49 | G65: 45 | H65: =F65/G65 -> 1.0888889 | J65: 23 | K65: 32 | L65: =J65/K65 -> 0.71875 | M65: =B65 -> 0 | N65: =J65+F65+C65 -> 141 | O65: =K65+G65+D65 -> 125 | Q65: gb
A66: Bury | C66: 47 | D66: 47 | E66: =C66/D66 -> 1 | F66: 36 | G66: 43 | H66: =F66/G66 -> 0.8372093 | J66: 29 | K66: 31 | L66: =J66/K66 -> 0.93548387 | M66: =B66 -> 0 | N66: =J66+F66+C66 -> 112 | O66: =K66+G66+D66 -> 121 | Q66: gb
A67: Rochdale | C67: 46 | D67: 59 | E67: =C67/D67 -> 0.77966102 | F67: 40 | G67: 54 | H67: =F67/G67 -> 0.74074074 | J67: 23 | K67: 39 | L67: =J67/K67 -> 0.58974359 | M67: =B67 -> 0 | N67: =J67+F67+C67 -> 109 | O67: =K67+G67+D67 -> 152 | P67: 46024 | Q67: gb
A68: SQ | C68: 64 | D68: 62 | E68: =C68/D68 -> 1.0322581 | F68: 50 | G68: 57 | H68: =F68/G68 -> 0.87719298 | J68: 32 | K68: 40 | L68: =J68/K68 -> 0.8 | M68: =B68 -> 0 | N68: =J68+F68+C68 -> 146 | O68: =K68+G68+D68 -> 159 | P68: 46024 | Q68: gb
A69: NORTH CDA | B69: =SUM(B65:B68) -> 0 | C69: =SUM(C65:C68) -> 226 | D69: =SUM(D65:D68) -> 216 | E69: =C69/D69 -> 1.0462963 | F69: =SUM(F65:F68) -> 175 | G69: =SUM(G65:G68) -> 199 | H69: =F69/G69 -> 0.87939698 | J69: =SUM(J65:J68) -> 107 | K69: =SUM(K65:K68) -> 142 | L69: =J69/K69 -> 0.75352113 | M69: =SUM(M65:M68) -> 0 | N69: =SUM(N65:N68) -> 508 | O69: =SUM(O65:O68) -> 557
A70: Altrincham | C70: 43 | D70: 44 | E70: =C70/D70 -> 0.97727273 | F70: 42 | G70: 41 | H70: =F70/G70 -> 1.0243902 | J70: 28 | K70: 28 | L70: =J70/K70 -> 1 | M70: =B70 -> 0 | N70: =J70+F70+C70 -> 113 | O70: =K70+G70+D70 -> 113 | P70: 46020 | Q70: NF
A71: Denton | C71: 36 | D71: 51 | E71: =C71/D71 -> 0.70588235 | F71: 27 | G71: 47 | H71: =F71/G71 -> 0.57446809 | J71: 31 | K71: 33 | L71: =J71/K71 -> 0.93939394 | M71: =B71 -> 0 | N71: =J71+F71+C71 -> 94 | O71: =K71+G71+D71 -> 131 | P71: 46020 | Q71: NF
A72: Macclesfield | C72: 44 | D72: 41 | E72: =C72/D72 -> 1.0731707 | F72: 27 | G72: 38 | H72: =F72/G72 -> 0.71052632 | J72: 28 | K72: 25 | L72: =J72/K72 -> 1.12 | M72: =B72 -> 0 | N72: =J72+F72+C72 -> 99 | O72: =K72+G72+D72 -> 104 | P72: 46020 | Q72: NF
A73: Stockport | C73: 88 | D73: 94 | E73: =C73/D73 -> 0.93617021 | F73: 63 | G73: 86 | H73: =F73/G73 -> 0.73255814 | J73: 54 | K73: 60 | L73: =J73/K73 -> 0.9 | M73: =B73 -> 0 | N73: =J73+F73+C73 -> 205 | O73: =K73+G73+D73 -> 240 | P73: 46020 | Q73: NF
A74: SOUTH CDA | B74: =SUM(B70:B73) -> 0 | C74: =SUM(C70:C73) -> 211 | D74: =SUM(D70:D73) -> 230 | E74: =C74/D74 -> 0.9173913 | F74: =SUM(F70:F73) -> 159 | G74: =SUM(G70:G73) -> 212 | H74: =F74/G74 -> 0.75 | J74: =SUM(J70:J73) -> 141 | K74: =SUM(K70:K73) -> 146 | L74: =J74/K74 -> 0.96575342 | M74: =SUM(M70:M73) -> 0 | N74: =SUM(N70:N73) -> 511 | O74: =SUM(O70:O73) -> 588
A75: Bradford | C75: 33 | D75: 38 | E75: =C75/D75 -> 0.86842105 | F75: 25 | G75: 35 | H75: =F75/G75 -> 0.71428571 | J75: 23 | K75: 25 | L75: =J75/K75 -> 0.92 | M75: =B75 -> 0 | N75: =J75+F75+C75 -> 81 | O75: =K75+G75+D75 -> 98 | P75: 46020 | Q75: PS
A76: Huddersfield | C76: 39 | D76: 51 | E76: =C76/D76 -> 0.76470588 | F76: 27 | G76: 47 | H76: =F76/G76 -> 0.57446809 | J76: 23 | K76: 33 | L76: =J76/K76 -> 0.6969697 | M76: =B76 -> 0 | N76: =J76+F76+C76 -> 89 | O76: =K76+G76+D76 -> 131 | P76: 46020 | Q76: PS
A77: Silsden | C77: 24 | D77: 23 | E77: =C77/D77 -> 1.0434783 | F77: 11 | G77: 21 | H77: =F77/G77 -> 0.52380952 | J77: 7 | K77: 15 | L77: =J77/K77 -> 0.46666667 | M77: =B77 -> 0 | N77: =J77+F77+C77 -> 42 | O77: =K77+G77+D77 -> 59 | P77: 46020 | Q77: PS
A78: WY CDA | B78: =SUM(B75:B77) -> 0 | C78: =SUM(C75:C77) -> 96 | D78: =SUM(D75:D77) -> 112 | E78: =C78/D78 -> 0.85714286 | F78: =SUM(F75:F77) -> 63 | G78: =SUM(G75:G77) -> 103 | H78: =F78/G78 -> 0.61165049 | J78: =SUM(J75:J77) -> 53 | K78: =SUM(K75:K77) -> 73 | L78: =J78/K78 -> 0.7260274 | M78: =SUM(M75:M77) -> 0 | N78: =SUM(N75:N77) -> 212 | O78: =SUM(O75:O77) -> 288
A81: TOTAL | B81: =B78+B74+B69 -> 0 | C81: =C78+C74+C69 -> 533 | D81: =D78+D74+D69 -> 558 | E81: =C81/D81 -> 0.95519713 | F81: =F78+F74+F69 -> 397 | G81: =G78+G74+G69 -> 514 | H81: =F81/G81 -> 0.77237354 | J81: =J78+J74+J69 -> 301 | K81: =K78+K74+K69 -> 361 | L81: =J81/K81 -> 0.83379501 | M81: =M78+M74+M69 -> 0 | N81: =N78+N74+N69 -> 1231 | O81: =O78+O74+O69 -> 1433

Sheet 2025 - Q3
A3: REGISTRATIONS (COUNTING) | AD3: Updated | AE3: By
C4: JULY | H4: AUG | M4: SEP | U4: TOTAL
B5: B/FWD | C5: Counting | D5: Counting Fleet | E5: Total | F5: Target | H5: Counting | I5: Counting Fleet | J5: Total | K5: Target | M5: Counting | N5: CLCP Regs | O5: Double Counters | P5: Counting Fleet | Q5: Total | R5: Target | T5: B/FWD | U5: Counting | V5: Counting Fleet | W5: Total | X5: Target | Y5: TO GO | Z5: PER WEEK | AA5: QTR REGS | AB5: TARGET | AC5: REGS v TGT | AF5: 45908 | AG5: CLCP | AH5: TARGET TO 1,200 | AI5: FINAL PROJECTED | AK5: Current GAP
A6: Bolton | C6: 19 | D6: 3 | E6: =SUM(C6:D6) -> 22 | F6: 34 | G6: =E6/F6 -> 0.64705882 | H6: 16 | I6: 1 | J6: =SUM(H6:I6) -> 17 | K6: 10 | L6: =J6/K6 -> 1.7 | M6: 77 | N6: 10 | O6: 4 | P6: 1 | Q6: =SUM(M6:P6) -> 92 | R6: 98 | S6: =Q6/R6 -> 0.93877551 | U6: =M6+H6+C6+N6+O6 -> 126 | V6: =P6+I6+D6 -> 5 | W6: =SUM(T6:V6) -> 131 | X6: =R6+K6+F6 -> 142 | Y6: =X6-W6 -> 11 | Z6: =ROUND(Y6/$Z$26*7,0) -> 0 | AA6: =V6+U6 -> 131 | AB6: =X6 -> 142 | AC6: =(U6+V6)/X6 -> 0.92253521 | AD6: 45930 | AE6: gb
A7: Bury | C7: 20 | E7: =SUM(C7:D7) -> 20 | F7: 26 | G7: =E7/F7 -> 0.76923077 | H7: 3 | J7: =SUM(H7:I7) -> 3 | K7: 10 | L7: =J7/K7 -> 0.3 | M7: 52 | N7: 12 | O7: 3 | Q7: =SUM(M7:P7) -> 67 | R7: 84 | S7: =Q7/R7 -> 0.79761905 | U7: =M7+H7+C7+N7+O7 -> 90 | V7: =P7+I7+D7 -> 0 | W7: =SUM(T7:V7) -> 90 | X7: =R7+K7+F7 -> 120 | Y7: =X7-W7 -> 30 | Z7: =ROUND(Y7/$Z$26*7,0) -> -1 | AA7: =V7+U7 -> 90 | AB7: =X7 -> 120 | AC7: =(U7+V7)/X7 -> 0.75 | AD7: 45930 | AE7: gb
A8: Rochdale | C8: 26 | E8: =SUM(C8:D8) -> 26 | F8: 36 | G8: =E8/F8 -> 0.72222222 | H8: 4 | J8: =SUM(H8:I8) -> 4 | K8: 10 | L8: =J8/K8 -> 0.4 | M8: 79 | N8: 11 | O8: 3 | Q8: =SUM(M8:P8) -> 93 | R8: 104 | S8: =Q8/R8 -> 0.89423077 | U8: =M8+H8+C8+N8+O8 -> 123 | V8: =P8+I8+D8 -> 0 | W8: =SUM(T8:V8) -> 123 | X8: =R8+K8+F8 -> 150 | Y8: =X8-W8 -> 27 | Z8: =ROUND(Y8/$Z$26*7,0) -> -1 | AA8: =V8+U8 -> 123 | AB8: =X8 -> 150 | AC8: =(U8+V8)/X8 -> 0.82 | AD8: 45930 | AE8: gb
A9: SQ | C9: 42 | D9: 4 | E9: =SUM(C9:D9) -> 46 | F9: 40 | G9: =E9/F9 -> 1.15 | H9: 17 | I9: 1 | J9: =SUM(H9:I9) -> 18 | K9: 15 | L9: =J9/K9 -> 1.2 | M9: 72 | N9: 14 | O9: 3 | P9: 4 | Q9: =SUM(M9:P9) -> 93 | R9: 124 | S9: =Q9/R9 -> 0.75 | U9: =M9+H9+C9+N9+O9 -> 148 | V9: =P9+I9+D9 -> 9 | W9: =SUM(T9:V9) -> 157 | X9: =R9+K9+F9 -> 179 | Y9: =X9-W9 -> 22 | Z9: =ROUND(Y9/$Z$26*7,0) -> 0 | AA9: =V9+U9 -> 157 | AB9: =X9 -> 179 | AC9: =(U9+V9)/X9 -> 0.87709497 | AD9: 45930 | AE9: gb
A10: NORTH CDA | B10: =SUM(B6:B9) -> 0 | C10: =SUM(C6:C9) -> 107 | D10: =SUM(D6:D9) -> 7 | E10: =SUM(E6:E9) -> 114 | F10: =SUM(F6:F9) -> 136 | G10: =E10/F10 -> 0.83823529 | H10: =SUM(H6:H9) -> 40 | I10: =SUM(I6:I9) -> 2 | J10: =SUM(J6:J9) -> 42 | K10: =SUM(K6:K9) -> 45 | L10: =J10/K10 -> 0.93333333 | M10: =SUM(M6:M9) -> 280 | N10: =SUM(N6:N9) -> 47 | O10: =SUM(O6:O9) -> 13 | P10: =SUM(P6:P9) -> 5 | Q10: =SUM(Q6:Q9) -> 345 | R10: =SUM(R6:R9) -> 410 | S10: =Q10/R10 -> 0.84146341 | T10: =SUM(T6:T9) -> 0 | U10: =SUM(U6:U9) -> 487 | V10: =SUM(V6:V9) -> 14 | W10: =SUM(W6:W9) -> 501 | X10: =SUM(X6:X9) -> 591 | Y10: =SUM(Y6:Y9) -> 90 | Z10: =ROUND(Y10/$Z$26*7,0) -> -2 | AA10: =SUM(AA6:AA9) -> 501 | AB10: =SUM(AB6:AB9) -> 591 | AC10: =AA10/AB10 -> 0.84771574 | AF10: 400 | AG10: =12*4 -> 48 | AH10: 48 | AI10: =AF10+AG10+AH10 -> 496 | AJ10: =AI10/X10 -> 0.8392555 | AK10: =AI10-W10 -> -5
A11: Altrincham | C11: 19 | E11: =SUM(C11:D11) -> 19 | F11: 28 | G11: =E11/F11 -> 0.67857143 | H11: 11 | J11: =SUM(H11:I11) -> 11 | K11: 9 | L11: =J11/K11 -> 1.2222222 | M11: 39 | N11: 9 | O11: 3 | Q11: =SUM(M11:P11) -> 51 | R11: 88 | S11: =Q11/R11 -> 0.57954545 | U11: =M11+H11+C11+N11+O11 -> 81 | V11: =P11+I11+D11 -> 0 | W11: =SUM(T11:V11) -> 81 | X11: =R11+K11+F11 -> 125 | Y11: =X11-W11 -> 44 | Z11: =ROUND(Y11/$Z$26*7,0) -> -1 | AA11: =V11+U11 -> 81 | AB11: =X11 -> 125 | AC11: =(U11+V11)/X11 -> 0.648 | AE11: NF
A12: Denton | C12: 15 | E12: =SUM(C12:D12) -> 15 | F12: 33 | G12: =E12/F12 -> 0.45454545 | H12: 16 | J12: =SUM(H12:I12) -> 16 | K12: 10 | L12: =J12/K12 -> 1.6 | M12: 79 | N12: 11 | O12: 2 | Q12: =SUM(M12:P12) -> 92 | R12: 100 | S12: =Q12/R12 -> 0.92 | U12: =M12+H12+C12+N12+O12 -> 123 | V12: =P12+I12+D12 -> 0 | W12: =SUM(T12:V12) -> 123 | X12: =R12+K12+F12 -> 143 | Y12: =X12-W12 -> 20 | Z12: =ROUND(Y12/$Z$26*7,0) -> 0 | AA12: =V12+U12 -> 123 | AB12: =X12 -> 143 | AC12: =(U12+V12)/X12 -> 0.86013986 | AE12: NF
A13: Macclesfield | C13: 13 | E13: =SUM(C13:D13) -> 13 | F13: 32 | G13: =E13/F13 -> 0.40625 | H13: 5 | J13: =SUM(H13:I13) -> 5 | K13: 12 | L13: =J13/K13 -> 0.41666667 | M13: 81 | N13: 10 | O13: 3 | Q13: =SUM(M13:P13) -> 94 | R13: 103 | S13: =Q13/R13 -> 0.91262136 | U13: =M13+H13+C13+N13+O13 -> 112 | V13: =P13+I13+D13 -> 0 | W13: =SUM(T13:V13) -> 112 | X13: =R13+K13+F13 -> 147 | Y13: =X13-W13 -> 35 | Z13: =ROUND(Y13/$Z$26*7,0) -> -1 | AA13: =V13+U13 -> 112 | AB13: =X13 -> 147 | AC13: =(U13+V13)/X13 -> 0.76190476 | AE13: NF
A14: Stockport | C14: 33 | E14: =SUM(C14:D14) -> 33 | F14: 44 | G14: =E14/F14 -> 0.75 | H14: 6 | J14: =SUM(H14:I14) -> 6 | K14: 18 | L14: =J14/K14 -> 0.33333333 | M14: 96 | N14: 16 | O14: 3 | P14: 0 | Q14: =SUM(M14:P14) -> 115 | R14: 140 | S14: =Q14/R14 -> 0.82142857 | U14: =M14+H14+C14+N14+O14 -> 154 | V14: =P14+I14+D14 -> 0 | W14: =SUM(T14:V14) -> 154 | X14: =R14+K14+F14 -> 202 | Y14: =X14-W14 -> 48 | Z14: =ROUND(Y14/$Z$26*7,0) -> -1 | AA14: =V14+U14 -> 154 | AB14: =X14 -> 202 | AC14: =(U14+V14)/X14 -> 0.76237624 | AE14: NF
A15: SOUTH CDA | B15: =SUM(B11:B14) -> 0 | C15: =SUM(C11:C14) -> 80 | D15: =SUM(D11:D14) -> 0 | E15: =SUM(E11:E14) -> 80 | F15: =SUM(F11:F14) -> 137 | G15: =E15/F15 -> 0.58394161 | H15: =SUM(H11:H14) -> 38 | I15: =SUM(I11:I14) -> 0 | J15: =SUM(J11:J14) -> 38 | K15: =SUM(K11:K14) -> 49 | L15: =J15/K15 -> 0.7755102 | M15: =SUM(M11:M14) -> 295 | N15: =SUM(N11:N14) -> 46 | O15: =SUM(O11:O14) -> 11 | P15: =SUM(P11:P14) -> 0 | Q15: =SUM(Q11:Q14) -> 352 | R15: =SUM(R11:R14) -> 431 | S15: =Q15/R15 -> 0.81670534 | T15: =SUM(T11:T14) -> 0 | U15: =SUM(U11:U14) -> 470 | V15: =SUM(V11:V14) -> 0 | W15: =SUM(W11:W14) -> 470 | X15: =SUM(X11:X14) -> 617 | Y15: =SUM(Y11:Y14) -> 147 | Z15: =ROUND(Y15/$Z$26*7,0) -> -3 | AA15: =SUM(AA11:AA14) -> 470 | AB15: =SUM(AB11:AB14) -> 617 | AC15: =AA15/AB15 -> 0.76175041 | AF15: 363 | AG15: 48 | AH15: 56 | AI15: =AF15+AG15+AH15 -> 467 | AJ15: =AI15/X15 -> 0.75688817 | AK15: =AI15-W15 -> -3
A16: Bradford | C16: 15 | D16: 9 | E16: =SUM(C16:D16) -> 24 | F16: 32 | G16: =E16/F16 -> 0.75 | H16: 2 | I16: 3 | J16: =SUM(H16:I16) -> 5 | K16: 11 | L16: =J16/K16 -> 0.45454545 | M16: 32 | N16: 16 | O16: 9 | P16: 4 | Q16: =SUM(M16:P16) -> 61 | R16: 101 | S16: =Q16/R16 -> 0.6039604 | U16: =M16+H16+C16+N16+O16 -> 74 | V16: =P16+I16+D16 -> 16 | W16: =SUM(T16:V16) -> 90 | X16: =R16+K16+F16 -> 144 | Y16: =X16-W16 -> 54 | Z16: =ROUND(Y16/$Z$26*7,0) -> -1 | AA16: =V16+U16 -> 90 | AB16: =X16 -> 144 | AC16: =(U16+V16)/X16 -> 0.625 | AD16: 45930 | AE16: PS
A17: Huddersfield | C17: 28 | E17: =SUM(C17:D17) -> 28 | F17: 31 | G17: =E17/F17 -> 0.90322581 | H17: 7 | J17: =SUM(H17:I17) -> 7 | K17: 9 | L17: =J17/K17 -> 0.77777778 | M17: 59 | N17: 15 | O17: 5 | Q17: =SUM(M17:P17) -> 79 | R17: 90 | S17: =Q17/R17 -> 0.87777778 | U17: =M17+H17+C17+N17+O17 -> 114 | V17: =P17+I17+D17 -> 0 | W17: =SUM(T17:V17) -> 114 | X17: =R17+K17+F17 -> 130 | Y17: =X17-W17 -> 16 | Z17: =ROUND(Y17/$Z$26*7,0) -> 0 | AA17: =V17+U17 -> 114 | AB17: =X17 -> 130 | AC17: =(U17+V17)/X17 -> 0.87692308 | AD17: 45930 | AE17: PS
A18: Silsden | C18: 11 | E18: =SUM(C18:D18) -> 11 | F18: 12 | G18: =E18/F18 -> 0.91666667 | H18: 7 | J18: =SUM(H18:I18) -> 7 | K18: 3 | L18: =J18/K18 -> 2.3333333 | M18: 15 | N18: 5 | O18: 2 | Q18: =SUM(M18:P18) -> 22 | R18: 35 | S18: =Q18/R18 -> 0.62857143 | U18: =M18+H18+C18+N18+O18 -> 40 | V18: =P18+I18+D18 -> 0 | W18: =SUM(T18:V18) -> 40 | X18: =R18+K18+F18 -> 50 | Y18: =X18-W18 -> 10 | Z18: =ROUND(Y18/$Z$26*7,0) -> 0 | AA18: =V18+U18 -> 40 | AB18: =X18 -> 50 | AC18: =(U18+V18)/X18 -> 0.8 | AD18: 45930 | AE18: PS
A19: WY CDA | B19: =SUM(B16:B18) -> 0 | C19: =SUM(C16:C18) -> 54 | D19: =SUM(D16:D18) -> 9 | E19: =SUM(E16:E18) -> 63 | F19: =SUM(F16:F18) -> 75 | G19: =E19/F19 -> 0.84 | H19: =SUM(H16:H18) -> 16 | I19: =SUM(I16:I18) -> 3 | J19: =SUM(J16:J18) -> 19 | K19: =SUM(K16:K18) -> 23 | L19: =J19/K19 -> 0.82608696 | M19: =SUM(M16:M18) -> 106 | N19: =SUM(N16:N18) -> 36 | O19: =SUM(O16:O18) -> 16 | P19: =SUM(P16:P18) -> 4 | Q19: =SUM(Q16:Q18) -> 162 | R19: =SUM(R16:R18) -> 226 | S19: =Q19/R19 -> 0.71681416 | T19: =SUM(T16:T18) -> 0 | U19: =SUM(U16:U18) -> 228 | V19: =SUM(V16:V18) -> 16 | W19: =SUM(W16:W18) -> 244 | X19: =SUM(X16:X18) -> 324 | Y19: =SUM(Y16:Y18) -> 80 | Z19: =ROUND(Y19/$Z$26*7,0) -> -1 | AA19: =SUM(AA16:AA18) -> 244 | AB19: =SUM(AB16:AB18) -> 324 | AC19: =AA19/AB19 -> 0.75308642 | AF19: 186 | AG19: 24 | AH19: 27 | AI19: =AF19+AG19+AH19 -> 237 | AJ19: =AI19/X19 -> 0.73148148 | AK19: =AI19-W19 -> -7
A22: TOTAL | B22: =B19+B15+B10 -> 0 | C22: =C19+C15+C10 -> 241 | D22: =D19+D15+D10 -> 16 | E22: =E19+E15+E10 -> 257 | F22: =F19+F15+F10 -> 348 | G22: =E22/F22 -> 0.73850575 | H22: =H19+H15+H10 -> 94 | I22: =I19+I15+I10 -> 5 | J22: =J19+J15+J10 -> 99 | K22: =K19+K15+K10 -> 117 | L22: =J22/K22 -> 0.84615385 | M22: =M19+M15+M10 -> 681 | N22: =N19+N15+N10 -> 129 | O22: =O19+O15+O10 -> 40 | P22: =P19+P15+P10 -> 9 | Q22: =Q19+Q15+Q10 -> 859 | R22: =R19+R15+R10 -> 1067 | S22: =Q22/R22 -> 0.80506092 | T22: =T19+T15+T10 -> 0 | U22: =U19+U15+U10 -> 1185 | V22: =V19+V15+V10 -> 30 | W22: =W19+W15+W10 -> 1215 | X22: =X19+X15+X10 -> 1532 | Y22: =Y19+Y15+Y10 -> 317 | Z22: =ROUND(Y22/$Z$26*7,0) -> -6 | AA22: =AA19+AA15+AA10 -> 1215 | AB22: =AB19+AB15+AB10 -> 1532 | AC22: =(U22+V22)/X22 -> 0.79308094 | AG22: =SUM(AG10:AG21) -> 120 | AH22: =SUM(AH10:AH21) -> 131 | AI22: =SUM(AI10:AI21) -> 1200 | AJ22: =AI22/X22 -> 0.78328982 | AK22: =SUM(AK10:AK21) -> -15
AI23: =ROUNDUP(X22*AJ23,0) -> 1226 | AJ23: 0.8
Z24: 45930 | AB24: =AB22-AA22 -> 317
A25: SEPT-DEC - FLEET TARGETS | Z25: =TODAY()-1 -> 46307
Z26: =Z24-Z25 -> -377
B27: Total | C27: Target | D27: TO GO (100%) | F27: UNREG ORDERS
A28: Salford | B28: 3 | C28: =12+11 -> 23 | D28: =C28-B28 -> 20 | I28: Kinto One
A29: Bolton | B29: 1 | C29: =6+7 -> 13 | D29: =C29-B29 -> 12 | I29: Kinto Fleet Partnership
A30: Bury | C30: =5+6 -> 11 | D30: =C30-B30 -> 11 | I30: Kinto PCH
A31: Rochdale | C31: =7+7 -> 14 | D31: =C31-B31 -> 14 | I31: Centre Fleet
A32: NORTH CDA | B32: =SUM(B28:B31) -> 4 | C32: =SUM(C28:C31) -> 61 | D32: =SUM(D28:D31) -> 57 | F32: =SUM(F28:F31) -> 0
A34: Macclesfield | B34: 1 | C34: =7+6 -> 13 | D34: =C34-B34 -> 12
A35: Denton | B35: 1 | C35: =9+9 -> 18 | D35: =C35-B35 -> 17 | F35: 1
A36: Altrincham | C36: =5+6 -> 11 | D36: =C36-B36 -> 11
A37: Stockport | C37: =9+9 -> 18 | D37: =C37-B37 -> 18
A38: SOUTH CDA | B38: =SUM(B34:B37) -> 2 | C38: =SUM(C34:C37) -> 60 | D38: =SUM(D34:D37) -> 58 | F38: =SUM(F34:F37) -> 1
A40: Bradford | B40: 3 | C40: =9+9 -> 18 | D40: =C40-B40 -> 15 | F40: 6
A41: Huddersfield | C41: =5+6 -> 11 | D41: =C41-B41 -> 11
A42: Silsden | C42: =2+3 -> 5 | D42: =C42-B42 -> 5
A43: WY CDA | B43: =SUM(B40:B42) -> 3 | C43: =SUM(C40:C42) -> 34 | D43: =SUM(D40:D42) -> 31 | F43: =SUM(F40:F42) -> 6
A46: TOTAL | B46: =B43+B38+B32 -> 9 | C46: =C43+C38+C32 -> 155 | D46: =D43+D38+D32 -> 146 | F46: =F43+F38+F32 -> 7
A49: REGISTRATIONS (NON-COUNTING) | W49: Updated | X49: By
C50: =C4 -> JULY | G50: =H4 -> AUG | K50: =M4 -> SEP | Q50: TOTAL
C51: Non-Counting Fleet (Reg) | D51: Non-Counting Fleet (Unreg) | E51: Total | F51: Budget | G51: Non-Counting Fleet (Reg) | H51: Non-Counting Fleet (Unreg) | I51: Total | J51: Budget | K51: Non-Counting Fleet (Reg) | L51: Non-Counting Fleet (Unreg) | M51: Total | N51: Budget | Q51: Non-Counting Fleet (Reg) | R51: Non-Counting Fleet (Unreg) | S51: Total | T51: Budget
A52: Salford | C52: 146 | D52: 0 | E52: =SUM(C52:D52) -> 146 | F52: 127 | G52: 81 | H52: 0 | I52: =SUM(G52:H52) -> 81 | J52: 81 | K52: 346 | L52: 0 | M52: =SUM(K52:L52) -> 346 | N52: 315 | P52: =B52 -> 0 | Q52: =K52+G52+C52 -> 573 | R52: =L52+H52+D52 -> 0 | S52: =SUM(P52:R52) -> 573 | T52: =N52+J52+F52 -> 523 | W52: 45929 | X52: GB
A53: NORTH CDA | C53: =SUM(C52) -> 146 | D53: =SUM(D52) -> 0 | E53: =SUM(E52) -> 146 | F53: =SUM(F52) -> 127 | G53: =SUM(G52) -> 81 | H53: =SUM(H52) -> 0 | I53: =SUM(I52) -> 81 | J53: =SUM(J52) -> 81 | ... N53: =SUM(N52) -> 315 | P53: =B53 -> 0 | Q53: =SUM(Q52) -> 573 | R53: =SUM(R52) -> 0 | S53: =SUM(S52) -> 573 | T53: =SUM(T52) -> 523
A54: Denton | C54: 27 | E54: =SUM(C54:D54) -> 27 | F54: 25 | G54: 31 | H54: 0 | I54: =SUM(G54:H54) -> 31 | J54: 15 | K54: 45 | L54: 0 | M54: =SUM(K54:L54) -> 45 | N54: 63 | P54: =B54 -> 0 | Q54: =K54+G54+O58+C54 -> 103 | R54: =L54+H54+D54 -> 0 | S54: =SUM(P54:R54) -> 103 | T54: =N54+J54+F54 -> 103 | W54: 45922 | X54: NF
A55: SOUTH CDA | C55: =SUM(C54) -> 27 | D55: =SUM(D54) -> 0 | E55: =SUM(E54) -> 27 | F55: =SUM(F54) -> 25 | G55: =SUM(G54) -> 31 | H55: =SUM(H54) -> 0 | I55: =SUM(I54) -> 31 | J55: =SUM(J54) -> 15 | ... N55: =SUM(N54) -> 63 | P55: =B55 -> 0 | Q55: =SUM(Q54) -> 103 | R55: =SUM(R54) -> 0 | S55: =SUM(S54) -> 103 | T55: =SUM(T54) -> 103
A56: Bradford | C56: 87 | D56: 0 | E56: =SUM(C56:D56) -> 87 | F56: 39 | G56: 108 | H56: 0 | I56: =SUM(G56:H56) -> 108 | J56: 19 | K56: 177 | L56: 0 | M56: =SUM(K56:L56) -> 177 | N56: 71 | P56: =B56 -> 0 | Q56: =K56+G56+C56 -> 372 | R56: =L56+H56+D56 -> 0 | S56: =SUM(P56:R56) -> 372 | T56: =N56+J56+F56 -> 129 | W56: 45930 | X56: PS
C57: =SUM(C56) -> 87 | D57: =SUM(D56) -> 0 | E57: =SUM(E56) -> 87 | F57: =SUM(F56) -> 39 | G57: =SUM(G56) -> 108 | H57: =SUM(H56) -> 0 | I57: =SUM(I56) -> 108 | J57: =SUM(J56) -> 19 | ... N57: =SUM(N56) -> 71 | P57: =B57 -> 0 | Q57: =SUM(Q56) -> 372 | R57: =SUM(R56) -> 0 | S57: =SUM(S56) -> 372 | T57: =SUM(T56) -> 129
P58: =B58 -> 0
A60: TOTAL | C60: =C57+C55+C53 -> 260 | D60: =D57+D55+D53 -> 0 | E60: =E57+E55+E53 -> 260 | F60: =F57+F55+F53 -> 191 | G60: =G57+G55+G53 -> 220 | H60: =H57+H55+H53 -> 0 | I60: =I57+I55+I53 -> 220 | J60: =J57+J55+J53 -> 115 | ... N60: =N57+N55+N53 -> 449 | Q60: =Q57+Q55+Q53 -> 1048 | R60: =R57+R55+R53 -> 0 | S60: =S57+S55+S53 -> 1048 | T60: =T57+T55+T53 -> 755
A62: USED COUNTING VOLUME | Q62: Updated | R62: By
B63: July | F63: August | I63: Sept | M63: TOTAL
B64: B/FWD | C64: Counting | D64: Target | F64: Counting | G64: Target | I64: Counting | J64: Target | L64: B/FWD | M64: Counting | N64: Target
A65: Bolton | C65: 61 | D65: 49 | E65: =C65/D65 -> 1.244898 | F65: 61 | G65: 48 | H65: =F65/G65 -> 1.2708333 | I65: 67 | J65: 48 | K65: =I65/J65 -> 1.3958333 | L65: =B65 -> 0 | M65: =I65+F65+C65 -> 189 | N65: =J65+G65+D65 -> 145 | O65: 45929 | P65: GB
A66: Bury | C66: 49 | D66: 47 | E66: =C66/D66 -> 1.0425532 | F66: 57 | G66: 46 | H66: =F66/G66 -> 1.2391304 | I66: 53 | J66: 46 | K66: =I66/J66 -> 1.1521739 | L66: =B66 -> 0 | M66: =I66+F66+C66 -> 159 | N66: =J66+G66+D66 -> 139 | O66: 45929 | P66: GB
A67: Rochdale | C67: 44 | D67: 60 | E67: =C67/D67 -> 0.73333333 | F67: 53 | G67: 58 | H67: =F67/G67 -> 0.9137931 | I67: 39 | J67: 58 | K67: =I67/J67 -> 0.67241379 | L67: =B67 -> 0 | M67: =I67+F67+C67 -> 136 | N67: =J67+G67+D67 -> 176 | O67: 45929 | P67: GB
A68: SQ | C68: 59 | D68: 62 | E68: =C68/D68 -> 0.9516129 | F68: 64 | G68: 61 | H68: =F68/G68 -> 1.0491803 | I68: 68 | J68: 61 | K68: =I68/J68 -> 1.1147541 | L68: =B68 -> 0 | M68: =I68+F68+C68 -> 191 | N68: =J68+G68+D68 -> 184 | O68: 45929 | P68: GB
A69: NORTH CDA | B69: =SUM(B65:B68) -> 0 | C69: =SUM(C65:C68) -> 213 | D69: =SUM(D65:D68) -> 218 | E69: =C69/D69 -> 0.97706422 | F69: =SUM(F65:F68) -> 235 | G69: =SUM(G65:G68) -> 213 | H69: =F69/G69 -> 1.1032864 | I69: =SUM(I65:I68) -> 227 | J69: =SUM(J65:J68) -> 213 | K69: =I69/J69 -> 1.0657277 | L69: =SUM(L65:L68) -> 0 | M69: =SUM(M65:M68) -> 675 | N69: =SUM(N65:N68) -> 644
A70: Altrincham | C70: 52 | D70: 45 | E70: =C70/D70 -> 1.1555556 | F70: 52 | G70: 44 | H70: =F70/G70 -> 1.1818182 | I70: 37 | J70: 44 | K70: =I70/J70 -> 0.84090909 | L70: =B70 -> 0 | M70: =I70+F70+C70 -> 141 | N70: =J70+G70+D70 -> 133 | O70: 45922 | P70: NF
A71: Denton | C71: 62 | D71: 51 | E71: =C71/D71 -> 1.2156863 | F71: 60 | G71: 50 | H71: =F71/G71 -> 1.2 | I71: 34 | J71: 50 | K71: =I71/J71 -> 0.68 | L71: =B71 -> 0 | M71: =I71+F71+C71 -> 156 | N71: =J71+G71+D71 -> 151 | O71: 45922 | P71: NF
A72: Macclesfield | C72: 52 | D72: 42 | E72: =C72/D72 -> 1.2380952 | F72: 44 | G72: 41 | H72: =F72/G72 -> 1.0731707 | I72: 34 | J72: 41 | K72: =I72/J72 -> 0.82926829 | L72: =B72 -> 0 | M72: =I72+F72+C72 -> 130 | N72: =J72+G72+D72 -> 124 | O72: 45922 | P72: NF
A73: Stockport | C73: 86 | D73: 95 | E73: =C73/D73 -> 0.90526316 | F73: 90 | G73: 93 | H73: =F73/G73 -> 0.96774194 | I73: 77 | J73: 93 | K73: =I73/J73 -> 0.82795699 | L73: =B73 -> 0 | M73: =I73+F73+C73 -> 253 | N73: =J73+G73+D73 -> 281 | O73: 45922 | P73: NF
A74: SOUTH CDA | B74: =SUM(B70:B73) -> 0 | C74: =SUM(C70:C73) -> 252 | D74: =SUM(D70:D73) -> 233 | E74: =C74/D74 -> 1.0815451 | F74: =SUM(F70:F73) -> 246 | G74: =SUM(G70:G73) -> 228 | H74: =F74/G74 -> 1.0789474 | I74: =SUM(I70:I73) -> 182 | J74: =SUM(J70:J73) -> 228 | K74: =I74/J74 -> 0.79824561 | L74: =SUM(L70:L73) -> 0 | M74: =SUM(M70:M73) -> 680 | N74: =SUM(N70:N73) -> 689
A75: Bradford | C75: 47 | D75: 38 | E75: =C75/D75 -> 1.2368421 | F75: 28 | G75: 37 | H75: =F75/G75 -> 0.75675676 | I75: 34 | J75: 37 | K75: =I75/J75 -> 0.91891892 | L75: =B75 -> 0 | M75: =I75+F75+C75 -> 109 | N75: =J75+G75+D75 -> 112 | O75: 45930 | P75: PS
A76: Huddersfield | C76: 50 | D76: 52 | E76: =C76/D76 -> 0.96153846 | F76: 59 | G76: 50 | H76: =F76/G76 -> 1.18 | I76: 53 | J76: 50 | K76: =I76/J76 -> 1.06 | L76: =B76 -> 0 | M76: =I76+F76+C76 -> 162 | N76: =J76+G76+D76 -> 152 | O76: 45930 | P76: PS
A77: Silsden | C77: 23 | D77: 23 | E77: =C77/D77 -> 1 | F77: 28 | G77: 22 | H77: =F77/G77 -> 1.2727273 | I77: 21 | J77: 22 | K77: =I77/J77 -> 0.95454545 | L77: =B77 -> 0 | M77: =I77+F77+C77 -> 72 | N77: =J77+G77+D77 -> 67 | O77: 45930 | P77: PS
A78: WY CDA | B78: =SUM(B75:B77) -> 0 | C78: =SUM(C75:C77) -> 120 | D78: =SUM(D75:D77) -> 113 | E78: =C78/D78 -> 1.0619469 | F78: =SUM(F75:F77) -> 115 | G78: =SUM(G75:G77) -> 109 | H78: =F78/G78 -> 1.0550459 | I78: =SUM(I75:I77) -> 108 | J78: =SUM(J75:J77) -> 109 | K78: =I78/J78 -> 0.99082569 | L78: =SUM(L75:L77) -> 0 | M78: =SUM(M75:M77) -> 343 | N78: =SUM(N75:N77) -> 331
A81: TOTAL | B81: =B78+B74+B69 -> 0 | C81: =C78+C74+C69 -> 585 | D81: =D78+D74+D69 -> 564 | E81: =C81/D81 -> 1.037234 | F81: =F78+F74+F69 -> 596 | G81: =G78+G74+G69 -> 550 | H81: =F81/G81 -> 1.0836364 | I81: =I78+I74+I69 -> 517 | J81: =J78+J74+J69 -> 550 | K81: =I81/J81 -> 0.94 | L81: =L78+L74+L69 -> 0 | M81: =M78+M74+M69 -> 1698 | N81: =N78+N74+N69 -> 1664

Sheet 2025 - Q2
A3: REGISTRATIONS (COUNTING) | AA3: Updated | AB3: By
C4: APRIL | H4: MAY | M4: JUNE | S4: TOTAL
B5: B/FWD | C5: Counting | D5: Counting Fleet | E5: Total | F5: Target | H5: Counting | I5: Counting Fleet | J5: Total | K5: Target | M5: Counting | N5: Counting Fleet | O5: Total | P5: Target | R5: B/FWD | S5: Counting | T5: Counting Fleet | U5: Total | V5: Target | W5: TO GO | X5: QTR REGS | Y5: TARGET | Z5: REGS v TGT
A6: Salford | B6: ='2025 - Q1'!U6-'2025 - Q1'!V6 -> 101 | C6: 39 | D6: 1 | E6: =SUM(C6:D6) -> 40 | F6: 35 | G6: =E6/F6 -> 1.1428571 | H6: 46 | I6: 2 | J6: =SUM(H6:I6) -> 48 | K6: 44 | L6: =J6/K6 -> 1.0909091 | M6: 33 | N6: 2 | O6: =SUM(M6:N6) -> 35 | P6: 51 | Q6: =O6/P6 -> 0.68627451 | R6: =B6 -> 101 | S6: =M6+H6+C6 -> 118 | T6: =N6+I6+D6 -> 5 | U6: =SUM(R6:T6) -> 224 | V6: =P6+K6+F6 -> 130 | W6: =V6-U6 -> -94 | X6: =T6+S6 -> 123 | Y6: =V6 -> 130 | Z6: =(S6+T6)/V6 -> 0.94615385 | AA6: 45838 | AB6: gb
A7: Bolton | B7: ='2025 - Q1'!U7-'2025 - Q1'!V7 -> -147 | C7: 18 | E7: =SUM(C7:D7) -> 18 | F7: 28 | G7: =E7/F7 -> 0.64285714 | H7: 28 | J7: =SUM(H7:I7) -> 28 | K7: 34 | L7: =J7/K7 -> 0.82352941 | M7: 39 | O7: =SUM(M7:N7) -> 39 | P7: 42 | Q7: =O7/P7 -> 0.92857143 | R7: =B7 -> -147 | S7: =M7+H7+C7 -> 85 | T7: =N7+I7+D7 -> 0 | U7: =SUM(R7:T7) -> -62 | V7: =P7+K7+F7 -> 104 | W7: =V7-U7 -> 166 | X7: =T7+S7 -> 85 | Y7: =V7 -> 104 | Z7: =(S7+T7)/V7 -> 0.81730769 | AA7: 45838 | AB7: gb
A8: Bury | B8: ='2025 - Q1'!U8-'2025 - Q1'!V8 -> 2 | C8: 14 | E8: =SUM(C8:D8) -> 14 | F8: 25 | G8: =E8/F8 -> 0.56 | H8: 20 | J8: =SUM(H8:I8) -> 20 | K8: 26 | L8: =J8/K8 -> 0.76923077 | M8: 25 | O8: =SUM(M8:N8) -> 25 | P8: 34 | Q8: =O8/P8 -> 0.73529412 | R8: =B8 -> 2 | S8: =M8+H8+C8 -> 59 | T8: =N8+I8+D8 -> 0 | U8: =SUM(R8:T8) -> 61 | V8: =P8+K8+F8 -> 85 | W8: =V8-U8 -> 24 | X8: =T8+S8 -> 59 | Y8: =V8 -> 85 | Z8: =(S8+T8)/V8 -> 0.69411765 | AA8: 45838 | AB8: gb
A9: Rochdale | B9: ='2025 - Q1'!U9-'2025 - Q1'!V9 -> -6 | C9: 19 | E9: =SUM(C9:D9) -> 19 | F9: 32 | G9: =E9/F9 -> 0.59375 | H9: 29 | J9: =SUM(H9:I9) -> 29 | K9: 35 | L9: =J9/K9 -> 0.82857143 | M9: 31 | O9: =SUM(M9:N9) -> 31 | P9: 42 | Q9: =O9/P9 -> 0.73809524 | R9: =B9 -> -6 | S9: =M9+H9+C9 -> 79 | T9: =N9+I9+D9 -> 0 | U9: =SUM(R9:T9) -> 73 | V9: =P9+K9+F9 -> 109 | W9: =V9-U9 -> 36 | X9: =T9+S9 -> 79 | Y9: =V9 -> 109 | Z9: =(S9+T9)/V9 -> 0.72477064 | AA9: 45838 | AB9: gb
A10: NORTH CDA | B10: =SUM(B6:B9) -> -50 | C10: =SUM(C6:C9) -> 90 | D10: =SUM(D6:D9) -> 1 | E10: =SUM(E6:E9) -> 91 | F10: =SUM(F6:F9) -> 120 | G10: =E10/F10 -> 0.75833333 | H10: =SUM(H6:H9) -> 123 | I10: =SUM(I6:I9) -> 2 | J10: =SUM(J6:J9) -> 125 | K10: =SUM(K6:K9) -> 139 | L10: =J10/K10 -> 0.89928058 | M10: =SUM(M6:M9) -> 128 | N10: =SUM(N6:N9) -> 2 | O10: =SUM(O6:O9) -> 130 | P10: =SUM(P6:P9) -> 169 | Q10: =O10/P10 -> 0.76923077 | R10: =SUM(R6:R9) -> -50 | S10: =SUM(S6:S9) -> 341 | T10: =SUM(T6:T9) -> 5 | U10: =SUM(U6:U9) -> 296 | V10: =SUM(V6:V9) -> 428 | W10: =SUM(W6:W9) -> 132 | X10: =SUM(X6:X9) -> 346 | Y10: =SUM(Y6:Y9) -> 428 | Z10: =X10/Y10 -> 0.80841121
A11: Macclesfield | B11: ='2025 - Q1'!U11-'2025 - Q1'!V11 -> 6 | C11: 11 | E11: =SUM(C11:D11) -> 11 | F11: 33 | G11: =E11/F11 -> 0.33333333 | H11: 28 | J11: =SUM(H11:I11) -> 28 | K11: 33 | L11: =J11/K11 -> 0.84848485 | M11: 41 | O11: =SUM(M11:N11) -> 41 | P11: 42 | Q11: =O11/P11 -> 0.97619048 | R11: =B11 -> 6 | S11: =M11+H11+C11 -> 80 | T11: =N11+I11+D11 -> 0 | U11: =SUM(R11:T11) -> 86 | V11: =P11+K11+F11 -> 108 | W11: =V11-U11 -> 22 | X11: =T11+S11 -> 80 | Y11: =V11 -> 108 | Z11: =(S11+T11)/V11 -> 0.74074074 | AA11: 45838 | AB11: AJB
A12: Denton | B12: ='2025 - Q1'!U12-'2025 - Q1'!V12 -> 15 | C12: 19 | D12: 1 | E12: =SUM(C12:D12) -> 20 | F12: 28 | G12: =E12/F12 -> 0.71428571 | H12: 26 | I12: 2 | J12: =SUM(H12:I12) -> 28 | K12: 35 | L12: =J12/K12 -> 0.8 | M12: 43 | O12: =SUM(M12:N12) -> 43 | P12: 44 | Q12: =O12/P12 -> 0.97727273 | R12: =B12 -> 15 | S12: =M12+H12+C12 -> 88 | T12: =N12+I12+D12 -> 3 | U12: =SUM(R12:T12) -> 106 | V12: =P12+K12+F12 -> 107 | W12: =V12-U12 -> 1 | X12: =T12+S12 -> 91 | Y12: =V12 -> 107 | Z12: =(S12+T12)/V12 -> 0.85046729 | AA12: 45838 | AB12: AJB
A13: Altrincham | B13: ='2025 - Q1'!U13-'2025 - Q1'!V13 -> 26 | C13: 29 | E13: =SUM(C13:D13) -> 29 | F13: 25 | G13: =E13/F13 -> 1.16 | H13: 21 | J13: =SUM(H13:I13) -> 21 | K13: 30 | L13: =J13/K13 -> 0.7 | M13: 41 | O13: =SUM(M13:N13) -> 41 | P13: 36 | Q13: =O13/P13 -> 1.1388889 | R13: =B13 -> 26 | S13: =M13+H13+C13 -> 91 | T13: =N13+I13+D13 -> 0 | U13: =SUM(R13:T13) -> 117 | V13: =P13+K13+F13 -> 91 | W13: =V13-U13 -> -26 | X13: =T13+S13 -> 91 | Y13: =V13 -> 91 | Z13: =(S13+T13)/V13 -> 1 | AA13: 45838 | AB13: AJB
A14: Stockport | B14: ='2025 - Q1'!U14-'2025 - Q1'!V14 -> 13 | C14: 28 | E14: =SUM(C14:D14) -> 28 | F14: 41 | G14: =E14/F14 -> 0.68292683 | H14: 37 | J14: =SUM(H14:I14) -> 37 | K14: 47 | L14: =J14/K14 -> 0.78723404 | M14: 59 | O14: =SUM(M14:N14) -> 59 | P14: 60 | Q14: =O14/P14 -> 0.98333333 | R14: =B14 -> 13 | S14: =M14+H14+C14 -> 124 | T14: =N14+I14+D14 -> 0 | U14: =SUM(R14:T14) -> 137 | V14: =P14+K14+F14 -> 148 | W14: =V14-U14 -> 11 | X14: =T14+S14 -> 124 | Y14: =V14 -> 148 | Z14: =(S14+T14)/V14 -> 0.83783784 | AA14: 45838 | AB14: AJB
A15: SOUTH CDA | B15: =SUM(B11:B14) -> 60 | C15: =SUM(C11:C14) -> 87 | D15: =SUM(D11:D14) -> 1 | E15: =SUM(E11:E14) -> 88 | F15: =SUM(F11:F14) -> 127 | G15: =E15/F15 -> 0.69291339 | H15: =SUM(H11:H14) -> 112 | I15: =SUM(I11:I14) -> 2 | J15: =SUM(J11:J14) -> 114 | K15: =SUM(K11:K14) -> 145 | L15: =J15/K15 -> 0.7862069 | M15: =SUM(M11:M14) -> 184 | N15: =SUM(N11:N14) -> 0 | O15: =SUM(O11:O14) -> 184 | P15: =SUM(P11:P14) -> 182 | Q15: =O15/P15 -> 1.010989 | R15: =SUM(R11:R14) -> 60 | S15: =SUM(S11:S14) -> 383 | T15: =SUM(T11:T14) -> 3 | U15: =SUM(U11:U14) -> 446 | V15: =SUM(V11:V14) -> 454 | W15: =SUM(W11:W14) -> 8 | X15: =SUM(X11:X14) -> 386 | Y15: =SUM(Y11:Y14) -> 454 | Z15: =X15/Y15 -> 0.85022026
A16: Bradford | B16: ='2025 - Q1'!U16-'2025 - Q1'!V16 -> 16 | C16: 23 | D16: 13 | E16: =SUM(C16:D16) -> 36 | F16: 28 | G16: =E16/F16 -> 1.2857143 | H16: 14 | I16: 16 | J16: =SUM(H16:I16) -> 30 | K16: 34 | L16: =J16/K16 -> 0.88235294 | M16: 22 | N16: 15 | O16: =SUM(M16:N16) -> 37 | P16: 42 | Q16: =O16/P16 -> 0.88095238 | R16: =B16 -> 16 | S16: =M16+H16+C16 -> 59 | T16: =N16+I16+D16 -> 44 | U16: =SUM(R16:T16) -> 119 | V16: =P16+K16+F16 -> 104 | W16: =V16-U16 -> -15 | X16: =T16+S16 -> 103 | Y16: =V16 -> 104 | Z16: =(S16+T16)/V16 -> 0.99038462 | AA16: 45838 | AB16: PS
A17: Huddersfield | B17: ='2025 - Q1'!U17-'2025 - Q1'!V17 -> -2 | C17: 25 | D17: 5 | E17: =SUM(C17:D17) -> 30 | F17: 27 | G17: =E17/F17 -> 1.1111111 | H17: 27 | I17: 4 | J17: =SUM(H17:I17) -> 31 | K17: 29 | L17: =J17/K17 -> 1.0689655 | M17: 44 | O17: =SUM(M17:N17) -> 44 | P17: 36 | Q17: =O17/P17 -> 1.2222222 | R17: =B17 -> -2 | S17: =M17+H17+C17 -> 96 | T17: =N17+I17+D17 -> 9 | U17: =SUM(R17:T17) -> 103 | V17: =P17+K17+F17 -> 92 | W17: =V17-U17 -> -11 | X17: =T17+S17 -> 105 | Y17: =V17 -> 92 | Z17: =(S17+T17)/V17 -> 1.1413043 | AA17: 45838 | AB17: PS
A18: Silsden | B18: ='2025 - Q1'!U18-'2025 - Q1'!V18 -> 15 | C18: 9 | E18: =SUM(C18:D18) -> 9 | F18: 12 | G18: =E18/F18 -> 0.75 | H18: 9 | I18: 0 | J18: =SUM(H18:I18) -> 9 | K18: 11 | L18: =J18/K18 -> 0.81818182 | M18: 17 | O18: =SUM(M18:N18) -> 17 | P18: 13 | Q18: =O18/P18 -> 1.3076923 | R18: =B18 -> 15 | S18: =M18+H18+C18 -> 35 | T18: =N18+I18+D18 -> 0 | U18: =SUM(R18:T18) -> 50 | V18: =P18+K18+F18 -> 36 | W18: =V18-U18 -> -14 | X18: =T18+S18 -> 35 | Y18: =V18 -> 36 | Z18: =(S18+T18)/V18 -> 0.97222222 | AA18: 45838 | AB18: PS
A19: WY CDA | B19: =SUM(B16:B18) -> 29 | C19: =SUM(C16:C18) -> 57 | D19: =SUM(D16:D18) -> 18 | E19: =SUM(E16:E18) -> 75 | F19: =SUM(F16:F18) -> 67 | G19: =E19/F19 -> 1.119403 | H19: =SUM(H16:H18) -> 50 | I19: =SUM(I16:I18) -> 20 | J19: =SUM(J16:J18) -> 70 | K19: =SUM(K16:K18) -> 74 | L19: =J19/K19 -> 0.94594595 | M19: =SUM(M16:M18) -> 83 | N19: =SUM(N16:N18) -> 15 | O19: =SUM(O16:O18) -> 98 | P19: =SUM(P16:P18) -> 91 | Q19: =O19/P19 -> 1.0769231 | R19: =SUM(R16:R18) -> 29 | S19: =SUM(S16:S18) -> 190 | T19: =SUM(T16:T18) -> 53 | U19: =SUM(U16:U18) -> 272 | V19: =SUM(V16:V18) -> 232 | W19: =SUM(W16:W18) -> -40 | X19: =SUM(X16:X18) -> 243 | Y19: =SUM(Y16:Y18) -> 232 | Z19: =X19/Y19 -> 1.0474138
A22: TOTAL | B22: =B19+B15+B10 -> 39 | C22: =C19+C15+C10 -> 234 | D22: =D19+D15+D10 -> 20 | E22: =E19+E15+E10 -> 254 | F22: =F19+F15+F10 -> 314 | G22: =E22/F22 -> 0.8089172 | H22: =H19+H15+H10 -> 285 | I22: =I19+I15+I10 -> 24 | J22: =J19+J15+J10 -> 309 | K22: =K19+K15+K10 -> 358 | L22: =J22/K22 -> 0.86312849 | M22: =M19+M15+M10 -> 395 | N22: =N19+N15+N10 -> 17 | O22: =O19+O15+O10 -> 412 | P22: =P19+P15+P10 -> 442 | Q22: =O22/P22 -> 0.9321267 | R22: =R19+R15+R10 -> 39 | S22: =S19+S15+S10 -> 914 | T22: =T19+T15+T10 -> 61 | U22: =U19+U15+U10 -> 1014 | V22: =V19+V15+V10 -> 1114 | W22: =W19+W15+W10 -> 100 | X22: =X19+X15+X10 -> 975 | Y22: =Y19+Y15+Y10 -> 1114 | Z22: =(S22+T22)/V22 -> 0.87522442
U24: =U22/V22 -> 0.91023339 | X24: =1114-200+111 -> 1025 | Y24: =Y22-X22 -> 139
A25: Q2 - BZ TARGETS
B27: Total | C27: Target | D27: TO GO (100%) | F27: UNREG ORDERS
A28: Salford | C28: 2 | D28: =C28-B28 -> 2 | F28: 0
A29: Bolton | C29: 2 | D29: =C29-B29 -> 2 | F29: 0
A30: Bury | C30: 2 | D30: =C30-B30 -> 2 | F30: 0
A31: Rochdale | B31: 4 | C31: 2 | D31: =C31-B31 -> -2 | F31: 0
A32: NORTH CDA | B32: =SUM(B28:B31) -> 4 | C32: =SUM(C28:C31) -> 8 | D32: =SUM(D28:D31) -> 4 | F32: =SUM(F28:F31) -> 0
A34: Macclesfield | B34: 3 | C34: 2 | D34: =C34-B34 -> -1 | F34: 0
A35: Denton | B35: 1 | C35: 2 | D35: =C35-B35 -> 1 | F35: 0
A36: Altrincham | C36: 2 | D36: =C36-B36 -> 2 | F36: 0
A37: Stockport | B37: 1 | C37: 2 | D37: =C37-B37 -> 1 | F37: 0
A38: SOUTH CDA | B38: =SUM(B34:B37) -> 5 | C38: =SUM(C34:C37) -> 8 | D38: =SUM(D34:D37) -> 3 | F38: =SUM(F34:F37) -> 0
A40: Bradford | C40: 3 | D40: =C40-B40 -> 3 | F40: 0
A41: Huddersfield | B41: 3 | C41: 2 | D41: =C41-B41 -> -1 | F41: 0
A42: Silsden | C42: 1 | D42: =C42-B42 -> 1 | F42: 0
A43: WY CDA | B43: =SUM(B40:B42) -> 3 | C43: =SUM(C40:C42) -> 6 | D43: =SUM(D40:D42) -> 3 | F43: =SUM(F40:F42) -> 0
A46: TOTAL | B46: =B43+B38+B32 -> 12 | C46: =C43+C38+C32 -> 22 | D46: =D43+D38+D32 -> 10 | F46: =F43+F38+F32 -> 0
A49: REGISTRATIONS (NON-COUNTING) | U49: Updated | V49: By
C50: =C4 -> APRIL | G50: =H4 -> MAY | K50: =M4 -> JUNE | Q50: TOTAL
C51: Non-Counting Fleet (Reg) | D51: Non-Counting Fleet (Unreg) | E51: Total | F51: Budget | G51: Non-Counting Fleet (Reg) | H51: Non-Counting Fleet (Unreg) | I51: Total | J51: Budget | K51: Non-Counting Fleet (Reg) | L51: Non-Counting Fleet (Unreg) | M51: Total | N51: Budget | Q51: Non-Counting Fleet (Reg) | R51: Non-Counting Fleet (Unreg) | S51: Total | T51: Budget
A52: Salford | C52: 53 | D52: 0 | E52: =SUM(C52:D52) -> 53 | F52: 114 | G52: 99 | I52: =SUM(G52:H52) -> 99 | J52: 129 | K52: 103 | L52: 57 | M52: =SUM(K52:L52) -> 160 | N52: 155 | P52: =B52 -> 0 | Q52: =K52+G52+C52 -> 255 | R52: =L52+H52+D52 -> 57 | S52: =SUM(P52:R52) -> 312 | T52: =N52+J52+F52 -> 398 | U52: 45831 | V52: gb
A53: NORTH CDA | C53: =SUM(C52) -> 53 | D53: =SUM(D52) -> 0 | E53: =SUM(E52) -> 53 | F53: =SUM(F52) -> 114 | G53: =SUM(G52) -> 99 | H53: =SUM(H52) -> 0 | I53: =SUM(I52) -> 99 | J53: =SUM(J52) -> 129 | ... N53: =SUM(N52) -> 155 | P53: =B53 -> 0 | Q53: =SUM(Q52) -> 255 | R53: =SUM(R52) -> 57 | S53: =SUM(S52) -> 312 | T53: =SUM(T52) -> 398
A54: Denton | C54: 60 | E54: =SUM(C54:D54) -> 60 | F54: 20 | G54: 50 | H54: 0 | I54: =SUM(G54:H54) -> 50 | J54: 30 | K54: 6 | L54: 46 | M54: =SUM(K54:L54) -> 52 | N54: 37 | P54: =B54 -> 0 | Q54: =K54+G54+O58+C54 -> 116 | R54: =L54+H54+D54 -> 46 | S54: =SUM(P54:R54) -> 162 | T54: =N54+J54+F54 -> 87 | U54: 45824 | V54: NF
A55: SOUTH CDA | C55: =SUM(C54) -> 60 | D55: =SUM(D54) -> 0 | E55: =SUM(E54) -> 60 | F55: =SUM(F54) -> 20 | G55: =SUM(G54) -> 50 | H55: =SUM(H54) -> 0 | I55: =SUM(I54) -> 50 | J55: =SUM(J54) -> 30 | ... N55: =SUM(N54) -> 37 | P55: =B55 -> 0 | Q55: =SUM(Q54) -> 116 | R55: =SUM(R54) -> 46 | S55: =SUM(S54) -> 162 | T55: =SUM(T54) -> 87
A56: Bradford | C56: 53 | D56: 0 | E56: =SUM(C56:D56) -> 53 | F56: 25 | G56: 45 | H56: 0 | I56: =SUM(G56:H56) -> 45 | J56: 38 | K56: 46 | L56: 0 | M56: =SUM(K56:L56) -> 46 | N56: 61 | P56: =B56 -> 0 | Q56: =K56+G56+C56 -> 144 | R56: =L56+H56+D56 -> 0 | S56: =SUM(P56:R56) -> 144 | T56: =N56+J56+F56 -> 124 | U56: 45838 | V56: PS
C57: =SUM(C56) -> 53 | D57: =SUM(D56) -> 0 | E57: =SUM(E56) -> 53 | F57: =SUM(F56) -> 25 | G57: =SUM(G56) -> 45 | H57: =SUM(H56) -> 0 | I57: =SUM(I56) -> 45 | J57: =SUM(J56) -> 38 | ... N57: =SUM(N56) -> 61 | P57: =B57 -> 0 | Q57: =SUM(Q56) -> 144 | R57: =SUM(R56) -> 0 | S57: =SUM(S56) -> 144 | T57: =SUM(T56) -> 124
P58: =B58 -> 0
A60: TOTAL | C60: =C57+C55+C53 -> 166 | D60: =D57+D55+D53 -> 0 | E60: =E57+E55+E53 -> 166 | F60: =F57+F55+F53 -> 159 | G60: =G57+G55+G53 -> 194 | H60: =H57+H55+H53 -> 0 | I60: =I57+I55+I53 -> 194 | J60: =J57+J55+J53 -> 197 | ... N60: =N57+N55+N53 -> 253 | Q60: =Q57+Q55+Q53 -> 515 | R60: =R57+R55+R53 -> 103 | S60: =S57+S55+S53 -> 618 | T60: =T57+T55+T53 -> 609
A62: USED COUNTING VOLUME
B63: APRIL | F63: MAY | I63: JUNE | M63: TOTAL | P63: Q1 | S63: Catch-back
B64: B/FWD | C64: Counting | D64: Target | F64: Counting | G64: Target | I64: Counting | J64: Target | L64: B/FWD | M64: Counting | N64: Target | P64: Counting | Q64: Target | S64: Target
A65: Salford | B65: -13 | C65: 42 | D65: 61 | E65: =C65/D65 -> 0.68852459 | F65: 55 | G65: 61 | H65: =F65/G65 -> 0.90163934 | I65: 41 | J65: 63 | K65: =I65/J65 -> 0.65079365 | L65: =B65 -> -13 | M65: =I65+F65+C65 -> 138 | N65: =J65+G65+D65 -> 185 | O65: 743 | P65: 185 | Q65: 198 | R65: =P65/Q65 -> 0.93434343 | S65: =N65+Q65-P65 -> 198 | T65: 62 | U65: 45838 | V65: GB
A66: Bolton | B66: 1 | C66: 60 | D66: 48 | E66: =C66/D66 -> 1.25 | F66: 52 | G66: 48 | H66: =F66/G66 -> 1.0833333 | I66: 54 | J66: 50 | K66: =I66/J66 -> 1.08 | L66: =B66 -> 1 | M66: =I66+F66+C66 -> 166 | N66: =J66+G66+D66 -> 146 | O66: 584 | P66: 157 | Q66: 156 | R66: =P66/Q66 -> 1.0064103 | S66: =N66+Q66-P66 -> 145 | T66: 52 | U66: 45838 | V66: GB
A67: Bury | B67: 27 | C67: 47 | D67: 46 | E67: =C67/D67 -> 1.0217391 | F67: 52 | G67: 46 | H67: =F67/G67 -> 1.1304348 | I67: 39 | J67: 48 | K67: =I67/J67 -> 0.8125 | L67: =B67 -> 27 | M67: =I67+F67+C67 -> 138 | N67: =J67+G67+D67 -> 140 | O67: 562 | P67: 177 | Q67: 150 | R67: =P67/Q67 -> 1.18 | S67: =N67+Q67-P67 -> 113 | T67: 59 | U67: 45838 | V67: GB
A68: Rochdale | B68: -45 | C68: 48 | D68: 58 | E68: =C68/D68 -> 0.82758621 | F68: 37 | G68: 58 | H68: =F68/G68 -> 0.63793103 | I68: 41 | J68: 60 | K68: =I68/J68 -> 0.68333333 | L68: =B68 -> -45 | M68: =I68+F68+C68 -> 126 | N68: =J68+G68+D68 -> 176 | O68: 711 | P68: 144 | Q68: 189 | R68: =P68/Q68 -> 0.76190476 | S68: =N68+Q68-P68 -> 221 | T68: 48 | U68: 45838 | V68: GB
A69: NORTH CDA | B69: =SUM(B65:B68) -> -30 | C69: =SUM(C65:C68) -> 197 | D69: =SUM(D65:D68) -> 213 | E69: =C69/D69 -> 0.92488263 | F69: =SUM(F65:F68) -> 196 | G69: =SUM(G65:G68) -> 213 | H69: =F69/G69 -> 0.92018779 | I69: =SUM(I65:I68) -> 175 | J69: =SUM(J65:J68) -> 221 | K69: =I69/J69 -> 0.7918552 | L69: =SUM(L65:L68) -> -30 | M69: =SUM(M65:M68) -> 568 | N69: =SUM(N65:N68) -> 647 | P69: =SUM(P65:P68) -> 663 | Q69: =SUM(Q65:Q68) -> 693 | R69: =P69/Q69 -> 0.95670996 | S69: =SUM(S65:S68) -> 677
A70: Macclesfield | B70: 16 | C70: 43 | D70: 39 | E70: =C70/D70 -> 1.1025641 | F70: 35 | G70: 39 | H70: =F70/G70 -> 0.8974359 | I70: 44 | J70: 40 | K70: =I70/J70 -> 1.1 | L70: =B70 -> 16 | M70: =I70+F70+C70 -> 122 | N70: =J70+G70+D70 -> 118 | O70: 473 | P70: 143 | Q70: 127 | R70: =P70/Q70 -> 1.1259843 | S70: =N70+Q70-P70 -> 102 | T70: 48 | U70: 45831 | V70: NF
A71: Denton | B71: -24 | C71: 34 | D71: 48 | E71: =C71/D71 -> 0.70833333 | F71: 25 | G71: 48 | H71: =F71/G71 -> 0.52083333 | I71: 44 | J71: 50 | K71: =I71/J71 -> 0.88 | L71: =B71 -> -24 | M71: =I71+F71+C71 -> 103 | N71: =J71+G71+D71 -> 146 | O71: 584 | P71: 132 | Q71: 156 | R71: =P71/Q71 -> 0.84615385 | S71: =N71+Q71-P71 -> 170 | T71: 44 | U71: 45831 | V71: NF
A72: Altrincham | B72: 5 | C72: 42 | D72: 42 | E72: =C72/D72 -> 1 | F72: 41 | G72: 42 | H72: =F72/G72 -> 0.97619048 | I72: 48 | J72: 43 | K72: =I72/J72 -> 1.1162791 | L72: =B72 -> 5 | M72: =I72+F72+C72 -> 131 | N72: =J72+G72+D72 -> 127 | O72: 509 | P72: 141 | Q72: 136 | R72: =P72/Q72 -> 1.0367647 | S72: =N72+Q72-P72 -> 122 | T72: 47 | U72: 45831 | V72: NF
A73: Stockport | B73: -32 | C73: 77 | D73: 88 | E73: =C73/D73 -> 0.875 | F73: 82 | G73: 88 | H73: =F73/G73 -> 0.93181818 | I73: 74 | J73: 92 | K73: =I73/J73 -> 0.80434783 | L73: =B73 -> -32 | M73: =I73+F73+C73 -> 233 | N73: =J73+G73+D73 -> 268 | O73: 1077 | P73: 256 | Q73: 288 | R73: =P73/Q73 -> 0.88888889 | S73: =N73+Q73-P73 -> 300 | T73: 85 | U73: 45831 | V73: NF
A74: SOUTH CDA | B74: =SUM(B70:B73) -> -35 | C74: =SUM(C70:C73) -> 196 | D74: =SUM(D70:D73) -> 217 | E74: =C74/D74 -> 0.90322581 | F74: =SUM(F70:F73) -> 183 | G74: =SUM(G70:G73) -> 217 | H74: =F74/G74 -> 0.84331797 | I74: =SUM(I70:I73) -> 210 | J74: =SUM(J70:J73) -> 225 | K74: =I74/J74 -> 0.93333333 | L74: =SUM(L70:L73) -> -35 | M74: =SUM(M70:M73) -> 589 | N74: =SUM(N70:N73) -> 659 | P74: =SUM(P70:P73) -> 672 | Q74: =SUM(Q70:Q73) -> 707 | R74: =P74/Q74 -> 0.95049505 | S74: =SUM(S70:S73) -> 694
A75: Bradford | B75: -28 | C75: 26 | D75: 38 | E75: =C75/D75 -> 0.68421053 | F75: 43 | G75: 38 | H75: =F75/G75 -> 1.1315789 | I75: 22 | J75: 39 | K75: =I75/J75 -> 0.56410256 | L75: =B75 -> -28 | M75: =I75+F75+C75 -> 91 | N75: =J75+G75+D75 -> 115 | O75: 462 | P75: 96 | Q75: 124 | R75: =P75/Q75 -> 0.77419355 | S75: =N75+Q75-P75 -> 143 | T75: 30 | U75: 45838 | V75: PS
A76: Huddersfield | B76: -40 | C76: 40 | D76: 51 | E76: =C76/D76 -> 0.78431373 | F76: 40 | G76: 51 | H76: =F76/G76 -> 0.78431373 | I76: 37 | J76: 53 | K76: =I76/J76 -> 0.69811321 | L76: =B76 -> -40 | M76: =I76+F76+C76 -> 117 | N76: =J76+G76+D76 -> 155 | O76: 623 | P76: 126 | Q76: 166 | R76: =P76/Q76 -> 0.75903614 | S76: =N76+Q76-P76 -> 195 | T76: 40 | U76: 45838 | V76: PS
A77: Silsden | B77: -4 | C77: 21 | D77: 23 | E77: =C77/D77 -> 0.91304348 | F77: 16 | G77: 23 | H77: =F77/G77 -> 0.69565217 | I77: 14 | J77: 23 | K77: =I77/J77 -> 0.60869565 | L77: =B77 -> -4 | M77: =I77+F77+C77 -> 51 | N77: =J77+G77+D77 -> 69 | O77: 275 | P77: 69 | Q77: 73 | R77: =P77/Q77 -> 0.94520548 | S77: =N77+Q77-P77 -> 73 | T77: 25 | U77: 45838 | V77: PS
A78: WY CDA | B78: =SUM(B75:B77) -> -72 | C78: =SUM(C75:C77) -> 87 | D78: =SUM(D75:D77) -> 112 | E78: =C78/D78 -> 0.77678571 | F78: =SUM(F75:F77) -> 99 | G78: =SUM(G75:G77) -> 112 | H78: =F78/G78 -> 0.88392857 | I78: =SUM(I75:I77) -> 73 | J78: =SUM(J75:J77) -> 115 | K78: =I78/J78 -> 0.63478261 | L78: =SUM(L75:L77) -> -72 | M78: =SUM(M75:M77) -> 259 | N78: =SUM(N75:N77) -> 339 | P78: =SUM(P75:P77) -> 291 | Q78: =SUM(Q75:Q77) -> 363 | R78: =P78/Q78 -> 0.80165289 | S78: =SUM(S75:S77) -> 411
A81: TOTAL | B81: =B78+B74+B69 -> -137 | C81: =C78+C74+C69 -> 480 | D81: =D78+D74+D69 -> 542 | E81: =C81/D81 -> 0.88560886 | F81: =F78+F74+F69 -> 478 | G81: =G78+G74+G69 -> 542 | H81: =F81/G81 -> 0.88191882 | I81: =I78+I74+I69 -> 458 | J81: =J78+J74+J69 -> 561 | K81: =I81/J81 -> 0.81639929 | L81: =L78+L74+L69 -> -137 | M81: =M78+M74+M69 -> 1416 | N81: =N78+N74+N69 -> 1645 | P81: =P78+P74+P69 -> 1626 | Q81: =Q78+Q74+Q69 -> 1763 | R81: =P81/Q81 -> 0.92229155 | S81: =S78+S74+S69 -> 1782
R84: 0.95 | S84: FY TARGET | T84: MONTHLY
R85: =S85*0.95 -> 2470 | S85: 2600 | T85: 220
R86: =S86*0.95 -> 2510.85 | S86: 2643 | T86: 220
R87: =S87*0.95 -> 1292 | S87: 1360 | T87: 100
R88: =SUM(R85:R87) -> 6272.85 | S88: =SUM(S85:S87) -> 6603 | T88: =SUM(T85:T87) -> 540

Sheet Fleet Volumes - Plan
A3: Salford | B3: Fleet Units | C3: 114 | D3: 129 | E3: 155 | F3: 127 | G3: 81 | H3: 315 | I3: 170 | J3: 159 | K3: 128 | L3: 134 | M3: 78 | N3: 315 | O3: 1905
A4: Denton | B4: Fleet Units | C4: 20 | D4: 30 | E4: 37 | F4: 25 | G4: 15 | H4: 63 | I4: 32 | J4: 25 | K4: 40 | L4: 26 | M4: 15 | N4: 72 | O4: 400
A5: Bradford | B5: Fleet Units | C5: 25 | D5: 38 | E5: 61 | F5: 39 | G5: 19 | H5: 71 | I5: 49 | J5: 40 | K5: 32 | L5: 20 | M5: 12 | N5: 79 | O5: 485

Sheet 2025 - Q1
A3: REGISTRATIONS (COUNTING) | AA3: Updated | AB3: By
C4: JANUARY | H4: FEBRUARY | M4: MARCH | S4: TOTAL
B5: B/FWD | C5: Counting | D5: Counting Fleet | E5: Total | F5: Target | H5: Counting | I5: Counting Fleet | J5: Total | K5: Target | M5: Counting | N5: Counting Fleet | O5: Total | P5: Target | R5: B/FWD | S5: Counting | T5: Counting Fleet | U5: Total | V5: Target | W5: TO GO | X5: QTR REGS | Y5: TARGET | Z5: REGS v TGT
A6: Salford | B6: =-'2024 - Q4'!U6 -> 106 | C6: 32 | D6: 1 | E6: =SUM(C6:D6) -> 33 | F6: 37 | G6: =E6/F6 -> 0.89189189 | H6: 12 | I6: 2 | J6: =SUM(H6:I6) -> 14 | K6: 20 | L6: =J6/K6 -> 0.7 | M6: 102 | N6: 7 | O6: =SUM(M6:N6) -> 109 | P6: 104 | Q6: =O6/P6 -> 1.0480769 | R6: =B6 -> 106 | S6: =M6+H6+C6 -> 146 | T6: =N6+I6+D6 -> 10 | U6: =SUM(R6:T6) -> 262 | V6: =P6+K6+F6 -> 161 | W6: =V6-U6 -> -101 | X6: =T6+S6 -> 156 | Y6: =V6 -> 161 | Z6: =(S6+T6)/V6 -> 0.9689441 | AA6: 45747 | AB6: gb
A7: Bolton | B7: =-'2024 - Q4'!U7 -> -113 | C7: 13 | E7: =SUM(C7:D7) -> 13 | F7: 27 | G7: =E7/F7 -> 0.48148148 | H7: 5 | J7: =SUM(H7:I7) -> 5 | K7: 16 | L7: =J7/K7 -> 0.3125 | M7: 72 | N7: 2 | O7: =SUM(M7:N7) -> 74 | P7: 83 | Q7: =O7/P7 -> 0.89156627 | R7: =B7 -> -113 | S7: =M7+H7+C7 -> 90 | T7: =N7+I7+D7 -> 2 | U7: =SUM(R7:T7) -> -21 | V7: =P7+K7+F7 -> 126 | W7: =V7-U7 -> 147 | X7: =T7+S7 -> 92 | Y7: =V7 -> 126 | Z7: =(S7+T7)/V7 -> 0.73015873 | AA7: 45747 | AB7: gb
A8: Bury | B8: =-'2024 - Q4'!U8 -> 15 | C8: 21 | E8: =SUM(C8:D8) -> 21 | F8: 24 | G8: =E8/F8 -> 0.875 | H8: 5 | J8: =SUM(H8:I8) -> 5 | K8: 14 | L8: =J8/K8 -> 0.35714286 | M8: 70 | O8: =SUM(M8:N8) -> 70 | P8: 71 | Q8: =O8/P8 -> 0.98591549 | R8: =B8 -> 15 | S8: =M8+H8+C8 -> 96 | T8: =N8+I8+D8 -> 0 | U8: =SUM(R8:T8) -> 111 | V8: =P8+K8+F8 -> 109 | W8: =V8-U8 -> -2 | X8: =T8+S8 -> 96 | Y8: =V8 -> 109 | Z8: =(S8+T8)/V8 -> 0.88073394 | AA8: 45747 | AB8: gb
A9: Rochdale | B9: =-'2024 - Q4'!U9 -> 34 | C9: 14 | D9: 2 | E9: =SUM(C9:D9) -> 16 | F9: 31 | G9: =E9/F9 -> 0.51612903 | H9: 7 | J9: =SUM(H9:I9) -> 7 | K9: 17 | L9: =J9/K9 -> 0.41176471 | M9: 74 | O9: =SUM(M9:N9) -> 74 | P9: 89 | Q9: =O9/P9 -> 0.83146067 | R9: =B9 -> 34 | S9: =M9+H9+C9 -> 95 | T9: =N9+I9+D9 -> 2 | U9: =SUM(R9:T9) -> 131 | V9: =P9+K9+F9 -> 137 | W9: =V9-U9 -> 6 | X9: =T9+S9 -> 97 | Y9: =V9 -> 137 | Z9: =(S9+T9)/V9 -> 0.7080292 | AA9: 45747 | AB9: gb
A10: NORTH CDA | B10: =SUM(B6:B9) -> 42 | C10: =SUM(C6:C9) -> 80 | D10: =SUM(D6:D9) -> 3 | E10: =SUM(E6:E9) -> 83 | F10: =SUM(F6:F9) -> 119 | G10: =E10/F10 -> 0.69747899 | H10: =SUM(H6:H9) -> 29 | I10: =SUM(I6:I9) -> 2 | J10: =SUM(J6:J9) -> 31 | K10: =SUM(K6:K9) -> 67 | L10: =J10/K10 -> 0.46268657 | M10: =SUM(M6:M9) -> 318 | N10: =SUM(N6:N9) -> 9 | O10: =SUM(O6:O9) -> 327 | P10: =SUM(P6:P9) -> 347 | Q10: =O10/P10 -> 0.94236311 | R10: =SUM(R6:R9) -> 42 | S10: =SUM(S6:S9) -> 427 | T10: =SUM(T6:T9) -> 14 | U10: =SUM(U6:U9) -> 483 | V10: =SUM(V6:V9) -> 533 | W10: =SUM(W6:W9) -> 50 | X10: =SUM(X6:X9) -> 441 | Y10: =SUM(Y6:Y9) -> 533 | Z10: =X10/Y10 -> 0.82739212
A11: Macclesfield | B11: =-'2024 - Q4'!U11 -> 31 | C11: 12 | E11: =SUM(C11:D11) -> 12 | F11: 27 | G11: =E11/F11 -> 0.44444444 | H11: 4 | J11: =SUM(H11:I11) -> 4 | K11: 17 | L11: =J11/K11 -> 0.23529412 | M11: 82 | N11: 6 | O11: =SUM(M11:N11) -> 88 | P11: 85 | Q11: =O11/P11 -> 1.0352941 | R11: =B11 -> 31 | S11: =M11+H11+C11 -> 98 | T11: =N11+I11+D11 -> 6 | U11: =SUM(R11:T11) -> 135 | V11: =P11+K11+F11 -> 129 | W11: =V11-U11 -> -6 | X11: =T11+S11 -> 104 | Y11: =V11 -> 129 | Z11: =(S11+T11)/V11 -> 0.80620155 | AA11: 45747 | AB11: NF
A12: Denton | B12: =-'2024 - Q4'!U12 -> 38 | C12: 18 | D12: 1 | E12: =SUM(C12:D12) -> 19 | F12: 30 | G12: =E12/F12 -> 0.63333333 | H12: 11 | J12: =SUM(H12:I12) -> 11 | K12: 17 | L12: =J12/K12 -> 0.64705882 | M12: 72 | N12: 5 | O12: =SUM(M12:N12) -> 77 | P12: 83 | Q12: =O12/P12 -> 0.92771084 | R12: =B12 -> 38 | S12: =M12+H12+C12 -> 101 | T12: =N12+I12+D12 -> 6 | U12: =SUM(R12:T12) -> 145 | V12: =P12+K12+F12 -> 130 | W12: =V12-U12 -> -15 | X12: =T12+S12 -> 107 | Y12: =V12 -> 130 | Z12: =(S12+T12)/V12 -> 0.82307692 | AA12: 45747 | AB12: NF
A13: Altrincham | B13: =-'2024 - Q4'!U13 -> 57 | C13: 20 | D13: 2 | E13: =SUM(C13:D13) -> 22 | F13: 26 | G13: =E13/F13 -> 0.84615385 | H13: 12 | J13: =SUM(H13:I13) -> 12 | K13: 13 | L13: =J13/K13 -> 0.92307692 | M13: 47 | N13: 1 | O13: =SUM(M13:N13) -> 48 | P13: 74 | Q13: =O13/P13 -> 0.64864865 | R13: =B13 -> 57 | S13: =M13+H13+C13 -> 79 | T13: =N13+I13+D13 -> 3 | U13: =SUM(R13:T13) -> 139 | V13: =P13+K13+F13 -> 113 | W13: =V13-U13 -> -26 | X13: =T13+S13 -> 82 | Y13: =V13 -> 113 | Z13: =(S13+T13)/V13 -> 0.72566372 | AA13: 45747 | AB13: NF
A14: Stockport | B14: =-'2024 - Q4'!U14 -> 35 | C14: 36 | D14: 1 | E14: =SUM(C14:D14) -> 37 | F14: 40 | G14: =E14/F14 -> 0.925 | H14: 7 | I14: 1 | J14: =SUM(H14:I14) -> 8 | K14: 24 | L14: =J14/K14 -> 0.33333333 | M14: 111 | N14: 5 | O14: =SUM(M14:N14) -> 116 | P14: 119 | Q14: =O14/P14 -> 0.97478992 | R14: =B14 -> 35 | S14: =M14+H14+C14 -> 154 | T14: =N14+I14+D14 -> 7 | U14: =SUM(R14:T14) -> 196 | V14: =P14+K14+F14 -> 183 | W14: =V14-U14 -> -13 | X14: =T14+S14 -> 161 | Y14: =V14 -> 183 | Z14: =(S14+T14)/V14 -> 0.87978142 | AA14: 45748 | AB14: NF
A15: SOUTH CDA | B15: =SUM(B11:B14) -> 161 | C15: =SUM(C11:C14) -> 86 | D15: =SUM(D11:D14) -> 4 | E15: =SUM(E11:E14) -> 90 | F15: =SUM(F11:F14) -> 123 | G15: =E15/F15 -> 0.73170732 | H15: =SUM(H11:H14) -> 34 | I15: =SUM(I11:I14) -> 1 | J15: =SUM(J11:J14) -> 35 | K15: =SUM(K11:K14) -> 71 | L15: =J15/K15 -> 0.49295775 | M15: =SUM(M11:M14) -> 312 | N15: =SUM(N11:N14) -> 17 | O15: =SUM(O11:O14) -> 329 | P15: =SUM(P11:P14) -> 361 | Q15: =O15/P15 -> 0.91135734 | R15: =SUM(R11:R14) -> 161 | S15: =SUM(S11:S14) -> 432 | T15: =SUM(T11:T14) -> 22 | U15: =SUM(U11:U14) -> 615 | V15: =SUM(V11:V14) -> 555 | W15: =SUM(W11:W14) -> -60 | X15: =SUM(X11:X14) -> 454 | Y15: =SUM(Y11:Y14) -> 555 | Z15: =X15/Y15 -> 0.81801802
A16: Bradford | B16: =-'2024 - Q4'!U16 -> 23 | C16: 6 | D16: 10 | E16: =SUM(C16:D16) -> 16 | F16: 28 | G16: =E16/F16 -> 0.57142857 | H16: 5 | I16: 9 | J16: =SUM(H16:I16) -> 14 | K16: 15 | L16: =J16/K16 -> 0.93333333 | M16: 65 | N16: 23 | O16: =SUM(M16:N16) -> 88 | P16: 82 | Q16: =O16/P16 -> 1.0731707 | R16: =B16 -> 23 | S16: =M16+H16+C16 -> 76 | T16: =N16+I16+D16 -> 42 | U16: =SUM(R16:T16) -> 141 | V16: =P16+K16+F16 -> 125 | W16: =V16-U16 -> -16 | X16: =T16+S16 -> 118 | Y16: =V16 -> 125 | Z16: =(S16+T16)/V16 -> 0.944 | AA16: 45747 | AB16: PS
A17: Huddersfield | B17: =-'2024 - Q4'!U17 -> 8 | C17: 13 | E17: =SUM(C17:D17) -> 13 | F17: 27 | G17: =E17/F17 -> 0.48148148 | H17: 9 | I17: 6 | J17: =SUM(H17:I17) -> 15 | K17: 14 | L17: =J17/K17 -> 1.0714286 | M17: 75 | N17: 1 | O17: =SUM(M17:N17) -> 76 | P17: 73 | Q17: =O17/P17 -> 1.0410959 | R17: =B17 -> 8 | S17: =M17+H17+C17 -> 97 | T17: =N17+I17+D17 -> 7 | U17: =SUM(R17:T17) -> 112 | V17: =P17+K17+F17 -> 114 | W17: =V17-U17 -> 2 | X17: =T17+S17 -> 104 | Y17: =V17 -> 114 | Z17: =(S17+T17)/V17 -> 0.9122807 | AA17: 45747 | AB17: PS
A18: Silsden | B18: =-'2024 - Q4'!U18 -> 16 | C18: 5 | E18: =SUM(C18:D18) -> 5 | F18: 10 | G18: =E18/F18 -> 0.5 | H18: 6 | I18: 5 | J18: =SUM(H18:I18) -> 11 | K18: 4 | L18: =J18/K18 -> 2.75 | M18: 26 | N18: 2 | O18: =SUM(M18:N18) -> 28 | P18: 31 | Q18: =O18/P18 -> 0.90322581 | R18: =B18 -> 16 | S18: =M18+H18+C18 -> 37 | T18: =N18+I18+D18 -> 7 | U18: =SUM(R18:T18) -> 60 | V18: =P18+K18+F18 -> 45 | W18: =V18-U18 -> -15 | X18: =T18+S18 -> 44 | Y18: =V18 -> 45 | Z18: =(S18+T18)/V18 -> 0.97777778 | AA18: 45747 | AB18: PS
A19: WY CDA | B19: =SUM(B16:B18) -> 47 | C19: =SUM(C16:C18) -> 24 | D19: =SUM(D16:D18) -> 10 | E19: =SUM(E16:E18) -> 34 | F19: =SUM(F16:F18) -> 65 | G19: =E19/F19 -> 0.52307692 | H19: =SUM(H16:H18) -> 20 | I19: =SUM(I16:I18) -> 20 | J19: =SUM(J16:J18) -> 40 | K19: =SUM(K16:K18) -> 33 | L19: =J19/K19 -> 1.2121212 | M19: =SUM(M16:M18) -> 166 | N19: =SUM(N16:N18) -> 26 | O19: =SUM(O16:O18) -> 192 | P19: =SUM(P16:P18) -> 186 | Q19: =O19/P19 -> 1.0322581 | R19: =SUM(R16:R18) -> 47 | S19: =SUM(S16:S18) -> 210 | T19: =SUM(T16:T18) -> 56 | U19: =SUM(U16:U18) -> 313 | V19: =SUM(V16:V18) -> 284 | W19: =SUM(W16:W18) -> -29 | X19: =SUM(X16:X18) -> 266 | Y19: =SUM(Y16:Y18) -> 284 | Z19: =X19/Y19 -> 0.93661972
A22: TOTAL | B22: =B19+B15+B10 -> 250 | C22: =C19+C15+C10 -> 190 | D22: =D19+D15+D10 -> 17 | E22: =E19+E15+E10 -> 207 | F22: =F19+F15+F10 -> 307 | G22: =E22/F22 -> 0.6742671 | H22: =H19+H15+H10 -> 83 | I22: =I19+I15+I10 -> 23 | J22: =J19+J15+J10 -> 106 | K22: =K19+K15+K10 -> 171 | L22: =J22/K22 -> 0.61988304 | M22: =M19+M15+M10 -> 796 | N22: =N19+N15+N10 -> 52 | O22: =O19+O15+O10 -> 848 | P22: =P19+P15+P10 -> 894 | Q22: =O22/P22 -> 0.94854586 | R22: =R19+R15+R10 -> 250 | S22: =S19+S15+S10 -> 1069 | T22: =T19+T15+T10 -> 92 | U22: =U19+U15+U10 -> 1411 | V22: =V19+V15+V10 -> 1372 | W22: =W19+W15+W10 -> -39 | X22: =X19+X15+X10 -> 1161 | Y22: =Y19+Y15+Y10 -> 1372 | Z22: =(S22+T22)/V22 -> 0.84620991
Y23: =X22-Y22 -> -211
A26: Q1 INCENTIVE
B28: Total | C28: Target | D28: TO GO (100%) | F28: TARGET (105%) | G28: TARGET (110%) | J28: TO GO (105%) | K28: TO GO (110%) | N28: CURRENT EARNINGS
A29: Salford | B29: =S6+T6 -> 156 | C29: =V6 -> 161 | D29: =C29-B29 -> 5 | F29: =ROUNDUP($C29*1.05,0) -> 170 | G29: =ROUNDUP($C29*1.1,0) -> 178 | J29: =B29-F29 -> -14 | K29: =B29-G29 -> -22 | N29: =B29/B$33*O$33 -> 0 | Y29: 0 | Z29: 0
A30: Bolton | B30: =S7+T7 -> 92 | C30: =V7 -> 126 | D30: =C30-B30 -> 34 | F30: =ROUNDUP(C30*1.05,0) -> 133 | G30: =ROUNDUP($C30*1.1,0) -> 139 | J30: =B30-F30 -> -41 | K30: =B30-G30 -> -47 | N30: =B30/B$33*O$33 -> 0 | Y30: =F33 -> 560 | Z30: 400
A31: Bury | B31: =S8+T8 -> 96 | C31: =V8 -> 109 | D31: =C31-B31 -> 13 | F31: =ROUNDUP(C31*1.05,0) -> 115 | G31: =ROUNDUP($C31*1.1,0) -> 120 | J31: =B31-F31 -> -19 | K31: =B31-G31 -> -24 | N31: =B31/B$33*O$33 -> 0 | Y31: =G33 -> 587 | Z31: 500
A32: Rochdale | B32: =S9+T9 -> 97 | C32: =V9 -> 137 | D32: =C32-B32 -> 40 | F32: =F33-F31-F30-F29 -> 142 | G32: =G33-G29-G30-G31 -> 150 | J32: =B32-F32 -> -45 | K32: =B32-G32 -> -53 | N32: =B32/B$33*O$33 -> 0 | X32: =TODAY() -> 46308 | Y32: =H33 -> 0 | Z32: 600
A33: NORTH CDA | B33: =SUM(B29:B32) -> 441 | C33: =SUM(C29:C32) -> 533 | D33: =SUM(D29:D32) -> 92 | F33: =ROUNDUP($C33*1.05,0) -> 560 | G33: =ROUNDUP($C33*1.1,0) -> 587 | J33: =SUM(J29:J32) -> -119 | K33: =SUM(K29:K32) -> -146 | N33: =SUM(N29:N32) -> 0 | O33: =LOOKUP(B33,Y29:Z32)*(B33-C33) -> 0 | X33: 45747
E34: POTENTIAL (£) | F34: =400*(F33-C33) -> 10800 | G34: =500*(G33-C33) -> 27000 | I34: PER WEEK | J34: =-J33/$X$35 -> -1.4875 | K34: =-K33/$X$35 -> -1.825 | X34: =X33-X32 -> -561
A35: Macclesfield | B35: =S11+T11 -> 104 | C35: =V11 -> 129 | D35: =C35-B35 -> 25 | F35: =ROUNDUP(C35*1.05,0) -> 136 | G35: =ROUNDUP($C35*1.1,0) -> 142 | J35: =B35-F35 -> -32 | K35: =B35-G35 -> -38 | N35: =B35/B$39*O$39 -> 0 | X35: =ROUND(X34/7,0) -> -80 | Y35: 0 | Z35: 0
A36: Denton | B36: =S12+T12 -> 107 | C36: =V12 -> 130 | D36: =C36-B36 -> 23 | F36: =ROUNDUP(C36*1.05,0) -> 137 | G36: =ROUNDUP($C36*1.1,0) -> 143 | J36: =B36-F36 -> -30 | K36: =B36-G36 -> -36 | N36: =B36/B$39*O$39 -> 0 | Y36: =F39 -> 583 | Z36: 400
A37: Altrincham | B37: =S13+T13 -> 82 | C37: =V13 -> 113 | D37: =C37-B37 -> 31 | F37: =ROUNDUP(C37*1.05,0) -> 119 | G37: =ROUNDUP($C37*1.1,0) -> 125 | J37: =B37-F37 -> -37 | K37: =B37-G37 -> -43 | N37: =B37/B$39*O$39 -> 0 | Y37: =G39 -> 611 | Z37: 500
A38: Stockport | B38: =S14+T14 -> 161 | C38: =V14 -> 183 | D38: =C38-B38 -> 22 | F38: =F39-F37-F36-F35 -> 191 | G38: =G39-G35-G36-G37 -> 201 | J38: =B38-F38 -> -30 | K38: =B38-G38 -> -40 | N38: =B38/B$39*O$39 -> 0 | Y38: =H39 -> 0 | Z38: 600
A39: SOUTH CDA | B39: =SUM(B35:B38) -> 454 | C39: =SUM(C35:C38) -> 555 | D39: =SUM(D35:D38) -> 101 | F39: =ROUNDUP(C39*1.05,0) -> 583 | G39: =ROUNDUP($C39*1.1,0) -> 611 | J39: =SUM(J35:J38) -> -129 | K39: =SUM(K35:K38) -> -157 | N39: =SUM(N35:N38) -> 0 | O39: =LOOKUP(B39,Y35:Z38)*(B39-C39) -> 0
E40: POTENTIAL (£) | F40: =400*(F39-$C39) -> 11200 | G40: =500*(G39-$C39) -> 28000 | I40: PER WEEK | J40: =-J39/$X$35 -> -1.6125 | K40: =-K39/$X$35 -> -1.9625 | Y40: 0 | Z40: 0
A41: Bradford | B41: =S16+T16 -> 118 | C41: =V16 -> 125 | D41: =C41-B41 -> 7 | F41: =F44-F42-F43 -> 131 | G41: =ROUNDUP($C41*1.1,0) -> 138 | J41: =B41-F41 -> -13 | K41: =B41-G41 -> -20 | N41: =B41/B$44*O$44 -> 0 | Y41: =F44 -> 299 | Z41: 400
A42: Huddersfield | B42: =S17+T17 -> 104 | C42: =V17 -> 114 | D42: =C42-B42 -> 10 | F42: =ROUNDUP(C42*1.05,0) -> 120 | G42: =ROUNDUP($C42*1.1,0) -> 126 | J42: =B42-F42 -> -16 | K42: =B42-G42 -> -22 | N42: =B42/B$44*O$44 -> 0 | Y42: =G44 -> 313 | Z42: 500
A43: Silsden | B43: =S18+T18 -> 44 | C43: =V18 -> 45 | D43: =C43-B43 -> 1 | F43: =ROUNDUP(C43*1.05,0) -> 48 | G43: =G44-G41-G42 -> 49 | J43: =B43-F43 -> -4 | K43: =B43-G43 -> -5 | N43: =B43/B$44*O$44 -> 0 | Y43: =H44 -> 0 | Z43: 600
A44: WY CDA | B44: =SUM(B41:B43) -> 266 | C44: =SUM(C41:C43) -> 284 | D44: =SUM(D41:D43) -> 18 | F44: =ROUNDUP(C44*1.05,0) -> 299 | G44: =ROUNDUP($C44*1.1,0) -> 313 | J44: =SUM(J41:J43) -> -33 | K44: =SUM(K41:K43) -> -47 | N44: =SUM(N41:N43) -> 0 | O44: =LOOKUP(B44,Y40:Z43)*(B44-C44) -> 0
E45: POTENTIAL (£) | F45: =400*(F44-$C44) -> 6000 | G45: =500*(G44-$C44) -> 14500 | I45: PER WEEK | J45: =-J44/$X$35 -> -0.4125 | K45: =-K44/$X$35 -> -0.5875
A47: TOTAL | B47: =B44+B39+B33 -> 1161 | C47: =C44+C39+C33 -> 1372 | D47: =D44+D39+D33 -> 211 | F47: =ROUNDUP(C47*1.05,0) -> 1441 | G47: =ROUNDUP($C47*1.1,0) -> 1510 | J47: =J44+J39+J33 -> -281 | K47: =K44+K39+K33 -> -350 | N47: =N44+N39+N33 -> 0
E48: POTENTIAL (£) | F48: =400*(F47-$C47) -> 27600 | G48: =500*(G47-$C47) -> 69000 | I48: PER WEEK | J48: =-J47/$X$35 -> -3.5125 | K48: =-K47/$X$35 -> -4.375
A51: Q1 - BZ TARGETS
B53: Total | C53: Target | D53: TO GO (100%) | F53: UNREG ORDERS
A54: Salford | B54: 2 | C54: 2 | D54: =C54-B54 -> 0 | F54: 0
A55: Bolton | B55: 1 | C55: 2 | D55: =C55-B55 -> 1 | F55: 0 | I55: 2
A56: Bury | B56: 1 | C56: 2 | D56: =C56-B56 -> 1 | F56: 0
A57: Rochdale | B57: 1 | C57: 2 | D57: =C57-B57 -> 1 | F57: 0
A58: NORTH CDA | B58: =SUM(B54:B57) -> 5 | C58: =SUM(C54:C57) -> 8 | D58: =SUM(D54:D57) -> 3 | F58: =SUM(F54:F57) -> 0
A60: Macclesfield | B60: 1 | C60: 2 | D60: =C60-B60 -> 1 | F60: 0 | I60: 1
A61: Denton | B61: 1 | C61: 2 | D61: =C61-B61 -> 1 | F61: 0
A62: Altrincham | B62: 1 | C62: 2 | D62: =C62-B62 -> 1 | F62: 0
A63: Stockport | B63: 2 | C63: 2 | D63: =C63-B63 -> 0 | F63: 0
A64: SOUTH CDA | B64: =SUM(B60:B63) -> 5 | C64: =SUM(C60:C63) -> 8 | D64: =SUM(D60:D63) -> 3 | F64: =SUM(F60:F63) -> 0
A66: Bradford | B66: 1 | C66: 3 | D66: =C66-B66 -> 2 | F66: 0 | I66: 2
A67: Huddersfield | B67: =S42+T42 -> 0 | C67: 2 | D67: =C67-B67 -> 2 | F67: 0
A68: Silsden | B68: 1 | C68: 1 | D68: =C68-B68 -> 0 | F68: 0
A69: WY CDA | B69: =SUM(B66:B68) -> 2 | C69: =SUM(C66:C68) -> 6 | D69: =SUM(D66:D68) -> 4 | F69: =SUM(F66:F68) -> 0
A72: TOTAL | B72: =B69+B64+B58 -> 12 | C72: =C69+C64+C58 -> 22 | D72: =D69+D64+D58 -> 10 | F72: =F69+F64+F58 -> 0
A75: REGISTRATIONS (NON-COUNTING) | U75: Updated | V75: By
C76: =C4 -> JANUARY | G76: =H4 -> FEBRUARY | K76: =M4 -> MARCH | Q76: TOTAL
C77: Non-Counting Fleet (Reg) | D77: Non-Counting Fleet (Unreg) | E77: Total | F77: Budget | G77: Non-Counting Fleet (Reg) | H77: Non-Counting Fleet (Unreg) | I77: Total | J77: Budget | K77: Non-Counting Fleet (Reg) | L77: Non-Counting Fleet (Unreg) | M77: Total | N77: Budget | Q77: Non-Counting Fleet (Reg) | R77: Non-Counting Fleet (Unreg) | S77: Total | T77: Budget
A78: Salford | C78: 85 | E78: =SUM(C78:D78) -> 85 | F78: 140 | G78: 90 | H78: 0 | I78: =SUM(G78:H78) -> 90 | J78: 82 | K78: 456 | L78: 0 | M78: =SUM(K78:L78) -> 456 | N78: 280 | P78: =B78 -> 0 | Q78: =K78+G78+C78 -> 631 | R78: =L78+H78+D78 -> 0 | S78: =SUM(P78:R78) -> 631 | T78: =N78+J78+F78 -> 502 | U78: 45747 | V78: gb
A79: Bolton | C79: 3 | E79: =SUM(C79:D79) -> 3 | F79: 22 | G79: 0 | I79: =SUM(G79:H79) -> 0 | J79: 9 | K79: 10 | M79: =SUM(K79:L79) -> 10 | N79: 49 | P79: =B79 -> 0 | Q79: =K79+G79+C79 -> 13 | R79: =L79+H79+D79 -> 0 | S79: =SUM(P79:R79) -> 13 | T79: =N79+J79+F79 -> 80 | U79: 45747 | V79: gb
A80: Bury | E80: =SUM(C80:D80) -> 0 | I80: =SUM(G80:H80) -> 0 | M80: =SUM(K80:L80) -> 0 | P80: =B80 -> 0 | Q80: =K80+G80+C80 -> 0 | R80: =L80+H80+D80 -> 0 | S80: =SUM(P80:R80) -> 0 | T80: =N80+J80+F80 -> 0 | U80: 45747 | V80: gb
A81: Rochdale | E81: =SUM(C81:D81) -> 0 | I81: =SUM(G81:H81) -> 0 | M81: =SUM(K81:L81) -> 0 | P81: =B81 -> 0 | Q81: =K81+G81+C81 -> 0 | R81: =L81+H81+D81 -> 0 | S81: =SUM(P81:R81) -> 0 | T81: =N81+J81+F81 -> 0 | U81: 45747 | V81: gb
A82: NORTH CDA | C82: =SUM(C78:C81) -> 88 | D82: =SUM(D78:D81) -> 0 | E82: =SUM(E78:E81) -> 88 | F82: =SUM(F78:F81) -> 162 | G82: =SUM(G78:G81) -> 90 | H82: =SUM(H78:H81) -> 0 | I82: =SUM(I78:I81) -> 90 | J82: =SUM(J78:J81) -> 91 | ... N82: =SUM(N78:N81) -> 329 | P82: =B82 -> 0 | Q82: =SUM(Q78:Q81) -> 644 | R82: =SUM(R78:R81) -> 0 | S82: =SUM(S78:S81) -> 644 | T82: =SUM(T78:T81) -> 582
A83: Macclesfield | C83: ='Regs Q2'!V128 -> 0 | E83: =SUM(C83:D83) -> 0 | I83: =SUM(G83:H83) -> 0 | M83: =SUM(K83:L83) -> 0 | P83: =B83 -> 0 | Q83: =K83+G83+C83 -> 0 | R83: =L83+H83+D83 -> 0 | S83: =SUM(P83:R83) -> 0 | T83: =N83+J83+F83 -> 0 | U83: 45747 | V83: NF
A84: Denton | C84: 29 | E84: =SUM(C84:D84) -> 29 | F84: 25 | G84: 6 | H84: 0 | I84: =SUM(G84:H84) -> 6 | J84: 18 | K84: 36 | L84: 0 | M84: =SUM(K84:L84) -> 36 | N84: 66 | P84: =B84 -> 0 | Q84: =K84+G84+O92+C84 -> 71 | R84: =L84+H84+D84 -> 0 | S84: =SUM(P84:R84) -> 71 | T84: =N84+J84+F84 -> 109 | U84: 45747 | V84: NF
A85: Altrincham | C85: ='Regs Q2'!V130 -> 0 | E85: =SUM(C85:D85) -> 0 | I85: =SUM(G85:H85) -> 0 | M85: =SUM(K85:L85) -> 0 | P85: =B85 -> 0 | Q85: =K85+G85+O93+C85 -> 0 | R85: 0 | S85: =SUM(P85:R85) -> 0 | T85: =N85+J85+F85 -> 0 | U85: 45747 | V85: NF
A86: Stockport | C86: ='Regs Q2'!V131 -> 0 | E86: =SUM(C86:D86) -> 0 | G86: ='Regs Q2'!V108 -> 0 | I86: =SUM(G86:H86) -> 0 | M86: =SUM(K86:L86) -> 0 | P86: =B86 -> 0 | Q86: =K86+G86+C86 -> 0 | R86: =L86+H86+D86 -> 0 | S86: =SUM(P86:R86) -> 0 | T86: =N86+J86+F86 -> 0 | U86: 45747 | V86: NF
A87: SOUTH CDA | C87: =SUM(C83:C86) -> 29 | D87: =SUM(D83:D86) -> 0 | E87: =SUM(E83:E86) -> 29 | F87: =SUM(F83:F86) -> 25 | G87: =SUM(G83:G86) -> 6 | H87: =SUM(H83:H86) -> 0 | I87: =SUM(I83:I86) -> 6 | J87: =SUM(J83:J86) -> 18 | ... N87: =SUM(N83:N86) -> 66 | P87: =B87 -> 0 | Q87: =SUM(Q83:Q86) -> 71 | R87: =SUM(R83:R86) -> 0 | S87: =SUM(S83:S86) -> 71 | T87: =SUM(T83:T86) -> 109
A88: Bradford | C88: 19 | E88: =SUM(C88:D88) -> 19 | F88: 44 | G88: 18 | H88: 0 | I88: =SUM(G88:H88) -> 18 | J88: 19 | K88: 80 | L88: 0 | M88: =SUM(K88:L88) -> 80 | N88: 100 | P88: =B88 -> 0 | Q88: =K88+G88+C88 -> 117 | R88: =L88+H88+D88 -> 0 | S88: =SUM(P88:R88) -> 117 | T88: =N88+J88+F88 -> 163 | U88: 45747 | V88: PS
A89: Huddersfield | E89: =SUM(C89:D89) -> 0 | I89: =SUM(G89:H89) -> 0 | K89: 2 | L89: 0 | M89: =SUM(K89:L89) -> 2 | P89: =B89 -> 0 | Q89: =K89+G89+C89 -> 2 | R89: =L89+H89+D89 -> 0 | S89: =SUM(P89:R89) -> 2 | T89: =N89+J89+F89 -> 0 | U89: 31/033 | V89: PS
A90: Silsden | C90: ='Regs Q2'!V135 -> 0 | E90: =SUM(C90:D90) -> 0 | I90: =SUM(G90:H90) -> 0 | K90: ='Regs Q2'!V89 -> 0 | M90: =SUM(K90:L90) -> 0 | P90: =B90 -> 0 | Q90: =K90+G90+C90 -> 0 | R90: =L90+H90+D90 -> 0 | S90: =SUM(P90:R90) -> 0 | T90: =N90+J90+F90 -> 0 | U90: 45747 | V90: PS
C91: =SUM(C88:C90) -> 19 | D91: =SUM(D88:D90) -> 0 | E91: =SUM(E88:E90) -> 19 | F91: =SUM(F88:F90) -> 44 | G91: =SUM(G88:G90) -> 18 | H91: =SUM(H88:H90) -> 0 | I91: =SUM(I88:I90) -> 18 | J91: =SUM(J88:J90) -> 19 | ... N91: =SUM(N88:N90) -> 100 | P91: =B91 -> 0 | Q91: =SUM(Q88:Q90) -> 119 | R91: =SUM(R88:R90) -> 0 | S91: =SUM(S88:S90) -> 119 | T91: =SUM(T88:T90) -> 163
P92: =B92 -> 0
A94: TOTAL | C94: =C91+C87+C82 -> 136 | D94: =D91+D87+D82 -> 0 | E94: =E91+E87+E82 -> 136 | F94: =F91+F87+F82 -> 231 | G94: =G91+G87+G82 -> 114 | H94: =H91+H87+H82 -> 0 | I94: =I91+I87+I82 -> 114 | J94: =J91+J87+J82 -> 128 | ... N94: =N91+N87+N82 -> 495 | Q94: =Q91+Q87+Q82 -> 834 | R94: =R91+R87+R82 -> 0 | S94: =S91+S87+S82 -> 834 | T94: =T91+T87+T82 -> 854

Sheet Sheet17

Sheet 2024 - Q4
A3: REGISTRATIONS (COUNTING) | Y3: Updated | Z3: By | AA3: REGISTRATIONS (BZ4X) | AU3: Updated | AV3: By
C4: OCTOBER | G4: NOVEMBER | K4: DECEMBER | Q4: TOTAL | AC4: Q2 (PBI) | AF4: Q3 | AJ4: Q4 | AQ4: TOTAL
B5: B/FWD | C5: Counting | D5: Counting Fleet | E5: Total | F5: Target | G5: Counting | H5: Counting Fleet | I5: Total | J5: Target | K5: Counting | L5: Counting Fleet | M5: Total | N5: Target | P5: B/FWD | Q5: Counting | R5: Counting Fleet | S5: Total | T5: Target | U5: TO GO | V5: QTR REGS | W5: TARGET | X5: REGS v TGT | AB5: B/FWD | AC5: BZ Counting (ex-Motab) | AD5: Total | AE5: Target | AF5: BZ Counting (ex-Motab) | AG5: Other EVs (Double Count) Pre-Q4 | AH5: Total | AI5: Target | AJ5: Other EVs (Double Count) | AK5: Uber | AL5: BZ Counting (ex-Motab) | AM5: Total | AN5: Target | AP5: B/FWD | AQ5: Counting (ex-Motab) | AR5: Total | AS5: Target | AT5: TO GO
A6: Salford | B6: =-'2024 - Q3'!U6 -> 70 | C6: 60 | D6: 3 | E6: =SUM(C6:D6) -> 63 | F6: =Targets!H2 -> 34 | G6: 37 | H6: 4 | I6: =SUM(G6:H6) -> 41 | J6: =Targets!I2 -> 40 | K6: 31 | M6: =SUM(K6:L6) -> 31 | N6: =Targets!J2 -> 25 | P6: =B6 -> 70 | Q6: =K6+G6+C6 -> 128 | R6: =L6+H6+D6 -> 7 | S6: =SUM(P6:R6) -> 205 | T6: =N6+J6+F6 -> 99 | U6: =T6-S6 -> -106 | V6: =R6+Q6 -> 135 | W6: =T6 -> 99 | X6: =(Q6+R6)/T6 -> 1.3636364 | Y6: 45663 | Z6: GB Final | AA6: Salford | AB6: =Targets!AC30 -> 5 | AC6: 1 | AD6: =SUM(AC6) -> 1 | AE6: =Targets!T43+Targets!U43 -> 8 | AF6: 1 | AG6: 2 | AH6: =AG6+AF6 -> 3 | AI6: =Targets!V43 -> 1 | AJ6: 2 | AK6: 7 | AM6: =SUM(AJ6:AK6) -> 9 | AN6: =Targets!W43 -> 0 | AP6: =AB6 -> 5 | AQ6: =AM6+AH6+AD6 -> 13 | AR6: =AQ6+AP6 -> 18 | AS6: =AN6+AI6+AE6 -> 9 | AT6: =AS6-AR6 -> -9 | AU6: 45657 | AV6: GB
A7: Bolton | B7: =-'2024 - Q3'!U7 -> -94 | C7: 30 | D7: 0 | E7: =SUM(C7:D7) -> 30 | F7: =Targets!H3 -> 28 | G7: 19 | I7: =SUM(G7:H7) -> 19 | J7: =Targets!I3 -> 37 | K7: 26 | M7: =SUM(K7:L7) -> 26 | N7: =Targets!J3 -> 29 | P7: =B7 -> -94 | Q7: =K7+G7+C7 -> 75 | R7: =L7+H7+D7 -> 0 | S7: =SUM(P7:R7) -> -19 | T7: =N7+J7+F7 -> 94 | U7: =T7-S7 -> 113 | V7: =R7+Q7 -> 75 | W7: =T7 -> 94 | X7: =(Q7+R7)/T7 -> 0.79787234 | Y7: 45663 | Z7: GB Final | AA7: Bolton | AB7: =Targets!AC27 -> 3 | AC7: 0 | AD7: =SUM(AC7) -> 0 | AE7: =Targets!T44+Targets!U44 -> 7 | AF7: 3 | AH7: =AG7+AF7 -> 3 | AI7: =Targets!V44 -> 1 | AM7: =SUM(AJ7:AL7) -> 0 | AN7: =Targets!W44 -> 0 | AP7: =AB7 -> 3 | AQ7: =AM7+AH7+AD7 -> 3 | AR7: =AQ7+AP7 -> 6 | AS7: =AN7+AI7+AE7 -> 8 | AT7: =AS7-AR7 -> 2 | AU7: 45657 | AV7: GB
A8: Bury | B8: =-'2024 - Q3'!U8 -> 6 | C8: 27 | E8: =SUM(C8:D8) -> 27 | F8: =Targets!H4 -> 19 | G8: 31 | I8: =SUM(G8:H8) -> 31 | J8: =Targets!I4 -> 26 | K8: 16 | M8: =SUM(K8:L8) -> 16 | N8: =Targets!J4 -> 20 | P8: =B8 -> 6 | Q8: =K8+G8+C8 -> 74 | R8: =L8+H8+D8 -> 0 | S8: =SUM(P8:R8) -> 80 | T8: =N8+J8+F8 -> 65 | U8: =T8-S8 -> -15 | V8: =R8+Q8 -> 74 | W8: =T8 -> 65 | X8: =(Q8+R8)/T8 -> 1.1384615 | Y8: 45663 | Z8: GB Final | AA8: Bury | AB8: 8 | AC8: 0 | AD8: =SUM(AC8) -> 0 | AE8: =Targets!T45+Targets!U45 -> 5 | AF8: 2 | AG8: 2 | AH8: =AG8+AF8 -> 4 | AI8: =Targets!V45 -> 1 | AL8: 1 | AM8: =SUM(AJ8:AL8) -> 1 | AN8: =Targets!W45 -> 0 | AP8: =AB8 -> 8 | AQ8: =AM8+AH8+AD8 -> 5 | AR8: =AQ8+AP8 -> 13 | AS8: =AN8+AI8+AE8 -> 6 | AT8: =AS8-AR8 -> -7 | AU8: 45657 | AV8: GB
A9: Rochdale | B9: =-'2024 - Q3'!U9 -> 21 | C9: 39 | E9: =SUM(C9:D9) -> 39 | F9: =Targets!H5 -> 26 | G9: 34 | I9: =SUM(G9:H9) -> 34 | J9: =Targets!I5 -> 34 | K9: 24 | M9: =SUM(K9:L9) -> 24 | N9: =Targets!J5 -> 24 | P9: =B9 -> 21 | Q9: =K9+G9+C9 -> 97 | R9: =L9+H9+D9 -> 0 | S9: =SUM(P9:R9) -> 118 | T9: =N9+J9+F9 -> 84 | U9: =T9-S9 -> -34 | V9: =R9+Q9 -> 97 | W9: =T9 -> 84 | X9: =(Q9+R9)/T9 -> 1.1547619 | Y9: 45663 | Z9: GB Final | AA9: Rochdale | AB9: =Targets!AC29 -> 1 | AC9: 1 | AD9: =SUM(AC9) -> 1 | AE9: =Targets!T46+Targets!U46 -> 6 | AF9: 1 | AH9: =AG9+AF9 -> 1 | AI9: =Targets!V46 -> 1 | AM9: =SUM(AJ9:AL9) -> 0 | AN9: =Targets!W46 -> 0 | AP9: =AB9 -> 1 | AQ9: =AM9+AH9+AD9 -> 2 | AR9: =AQ9+AP9 -> 3 | AS9: =AN9+AI9+AE9 -> 7 | AT9: =AS9-AR9 -> 4 | AU9: 45657 | AV9: GB
A10: NORTH CDA | B10: =SUM(B6:B9) -> 3 | C10: =SUM(C6:C9) -> 156 | D10: =SUM(D6:D9) -> 3 | E10: =SUM(E6:E9) -> 159 | F10: =SUM(F6:F9) -> 107 | G10: =SUM(G6:G9) -> 121 | H10: =SUM(H6:H9) -> 4 | I10: =SUM(I6:I9) -> 125 | ... N10: =SUM(N6:N9) -> 98 | P10: =SUM(P6:P9) -> 3 | Q10: =SUM(Q6:Q9) -> 374 | R10: =SUM(R6:R9) -> 7 | S10: =SUM(S6:S9) -> 384 | T10: =SUM(T6:T9) -> 342 | U10: =SUM(U6:U9) -> -42 | V10: =SUM(V6:V9) -> 381 | W10: =SUM(W6:W9) -> 342 | X10: =V10/W10 -> 1.1140351 | Y10: 8750 | AA10: NORTH CDA | AB10: =SUM(AB6:AB9) -> 17 | AC10: =SUM(AC6:AC9) -> 2 | AD10: =SUM(AD6:AD9) -> 2 | AE10: =SUM(AE6:AE9) -> 26 | AF10: =SUM(AF6:AF9) -> 7 | AG10: =SUM(AG6:AG9) -> 4 | AH10: =SUM(AH6:AH9) -> 11 | AI10: =SUM(AI6:AI9) -> 4 | ... AN10: =SUM(AN6:AN9) -> 0 | AP10: =SUM(AP6:AP9) -> 17 | AQ10: =SUM(AQ6:AQ9) -> 23 | AR10: =SUM(AR6:AR9) -> 40 | AS10: =SUM(AS6:AS9) -> 30 | AT10: =SUM(AT6:AT9) -> -10
A11: Macclesfield | B11: =-'2024 - Q3'!U11 -> 16 | C11: 41 | E11: =SUM(C11:D11) -> 41 | F11: =Targets!H7 -> 29 | G11: 25 | I11: =SUM(G11:H11) -> 25 | J11: =Targets!I7 -> 34 | K11: 24 | L11: 8 | M11: =SUM(K11:L11) -> 32 | N11: =Targets!J7 -> 20 | P11: 16 | Q11: =K11+G11+C11 -> 90 | R11: =L11+H11+D11 -> 8 | S11: =SUM(P11:R11) -> 114 | T11: =N11+J11+F11 -> 83 | U11: =T11-S11 -> -31 | V11: =R11+Q11 -> 98 | W11: =T11 -> 83 | X11: =(Q11+R11)/T11 -> 1.1807229 | Y11: 45656 | Z11: NF | AA11: Macclesfield | AB11: =Targets!AC33 -> 6 | AC11: 0 | AD11: =SUM(AC11) -> 0 | AE11: =Targets!T48+Targets!U48 -> 7 | AF11: 1 | AG11: 2 | AH11: =AG11+AF11 -> 3 | AI11: =Targets!V48 -> 1 | AL11: 1 | AM11: =SUM(AJ11:AL11) -> 1 | AN11: =Targets!W48 -> 0 | AP11: =AB11 -> 6 | AQ11: =AM11+AH11+AD11 -> 4 | AR11: =AQ11+AP11 -> 10 | AS11: =AN11+AI11+AE11 -> 8 | AT11: =AS11-AR11 -> -2 | AU11: 45656 | AV11: NF
A12: Denton | B12: =-'2024 - Q3'!U12 -> 4 | C12: 33 | E12: =SUM(C12:D12) -> 33 | F12: =Targets!H8 -> 22 | G12: 35 | H12: 1 | I12: =SUM(G12:H12) -> 36 | J12: =Targets!I8 -> 31 | K12: 37 | L12: 2 | M12: =SUM(K12:L12) -> 39 | N12: =Targets!J8 -> 21 | P12: =B12 -> 4 | Q12: =K12+G12+C12 -> 105 | R12: =L12+H12+D12 -> 3 | S12: =SUM(P12:R12) -> 112 | T12: =N12+J12+F12 -> 74 | U12: =T12-S12 -> -38 | V12: =R12+Q12 -> 108 | W12: =T12 -> 74 | X12: =(Q12+R12)/T12 -> 1.4594595 | Y12: 45656 | Z12: NF | AA12: Denton | AB12: =Targets!AC32 -> 2 | AC12: 0 | AD12: =SUM(AC12) -> 0 | AE12: =Targets!T49+Targets!U49 -> 7 | AF12: 1 | AH12: =AG12+AF12 -> 1 | AI12: =Targets!V49 -> 1 | AJ12: 2 | AM12: =SUM(AJ12:AL12) -> 2 | AN12: =Targets!W49 -> 0 | AP12: =AB12 -> 2 | AQ12: =AM12+AH12+AD12 -> 3 | AR12: =AQ12+AP12 -> 5 | AS12: =AN12+AI12+AE12 -> 8 | AT12: =AS12-AR12 -> 3 | AU12: 45656 | AV12: NF
A13: Altrincham | B13: =-'2024 - Q3'!U13 -> 29 | C13: 35 | E13: =SUM(C13:D13) -> 35 | F13: =Targets!H9 -> 20 | G13: 23 | H13: 0 | I13: =SUM(G13:H13) -> 23 | J13: =Targets!I9 -> 21 | K13: 23 | L13: 1 | M13: =SUM(K13:L13) -> 24 | N13: =Targets!J9 -> 13 | P13: =B13 -> 29 | Q13: =K13+G13+C13 -> 81 | R13: =L13+H13+D13 -> 1 | S13: =SUM(P13:R13) -> 111 | T13: =N13+J13+F13 -> 54 | U13: =T13-S13 -> -57 | V13: =R13+Q13 -> 82 | W13: =T13 -> 54 | X13: =(Q13+R13)/T13 -> 1.5185185 | Y13: 45656 | Z13: NF | AA13: Altrincham | AB13: =Targets!AC31 -> 2 | AC13: 1 | AD13: =SUM(AC13) -> 1 | AE13: =Targets!T50+Targets!U50 -> 5 | AF13: 0 | AG13: 2 | AH13: =AG13+AF13 -> 2 | AI13: =Targets!V50 -> 1 | AK13: 3 | AM13: =SUM(AJ13:AL13) -> 3 | AN13: =Targets!W50 -> 0 | AP13: =AB13 -> 2 | AQ13: =AM13+AH13+AD13 -> 6 | AR13: =AQ13+AP13 -> 8 | AS13: =AN13+AI13+AE13 -> 6 | AT13: =AS13-AR13 -> -2 | AU13: 45656 | AV13: NF
A14: Stockport | B14: =-'2024 - Q3'!U14 -> 1 | C14: 54 | E14: =SUM(C14:D14) -> 54 | F14: =Targets!H10 -> 33 | G14: 47 | I14: =SUM(G14:H14) -> 47 | J14: =Targets!I10 -> 45 | K14: 32 | L14: 6 | M14: =SUM(K14:L14) -> 38 | N14: =Targets!J10 -> 27 | P14: =B14 -> 1 | Q14: =K14+G14+C14 -> 133 | R14: =L14+H14+D14 -> 6 | S14: =SUM(P14:R14) -> 140 | T14: =N14+J14+F14 -> 105 | U14: =T14-S14 -> -35 | V14: =R14+Q14 -> 139 | W14: =T14 -> 105 | X14: =(Q14+R14)/T14 -> 1.3238095 | Y14: 45656 | Z14: NF | AA14: Stockport | AB14: =Targets!AC34 -> 7 | AC14: 1 | AD14: =SUM(AC14) -> 1 | AE14: =Targets!T51+Targets!U51 -> 9 | AF14: 0 | AH14: =AG14+AF14 -> 0 | AI14: =Targets!V51 -> 2 | AK14: 1 | AM14: =SUM(AJ14:AL14) -> 1 | AN14: =Targets!W51 -> 0 | AP14: =AB14 -> 7 | AQ14: =AM14+AH14+AD14 -> 2 | AR14: =AQ14+AP14 -> 9 | AS14: 9 | AT14: =AS14-AR14 -> 0 | AU14: 45656 | AV14: NF
A15: SOUTH CDA | B15: =SUM(B11:B14) -> 50 | C15: =SUM(C11:C14) -> 163 | D15: =SUM(D11:D14) -> 0 | E15: =SUM(E11:E14) -> 163 | F15: =SUM(F11:F14) -> 104 | G15: =SUM(G11:G14) -> 130 | H15: =SUM(H11:H14) -> 1 | I15: =SUM(I11:I14) -> 131 | ... N15: =SUM(N11:N14) -> 81 | P15: =SUM(P11:P14) -> 50 | Q15: =SUM(Q11:Q14) -> 409 | R15: =SUM(R11:R14) -> 18 | S15: =SUM(S11:S14) -> 477 | T15: =SUM(T11:T14) -> 316 | U15: =SUM(U11:U14) -> -161 | V15: =SUM(V11:V14) -> 427 | W15: =SUM(W11:W14) -> 316 | X15: =V15/W15 -> 1.3512658 | Y15: 78000 | AA15: SOUTH CDA | AB15: =SUM(AB11:AB14) -> 17 | AC15: =SUM(AC11:AC14) -> 2 | AD15: =SUM(AD11:AD14) -> 2 | AE15: =SUM(AE11:AE14) -> 28 | AF15: =SUM(AF11:AF14) -> 2 | AG15: =SUM(AG11:AG14) -> 4 | AH15: =SUM(AH11:AH14) -> 6 | AI15: =SUM(AI11:AI14) -> 5 | ... AN15: =SUM(AN11:AN14) -> 0 | AP15: =SUM(AP11:AP14) -> 17 | AQ15: =SUM(AQ11:AQ14) -> 15 | AR15: =SUM(AR11:AR14) -> 32 | AS15: =SUM(AS11:AS14) -> 31 | AT15: =SUM(AT11:AT14) -> -1
A16: Bradford | B16: =-'2024 - Q3'!U16 -> 12 | C16: 30 | D16: 4 | E16: =SUM(C16:D16) -> 34 | F16: =Targets!H12 -> 20 | G16: 21 | H16: 8 | I16: =SUM(G16:H16) -> 29 | J16: =Targets!I12 -> 31 | K16: 17 | L16: 6 | M16: =SUM(K16:L16) -> 23 | N16: =Targets!J12 -> 24 | P16: =B16 -> 12 | Q16: =K16+G16+C16 -> 68 | R16: =L16+H16+D16 -> 18 | S16: =SUM(P16:R16) -> 98 | T16: =N16+J16+F16 -> 75 | U16: =T16-S16 -> -23 | V16: =R16+Q16 -> 86 | W16: =T16 -> 75 | X16: =(Q16+R16)/T16 -> 1.1466667 | Y16: 45657 | Z16: PS | AA16: Bradford | AB16: =Targets!AC35 -> 3 | AC16: 0 | AD16: =SUM(AC16) -> 0 | AE16: =Targets!T53+Targets!U53 -> 6 | AF16: 0 | AH16: =AG16+AF16 -> 0 | AI16: =Targets!V53 -> 1 | AK16: 1 | AL16: 1 | AM16: =SUM(AJ16:AL16) -> 2 | AN16: =Targets!W53 -> 0 | AP16: =AB16 -> 3 | AQ16: =AM16+AH16+AD16 -> 2 | AR16: =AQ16+AP16 -> 5 | AS16: =AN16+AI16+AE16 -> 7 | AT16: =AS16-AR16 -> 2 | AU16: 45657 | AV16: PS
A17: Huddersfield | B17: =-'2024 - Q3'!U17 -> -15 | C17: 34 | D17: 9 | E17: =SUM(C17:D17) -> 43 | F17: =Targets!H13 -> 28 | G17: 36 | H17: 1 | I17: =SUM(G17:H17) -> 37 | J17: =Targets!I13 -> 36 | K17: 31 | M17: =SUM(K17:L17) -> 31 | N17: =Targets!J13 -> 24 | P17: =B17 -> -15 | Q17: =K17+G17+C17 -> 101 | R17: =L17+H17+D17 -> 10 | S17: =SUM(P17:R17) -> 96 | T17: =N17+J17+F17 -> 88 | U17: =T17-S17 -> -8 | V17: =R17+Q17 -> 111 | W17: =T17 -> 88 | X17: =(Q17+R17)/T17 -> 1.2613636 | Y17: 45657 | Z17: PS | AA17: Huddersfield | AB17: =Targets!AC36 -> 4 | AC17: 0 | AD17: =SUM(AC17) -> 0 | AE17: =Targets!T54+Targets!U54 -> 7 | AF17: 2 | AH17: =AG17+AF17 -> 2 | AI17: =Targets!V54 -> 1 | AL17: 1 | AM17: =SUM(AJ17:AL17) -> 1 | AN17: =Targets!W54 -> 0 | AP17: =AB17 -> 4 | AQ17: =AM17+AH17+AD17 -> 3 | AR17: =AQ17+AP17 -> 7 | AS17: =AN17+AI17+AE17 -> 8 | AT17: =AS17-AR17 -> 1 | AU17: 45657 | AV17: PS
A18: Silsden | B18: =-'2024 - Q3'!U18 -> 4 | C18: 15 | D18: 1 | E18: =SUM(C18:D18) -> 16 | F18: =Targets!H14 -> 9 | G18: 14 | I18: =SUM(G18:H18) -> 14 | J18: =Targets!I14 -> 16 | K18: 14 | L18: 2 | M18: =SUM(K18:L18) -> 16 | N18: =Targets!J14 -> 9 | P18: =B18 -> 4 | Q18: =K18+G18+C18 -> 43 | R18: =L18+H18+D18 -> 3 | S18: =SUM(P18:R18) -> 50 | T18: =N18+J18+F18 -> 34 | U18: =T18-S18 -> -16 | V18: =R18+Q18 -> 46 | W18: =T18 -> 34 | X18: =(Q18+R18)/T18 -> 1.3529412 | Y18: 45657 | Z18: PS | AA18: Silsden | AB18: =Targets!AC37 -> 1 | AC18: 1 | AD18: =SUM(AC18) -> 1 | AE18: =Targets!T55+Targets!U55 -> 2 | AF18: 0 | AH18: =AG18+AF18 -> 0 | AI18: =Targets!V55 -> 1 | AL18: 2 | AM18: =SUM(AJ18:AL18) -> 2 | AN18: =Targets!W55 -> 0 | AP18: =AB18 -> 1 | AQ18: =AM18+AH18+AD18 -> 3 | AR18: =AQ18+AP18 -> 4 | AS18: =AN18+AI18+AE18 -> 3 | AT18: =AS18-AR18 -> -1 | AU18: 45657 | AV18: PS
A19: WY CDA | B19: =SUM(B16:B18) -> 1 | C19: =SUM(C16:C18) -> 79 | D19: =SUM(D16:D18) -> 14 | E19: =SUM(E16:E18) -> 93 | F19: =SUM(F16:F18) -> 57 | G19: =SUM(G16:G18) -> 71 | H19: =SUM(H16:H18) -> 9 | I19: =SUM(I16:I18) -> 80 | ... N19: =SUM(N16:N18) -> 57 | P19: =SUM(P16:P18) -> 1 | Q19: =SUM(Q16:Q18) -> 212 | R19: =SUM(R16:R18) -> 31 | S19: =SUM(S16:S18) -> 244 | T19: =SUM(T16:T18) -> 197 | U19: =SUM(U16:U18) -> -47 | V19: =SUM(V16:V18) -> 243 | W19: =SUM(W16:W18) -> 197 | X19: =V19/W19 -> 1.2335025 | Y19: 21500 | AA19: WY CDA | AB19: =SUM(AB16:AB18) -> 8 | AC19: =SUM(AC16:AC18) -> 1 | AD19: =SUM(AD16:AD18) -> 1 | AE19: =SUM(AE16:AE18) -> 15 | AF19: =SUM(AF16:AF18) -> 2 | AG19: =SUM(AG16:AG18) -> 0 | AH19: =SUM(AH16:AH18) -> 2 | AI19: =SUM(AI16:AI18) -> 3 | ... AN19: =SUM(AN16:AN18) -> 0 | AP19: =SUM(AP16:AP18) -> 8 | AQ19: =SUM(AQ16:AQ18) -> 8 | AR19: =SUM(AR16:AR18) -> 16 | AS19: =SUM(AS16:AS18) -> 18 | AT19: =SUM(AT16:AT18) -> 2
O20: `
A22: TOTAL | B22: =B19+B15+B10 -> 54 | C22: =C19+C15+C10 -> 398 | D22: =D19+D15+D10 -> 17 | E22: =E19+E15+E10 -> 415 | F22: =F19+F15+F10 -> 268 | G22: =G19+G15+G10 -> 322 | H22: =H19+H15+H10 -> 14 | I22: =I19+I15+I10 -> 336 | ... N22: =N19+N15+N10 -> 236 | P22: =P19+P15+P10 -> 54 | Q22: =Q19+Q15+Q10 -> 995 | R22: =R19+R15+R10 -> 56 | S22: =S19+S15+S10 -> 1105 | T22: =T19+T15+T10 -> 855 | U22: =U19+U15+U10 -> -250 | V22: =V19+V15+V10 -> 1051 | W22: =W19+W15+W10 -> 855 | X22: =(Q22+R22)/T22 -> 1.2292398 | Y22: 91000 | AA22: TOTAL | AB22: =AB19+AB15+AB10 -> 42 | AC22: =AC19+AC15+AC10 -> 5 | AD22: =AD19+AD15+AD10 -> 5 | AE22: =AE19+AE15+AE10 -> 69 | AF22: =AF19+AF15+AF10 -> 11 | AG22: =AG19+AG15+AG10 -> 8 | AH22: =AH19+AH15+AH10 -> 19 | AI22: =AI19+AI15+AI10 -> 12 | ... AN22: =AN19+AN15+AN10 -> 0 | AP22: =AP19+AP15+AP10 -> 42 | AQ22: =AQ19+AQ15+AQ10 -> 46 | AR22: =AR19+AR15+AR10 -> 88 | AS22: =AS19+AS15+AS10 -> 79 | AT22: =AT19+AT15+AT10 -> -9
A24: REGISTRATIONS (NON-COUNTING) | Y24: Updated | Z24: By | AA24: B/FWD | AB24: =AB22 -> 42 | AD24: =AD22 -> 5 | AH24: =AH22 -> 19 | AI24: =SUM(AB24:AH24) -> 66
C25: OCTOBER | G25: NOVEMBER | K25: DECEMBER | Q25: TOTAL | V25: 1112 | W25: =V25-V22 -> 61
C26: Non-Counting Fleet (Reg) | D26: Non-Counting Fleet (Unreg) | E26: Total | F26: Budget | G26: Non-Counting Fleet (Reg) | H26: Non-Counting Fleet (Unreg) | I26: Total | J26: Budget | K26: Non-Counting Fleet (Reg) | L26: Non-Counting Fleet (Unreg) | M26: Total | N26: Budget | Q26: Non-Counting Fleet (Reg) | R26: Non-Counting Fleet (Unreg) | S26: Total | T26: Budget | V26: =445-374 -> 71 | W26: North | AO26: `
A27: Salford | C27: 90 | D27: 0 | E27: =SUM(C27:D27) -> 90 | F27: 155 | G27: 135 | I27: =SUM(G27:H27) -> 135 | J27: 115 | K27: 194 | M27: =SUM(K27:L27) -> 194 | N27: 110 | P27: =B27 -> 0 | Q27: =K27+G27+C27 -> 419 | R27: =L27+H27+D27 -> 0 | S27: =SUM(P27:R27) -> 419 | T27: =N27+J27+F27 -> 380 | V27: 2 | W27: South | Y27: 45657 | Z27: GB | AO27: Not taxed
A28: Bolton | C28: 12 | D28: 0 | E28: =SUM(C28:D28) -> 12 | F28: 28 | G28: 19 | I28: =SUM(G28:H28) -> 19 | J28: 13 | K28: 32 | M28: =SUM(K28:L28) -> 32 | N28: 16 | P28: =B28 -> 0 | Q28: =K28+G28+C28 -> 63 | R28: =L28+H28+D28 -> 0 | S28: =SUM(P28:R28) -> 63 | T28: =N28+J28+F28 -> 57 | V28: =256-238 -> 18 | W28: WY | Y28: 45657 | Z28: GB | AO28: Salford | AR28: 3
A29: Bury | E29: =SUM(C29:D29) -> 0 | I29: =SUM(G29:H29) -> 0 | M29: =SUM(K29:L29) -> 0 | P29: =B29 -> 0 | Q29: =K29+G29+C29 -> 0 | R29: =L29+H29+D29 -> 0 | S29: =SUM(P29:R29) -> 0 | T29: =N29+J29+F29 -> 0 | Y29: 45657 | Z29: GB | AO29: Altrincham | AR29: 3
A30: Rochdale | E30: =SUM(C30:D30) -> 0 | I30: =SUM(G30:H30) -> 0 | M30: =SUM(K30:L30) -> 0 | P30: =B30 -> 0 | Q30: =K30+G30+C30 -> 0 | R30: =L30+H30+D30 -> 0 | S30: =SUM(P30:R30) -> 0 | T30: =N30+J30+F30 -> 0 | Y30: 45657 | Z30: GB | AO30: Bury | AR30: 1
A31: NORTH CDA | C31: =SUM(C27:C30) -> 102 | D31: =SUM(D27:D30) -> 0 | E31: =SUM(E27:E30) -> 102 | F31: =SUM(F27:F30) -> 183 | G31: =SUM(G27:G30) -> 154 | H31: =SUM(H27:H30) -> 0 | I31: =SUM(I27:I30) -> 154 | J31: =SUM(J27:J30) -> 128 | ... N31: =SUM(N27:N30) -> 126 | P31: =B31 -> 0 | Q31: =SUM(Q27:Q30) -> 482 | R31: =SUM(R27:R30) -> 0 | S31: =SUM(S27:S30) -> 482 | T31: =SUM(T27:T30) -> 437 | AO31: Silsden | AR31: 2
A32: Macclesfield | C32: ='Regs Q2'!V77 -> 0 | E32: =SUM(C32:D32) -> 0 | G32: ='Regs Q2'!V54 -> 0 | I32: =SUM(G32:H32) -> 0 | K32: ='Regs Q2'!V31 -> 0 | M32: =SUM(K32:L32) -> 0 | P32: =B32 -> 0 | Q32: =K32+G32+C32 -> 0 | R32: =L32+H32+D32 -> 0 | S32: =SUM(P32:R32) -> 0 | T32: =N32+J32+F32 -> 0 | Y32: 45656 | Z32: NF | AR32: =SUM(AR28:AR31) -> 9
A33: Denton | C33: 24 | D33: 0 | E33: =SUM(C33:D33) -> 24 | F33: 33 | G33: 46 | H33: 0 | I33: =SUM(G33:H33) -> 46 | J33: 26 | K33: 66 | L33: 4 | M33: =SUM(K33:L33) -> 70 | N33: 46 | P33: =B33 -> 0 | Q33: =K33+G33+O41+C33 -> 136 | R33: =L33+H33+D33 -> 4 | S33: =SUM(P33:R33) -> 140 | T33: =N33+J33+F33 -> 105 | Y33: 45656 | Z33: NF | AO33: Power BI (26.11) | AQ33: 81 | AR33: =AR22-AR32 -> 79 | AS33: =AQ33-AR33 -> 2
A34: Altrincham | C34: ='Regs Q2'!V79 -> 0 | E34: =SUM(C34:D34) -> 0 | G34: ='Regs Q2'!V56 -> 0 | I34: =SUM(G34:H34) -> 0 | K34: ='Regs Q2'!V33 -> 0 | M34: =SUM(K34:L34) -> 0 | P34: =B34 -> 0 | Q34: =K34+G34+O42+C34 -> 0 | R34: 0 | S34: =SUM(P34:R34) -> 0 | T34: =N34+J34+F34 -> 0 | Y34: 45656 | Z34: NF | AS34: CHECK
A35: Stockport | C35: ='Regs Q2'!V80 -> 0 | E35: =SUM(C35:D35) -> 0 | G35: ='Regs Q2'!V57 -> 0 | I35: =SUM(G35:H35) -> 0 | K35: ='Regs Q2'!V34 -> 0 | M35: =SUM(K35:L35) -> 0 | P35: =B35 -> 0 | Q35: =K35+G35+C35 -> 0 | R35: =L35+H35+D35 -> 0 | S35: =SUM(P35:R35) -> 0 | T35: =N35+J35+F35 -> 0 | Y35: 45656 | Z35: NF
A36: SOUTH CDA | C36: =SUM(C32:C35) -> 24 | D36: =SUM(D32:D35) -> 0 | E36: =SUM(E32:E35) -> 24 | F36: =SUM(F32:F35) -> 33 | G36: =SUM(G32:G35) -> 46 | H36: =SUM(H32:H35) -> 0 | I36: =SUM(I32:I35) -> 46 | J36: =SUM(J32:J35) -> 26 | ... N36: =SUM(N32:N35) -> 46 | P36: =B36 -> 0 | Q36: =SUM(Q32:Q35) -> 136 | R36: =SUM(R32:R35) -> 4 | S36: =SUM(S32:S35) -> 140 | T36: =SUM(T32:T35) -> 105
A37: Bradford | C37: 42 | D37: 0 | E37: =SUM(C37:D37) -> 42 | F37: 61 | G37: 23 | H37: 0 | I37: =SUM(G37:H37) -> 23 | J37: 52 | K37: 75 | L37: 0 | M37: =SUM(K37:L37) -> 75 | N37: 40 | P37: =B37 -> 0 | Q37: =K37+G37+C37 -> 140 | R37: =L37+H37+D37 -> 0 | S37: =SUM(P37:R37) -> 140 | T37: =N37+J37+F37 -> 153 | Y37: 45657 | Z37: PS
A38: Huddersfield | C38: ='Regs Q2'!V83 -> 0 | D38: 0 | E38: =SUM(C38:D38) -> 0 | H38: 0 | I38: =SUM(G38:H38) -> 0 | L38: 0 | M38: =SUM(K38:L38) -> 0 | P38: =B38 -> 0 | Q38: =K38+G38+C38 -> 0 | R38: =L38+H38+D38 -> 0 | S38: =SUM(P38:R38) -> 0 | T38: =N38+J38+F38 -> 0 | Y38: 45657 | Z38: PS
A39: Silsden | C39: ='Regs Q2'!V84 -> 0 | E39: =SUM(C39:D39) -> 0 | I39: =SUM(G39:H39) -> 0 | K39: ='Regs Q2'!V38 -> 0 | M39: =SUM(K39:L39) -> 0 | P39: =B39 -> 0 | Q39: =K39+G39+C39 -> 0 | R39: =L39+H39+D39 -> 0 | S39: =SUM(P39:R39) -> 0 | T39: =N39+J39+F39 -> 0 | Y39: 45657 | Z39: PS
C40: =SUM(C37:C39) -> 42 | D40: =SUM(D37:D39) -> 0 | E40: =SUM(E37:E39) -> 42 | F40: =SUM(F37:F39) -> 61 | G40: =SUM(G37:G39) -> 23 | H40: =SUM(H37:H39) -> 0 | I40: =SUM(I37:I39) -> 23 | J40: =SUM(J37:J39) -> 52 | ... N40: =SUM(N37:N39) -> 40 | P40: =B40 -> 0 | Q40: =SUM(Q37:Q39) -> 140 | R40: =SUM(R37:R39) -> 0 | S40: =SUM(S37:S39) -> 140 | T40: =SUM(T37:T39) -> 153
P41: =B41 -> 0
A43: TOTAL | C43: =C40+C36+C31 -> 168 | D43: =D40+D36+D31 -> 0 | E43: =E40+E36+E31 -> 168 | F43: =F40+F36+F31 -> 277 | G43: =G40+G36+G31 -> 223 | H43: =H40+H36+H31 -> 0 | I43: =I40+I36+I31 -> 223 | J43: =J40+J36+J31 -> 206 | ... N43: =N40+N36+N31 -> 212 | Q43: =Q40+Q36+Q31 -> 758 | R43: =R40+R36+R31 -> 4 | S43: =S40+S36+S31 -> 762 | T43: =T40+T36+T31 -> 695
K45: =K43+K22+L22 -> 667

Sheet Sheet11

Sheet Regs Q1-Q4
C3: COUNTING REGS - Q1
C4: PRI | D4: OR | E4: MOT | F4: CSS (CBS) | G4: DEM | H4: KIN | I4: CF | M4: BUS | N4: TOTAL | O4: NON-COUNTING | P4: TOTAL REGS
B6: Salford | C6: 97 | D6: 0 | E6: 41 | F6: 20 | G6: 4 | H6: 34 | I6: 2 | M6: 1 | N6: =SUM(C6:M6) -> 199 | O6: =333+30 -> 363 | P6: =SUM(N6:O6) -> 562
B7: Bolton | C7: 58 | D7: 0 | E7: 52 | F7: 4 | G7: 3 | H7: 5 | I7: 7 | M7: 1 | N7: =SUM(C7:M7) -> 130 | O7: 50 | P7: =SUM(N7:O7) -> 180
B8: Bury | C8: 53 | D8: 0 | E8: 20 | F8: 14 | G8: 4 | H8: 3 | I8: 0 | M8: 2 | N8: =SUM(C8:M8) -> 96 | P8: =SUM(N8:O8) -> 96
B9: Rochdale | C9: 74 | D9: 0 | E9: 50 | F9: 18 | G9: 5 | H9: 0 | I9: 1 | M9: 1 | N9: =SUM(C9:M9) -> 149 | P9: =SUM(N9:O9) -> 149
B10: NORTH CDA | C10: =SUM(C6:C9) -> 282 | D10: =SUM(D6:D9) -> 0 | E10: =SUM(E6:E9) -> 163 | F10: =SUM(F6:F9) -> 56 | G10: =SUM(G6:G9) -> 16 | H10: =SUM(H6:H9) -> 42 | I10: =SUM(I6:I9) -> 10 | M10: =SUM(M6:M9) -> 5 | N10: =SUM(N6:N9) -> 574 | O10: =SUM(O6:O9) -> 413 | P10: =SUM(P6:P9) -> 987
B11: Macclesfield | C11: 116 | D11: 0 | E11: 14 | F11: 7 | G11: 4 | H11: 1 | I11: 1 | M11: 1 | N11: =SUM(C11:M11) -> 144 | O11: 1 | P11: =SUM(N11:O11) -> 145
B12: Denton | C12: 74 | D12: 0 | E12: 22 | F12: 13 | G12: 8 | H12: 2 | I12: 6 | M12: 1 | N12: =SUM(C12:M12) -> 126 | O12: 134 | P12: =SUM(N12:O12) -> 260
B13: Altrincham | C13: 77 | D13: 0 | E13: 22 | F13: 3 | G13: 5 | H13: 1 | I13: 0 | M13: 0 | N13: =SUM(C13:M13) -> 108 | P13: =SUM(N13:O13) -> 108
B14: Stockport | C14: 105 | D14: 0 | E14: 44 | F14: 3 | G14: 8 | H14: 1 | I14: 0 | M14: 0 | N14: =SUM(C14:M14) -> 161 | P14: =SUM(N14:O14) -> 161
B15: SOUTH CDA | C15: =SUM(C11:C14) -> 372 | D15: =SUM(D11:D14) -> 0 | E15: =SUM(E11:E14) -> 102 | F15: =SUM(F11:F14) -> 26 | G15: =SUM(G11:G14) -> 25 | H15: =SUM(H11:H14) -> 5 | I15: =SUM(I11:I14) -> 7 | M15: =SUM(M11:M14) -> 2 | N15: =SUM(N11:N14) -> 539 | O15: =SUM(O11:O14) -> 135 | P15: =SUM(P11:P14) -> 674
B16: Bradford | C16: 51 | D16: 0 | E16: 32 | F16: 4 | G16: 5 | H16: 35 | I16: 0 | M16: 4 | N16: =SUM(C16:M16) -> 131 | O16: 180 | P16: =SUM(N16:O16) -> 311
B17: Huddersfield | C17: 55 | D17: 1 | E17: 38 | F17: 15 | G17: 3 | H17: 0 | I17: 0 | M17: 1 | N17: =SUM(C17:M17) -> 113 | P17: =SUM(N17:O17) -> 113
B18: Silsden | C18: 28 | D18: 0 | E18: 8 | F18: 2 | G18: 5 | H18: 0 | I18: 0 | M18: 3 | N18: =SUM(C18:M18) -> 46 | O18: 3 | P18: =SUM(N18:O18) -> 49
B19: WY CDA | C19: =SUM(C16:C18) -> 134 | D19: =SUM(D16:D18) -> 1 | E19: =SUM(E16:E18) -> 78 | F19: =SUM(F16:F18) -> 21 | G19: =SUM(G16:G18) -> 13 | H19: =SUM(H16:H18) -> 35 | I19: =SUM(I16:I18) -> 0 | M19: =SUM(M16:M18) -> 8 | N19: =SUM(N16:N18) -> 290 | O19: =SUM(O16:O18) -> 183 | P19: =SUM(P16:P18) -> 473
B22: TOTAL | C22: =C19+C15+C10 -> 788 | D22: =D19+D15+D10 -> 1 | E22: =E19+E15+E10 -> 343 | F22: =F19+F15+F10 -> 103 | G22: =G19+G15+G10 -> 54 | H22: =H19+H15+H10 -> 82 | I22: =I19+I15+I10 -> 17 | M22: =M19+M15+M10 -> 15 | N22: =N19+N15+N10 -> 1403 | O22: =O19+O15+O10 -> 731 | P22: =P19+P15+P10 -> 2134 | R22: 834
C25: COUNTING REGS - Q2
C26: PRI | D26: OR | E26: MOT | F26: CSS (CBS) | G26: DEM | H26: KIN | I26: CF | M26: BUS | N26: TOTAL | O26: NON-COUNTING | P26: TOTAL REGS
B28: Salford | C28: 92 | E28: 36 | F28: 16 | G28: 6 | H28: 5 | M28: 2 | N28: =SUM(C28:M28) -> 157 | O28: 303 | P28: =SUM(N28:O28) -> 460
B29: Bolton | C29: 73 | E29: 26 | F29: 8 | G29: 3 | H29: 3 | I29: 2 | N29: =SUM(C29:M29) -> 115 | O29: 39 | P29: =SUM(N29:O29) -> 154
B30: Bury | C30: 63 | E30: 15 | F30: 7 | G30: 5 | H30: 1 | M30: 1 | N30: =SUM(C30:M30) -> 92 | P30: =SUM(N30:O30) -> 92
B31: Rochdale | C31: 71 | E31: 32 | F31: 8 | G31: 2 | H31: 1 | N31: =SUM(C31:M31) -> 114 | P31: =SUM(N31:O31) -> 114
B32: NORTH CDA | C32: =SUM(C28:C31) -> 299 | D32: =SUM(D28:D31) -> 0 | E32: =SUM(E28:E31) -> 109 | F32: =SUM(F28:F31) -> 39 | G32: =SUM(G28:G31) -> 16 | H32: =SUM(H28:H31) -> 10 | I32: =SUM(I28:I31) -> 2 | M32: =SUM(M28:M31) -> 3 | N32: =SUM(N28:N31) -> 478 | O32: =SUM(O28:O31) -> 342 | P32: =SUM(P28:P31) -> 820
B33: Macclesfield | C33: 86 | E33: 12 | F33: 1 | G33: 5 | H33: 1 | M33: 2 | N33: =SUM(C33:M33) -> 107 | P33: =SUM(N33:O33) -> 107
B34: Denton | C34: 73 | E34: 24 | F34: 11 | G34: 2 | H34: 3 | N34: =SUM(C34:M34) -> 113 | O34: 73 | P34: =SUM(N34:O34) -> 186
B35: Altrincham | C35: 81 | E35: 22 | F35: 6 | G35: 4 | H35: 1 | N35: =SUM(C35:M35) -> 114 | P35: =SUM(N35:O35) -> 114
B36: Stockport | C36: 117 | E36: 26 | F36: 8 | G36: 3 | M36: 2 | N36: =SUM(C36:M36) -> 156 | P36: =SUM(N36:O36) -> 156
B37: SOUTH CDA | C37: =SUM(C33:C36) -> 357 | D37: =SUM(D33:D36) -> 0 | E37: =SUM(E33:E36) -> 84 | F37: =SUM(F33:F36) -> 26 | G37: =SUM(G33:G36) -> 14 | H37: =SUM(H33:H36) -> 5 | I37: =SUM(I33:I36) -> 0 | M37: =SUM(M33:M36) -> 4 | N37: =SUM(N33:N36) -> 490 | O37: =SUM(O33:O36) -> 73 | P37: =SUM(P33:P36) -> 563
B38: Bradford | C38: 52 | E38: 24 | F38: 4 | G38: 6 | H38: 39 | M38: 2 | N38: =SUM(C38:M38) -> 127 | O38: 139 | P38: =SUM(N38:O38) -> 266
B39: Huddersfield | C39: 62 | E39: 28 | F39: 11 | G39: 8 | H39: 1 | M39: 2 | N39: =SUM(C39:M39) -> 112 | P39: =SUM(N39:O39) -> 112
B40: Silsden | C40: 38 | E40: 4 | F40: 3 | G40: 1 | M40: 1 | N40: =SUM(C40:M40) -> 47 | O40: 1 | P40: =SUM(N40:O40) -> 48
B41: WY CDA | C41: =SUM(C38:C40) -> 152 | D41: =SUM(D38:D40) -> 0 | E41: =SUM(E38:E40) -> 56 | F41: =SUM(F38:F40) -> 18 | G41: =SUM(G38:G40) -> 15 | H41: =SUM(H38:H40) -> 40 | I41: =SUM(I38:I40) -> 0 | M41: =SUM(M38:M40) -> 5 | N41: =SUM(N38:N40) -> 286 | O41: =SUM(O38:O40) -> 140 | P41: =SUM(P38:P40) -> 426
B44: TOTAL | C44: =C41+C37+C32 -> 808 | D44: =D41+D37+D32 -> 0 | E44: =E41+E37+E32 -> 249 | F44: =F41+F37+F32 -> 83 | G44: =G41+G37+G32 -> 45 | H44: =H41+H37+H32 -> 55 | I44: =I41+I37+I32 -> 2 | M44: =M41+M37+M32 -> 12 | N44: =N41+N37+N32 -> 1254 | O44: =O41+O37+O32 -> 555 | P44: =P41+P37+P32 -> 1809 | R44: 618
C47: COUNTING REGS - Q3
C48: PRI | D48: OR | E48: MOT | F48: CSS (CBS) | G48: DEM | H48: KIN | I48: CF | M48: BUS | N48: TOTAL | O48: NON-COUNTING | P48: TOTAL REGS
B50: Salford | C50: 89 | E50: 47 | F50: 25 | G50: 8 | H50: 2 | I50: 1 | M50: 1 | N50: =SUM(C50:M50) -> 173 | O50: 503 | P50: =SUM(N50:O50) -> 676
